Workbook
Name NativeTimeline_Leased_Date: #N/A
Name Scenario: #REF!
Name Slicer_Baths: #N/A
Name Slicer_Beds: #N/A
Name Slicer_Beds1: #N/A
Name Slicer_Property_Name: #N/A
Name Slicer_Property_Name1: #N/A

Sheet Intro
B7: Click "Enable Editing" to update.
B9: Table of Contents
B11: 1 | C11: Weekly Market Updates
B12: 2 | C12: 30-Day Trends
B13: 3 | C13: Data Analysis
B14: 4 | C14: Leasing Trends
B15: 5 | C15: Rent Comps
B16: 6 | C16: Rent Comparison
B17: 7 | C17: Rents by Unit Type
B18: 8 | C18: Unit-Level Data
B19: 9 | C19: Unit Mix
B20: 10 | C20: Reviews Analysis
B21: 11 | C21: Fees & Amenities
B22: 12 | C22: Specials
B24: © 2025 Hello Data, Inc. All rights reserved.
B25: This spreadsheet and its contents are proprietary and confidential. Unauthorized reproduction, distribution, or use of this template, including for the development of competing software products or services, is strictly prohibited.

Sheet Weekly Market Updates
B2: Weekly Market Updates | P2: Week Ending: | Q2: 45978
B3: Note: Delta (△) figures show change from previous 7-day period.
B5: Property | C5: Active Concessions | E5: Type | F5: # Leased | G5: △ | H5: Leased Rents | I5: $△ | J5: %△ | K5: # New | L5: △ | M5: New Listing Rents | N5: # Active | O5: △ | P5: Asking Rents | Q5: Exposure
B6: =IF(OFFSET('Rent Comparison'!$A$1,2,2)="{{subject.building_name}}","",IF(OFFSET('Rent Comparison'!$A$1,2,2)=0,B7,OFFSET('Rent Comparison'!$A$1,2,2))) -> Grand Mesa Flats | C6: =IF(ISBLANK(B6),"",IFERROR(INDEX(Specials!B:J,MATCH(B6&" - Active",Specials!I:I,0),2),"")) | E6: Studio | F6: =COUNTIFS(unit_details[Leased Date], ">=" & ($Q$2 - 7), unit_details[Leased Date], "<" & $Q$2, unit_details[Beds], 0, unit_details[Property Name], B6) -> 0 | G6: =COUNTIFS(unit_details[Leased Date], ">=" & ($Q$2 - 7), unit_details[Leased Date], "<" & $Q$2, unit_details[Beds], 0, unit_details[Property Name], B6) - COUNTIFS(unit_details[Leased Date], ">=" & ($Q$2 - 14), unit_details[Leased Date], "<=" & ($Q$2 - 7), unit_details[Beds], 0, unit_details[Property Name], B6) -> 0 | H6: =IFERROR(AVERAGEIFS( unit_details[Asking Rent], unit_details[Leased Date], ">=" & ($Q$2 - 7), unit_details[Leased Date], "<" & $Q$2, unit_details[Beds], 0, unit_details[Property Name], B6),"") | I6: =IFERROR( AVERAGEIFS(unit_details[Asking Rent], unit_details[Leased Date], ">=" & ($Q$2 - 7), unit_details[Leased Date], "<" & $Q$2, unit_details[Beds], 0, unit_details[Property Name], B6) - AVERAGEIFS(unit_details[Asking Rent], unit_details[Leased Date], ">=" & ($Q$2 - 14), unit_details[Leased Date], "<=" & ($Q$2 - 7), unit_details[Beds], 0, unit_details[Property Name], B6), 0) -> 0 | J6: =IFERROR(I6/AVERAGEIFS(unit_details[Asking Rent], unit_details[Leased Date], ">=" & ($Q$2 - 14), unit_details[Leased Date], "<=" & ($Q$2 - 7), unit_details[Beds], 0, unit_details[Property Name], B6),0) -> 0 | K6: =COUNTIFS(unit_details[First Listed], ">=" & ($Q$2 - 7), unit_details[First Listed], "<" & $Q$2, unit_details[Beds], 0, unit_details[Property Name], B6) -> 0 | L6: =COUNTIFS( unit_details[First Listed], ">=" & ($Q$2 - 7), unit_details[First Listed], "<" & $Q$2, unit_details[Beds], 0, unit_details[Property Name], B6 ) - COUNTIFS( unit_details[First Listed], ">=" & ($Q$2 - 14), unit_details[First Listed], "<=" & ($Q$2 - 7), unit_details[Beds], 0, unit_details[Property Name], B6 ) -> 0 | M6: =IFERROR(AVERAGEIFS(unit_details[Asking Rent],unit_details[First Listed],">="&($Q$2-7), unit_details[First Listed],"<="&$Q$2, unit_details[Beds],0, unit_details[Property Name],B6),"") | N6: =COUNTIFS(unit_details[Property Name], B6, unit_details[Beds], 0, unit_details[Leased Date], "") -> 0 | O6: =N6-(N6-K6+F6) -> 0 | P6: =IFERROR(AVERAGEIFS(unit_details[Asking Rent],unit_details[Property Name], B6, unit_details[Beds], 0, unit_details[Leased Date], ""),"") | Q6: =IFERROR(N6/SUMIFS(unit_mix_table['# Units],unit_mix_table[Beds],0,unit_mix_table[Property Name],B6),"")
B7: 1681 Rodeo Way, Delta, CO 81416 | E7: 1 BR | F7: =COUNTIFS(unit_details[Leased Date], ">=" & ($Q$2 - 7), unit_details[Leased Date], "<" & $Q$2, unit_details[Beds], 1, unit_details[Property Name], B6) -> 0 | G7: =COUNTIFS(unit_details[Leased Date], ">=" & ($Q$2 - 7), unit_details[Leased Date], "<" & $Q$2, unit_details[Beds], 1, unit_details[Property Name], B6) - COUNTIFS(unit_details[Leased Date], ">=" & ($Q$2 - 14), unit_details[Leased Date], "<=" & ($Q$2 - 7), unit_details[Beds], 1, unit_details[Property Name], B6) -> 0 | H7: =IFERROR(AVERAGEIFS( unit_details[Asking Rent], unit_details[Leased Date], ">=" & ($Q$2 - 7), unit_details[Leased Date], "<" & $Q$2, unit_details[Beds], 1, unit_details[Property Name], B6),"") | I7: =IFERROR( AVERAGEIFS(unit_details[Asking Rent], unit_details[Leased Date], ">=" & ($Q$2 - 7), unit_details[Leased Date], "<" & $Q$2, unit_details[Beds], 1, unit_details[Property Name], B6) - AVERAGEIFS(unit_details[Asking Rent], unit_details[Leased Date], ">=" & ($Q$2 - 14), unit_details[Leased Date], "<=" & ($Q$2 - 7), unit_details[Beds], 1, unit_details[Property Name], B6), 0) -> 0 | J7: =IFERROR(I7/AVERAGEIFS(unit_details[Asking Rent], unit_details[Leased Date], ">=" & ($Q$2 - 14), unit_details[Leased Date], "<=" & ($Q$2 - 7), unit_details[Beds], 1, unit_details[Property Name], B6),0) -> 0 | K7: =COUNTIFS(unit_details[First Listed], ">=" & ($Q$2 - 7), unit_details[First Listed], "<" & $Q$2, unit_details[Beds], 1, unit_details[Property Name], B6) -> 0 | L7: =COUNTIFS( unit_details[First Listed], ">=" & ($Q$2 - 7), unit_details[First Listed], "<" & $Q$2, unit_details[Beds], 1, unit_details[Property Name], B6 ) - COUNTIFS( unit_details[First Listed], ">=" & ($Q$2 - 14), unit_details[First Listed], "<=" & ($Q$2 - 7), unit_details[Beds], 1, unit_details[Property Name], B6 ) -> 0 | M7: =IFERROR(AVERAGEIFS(unit_details[Asking Rent],unit_details[First Listed],">="&($Q$2-7), unit_details[First Listed],"<="&$Q$2, unit_details[Beds],1, unit_details[Property Name],B6),"") | N7: =COUNTIFS(unit_details[Property Name], B6, unit_details[Beds], 1, unit_details[Leased Date], "") -> 0 | O7: =N7-(N7-K7+F7) -> 0 | P7: =IFERROR(AVERAGEIFS(unit_details[Asking Rent],unit_details[Property Name], B6, unit_details[Beds], 1, unit_details[Leased Date], ""),"") | Q7: =IFERROR(N7/SUMIFS(unit_mix_table['# Units],unit_mix_table[Beds],1,unit_mix_table[Property Name],B6),"")
E8: 2 BR | F8: =COUNTIFS(unit_details[Leased Date], ">=" & ($Q$2 - 7), unit_details[Leased Date], "<" & $Q$2, unit_details[Beds], 2, unit_details[Property Name], B6) -> 1 | G8: =COUNTIFS(unit_details[Leased Date], ">=" & ($Q$2 - 7), unit_details[Leased Date], "<" & $Q$2, unit_details[Beds], 2, unit_details[Property Name], B6) - COUNTIFS(unit_details[Leased Date], ">=" & ($Q$2 - 14), unit_details[Leased Date], "<=" & ($Q$2 - 7), unit_details[Beds], 2, unit_details[Property Name], B6) -> 1 | H8: =IFERROR(AVERAGEIFS( unit_details[Asking Rent], unit_details[Leased Date], ">=" & ($Q$2 - 7), unit_details[Leased Date], "<" & $Q$2, unit_details[Beds], 2, unit_details[Property Name], B6),"") -> 1490 | I8: =IFERROR( AVERAGEIFS(unit_details[Asking Rent], unit_details[Leased Date], ">=" & ($Q$2 - 7), unit_details[Leased Date], "<" & $Q$2, unit_details[Beds], 2, unit_details[Property Name], B6) - AVERAGEIFS(unit_details[Asking Rent], unit_details[Leased Date], ">=" & ($Q$2 - 14), unit_details[Leased Date], "<=" & ($Q$2 - 7), unit_details[Beds], 2, unit_details[Property Name], B6), 0) -> 0 | J8: =IFERROR(I8/AVERAGEIFS(unit_details[Asking Rent], unit_details[Leased Date], ">=" & ($Q$2 - 14), unit_details[Leased Date], "<=" & ($Q$2 - 7), unit_details[Beds], 2, unit_details[Property Name], B6),0) -> 0 | K8: =COUNTIFS(unit_details[First Listed], ">=" & ($Q$2 - 7), unit_details[First Listed], "<" & $Q$2, unit_details[Beds], 2, unit_details[Property Name], B6) -> 0 | L8: =COUNTIFS( unit_details[First Listed], ">=" & ($Q$2 - 7), unit_details[First Listed], "<" & $Q$2, unit_details[Beds], 2, unit_details[Property Name], B6 ) - COUNTIFS( unit_details[First Listed], ">=" & ($Q$2 - 14), unit_details[First Listed], "<=" & ($Q$2 - 7), unit_details[Beds], 2, unit_details[Property Name], B6 ) -> 0 | M8: =IFERROR(AVERAGEIFS(unit_details[Asking Rent],unit_details[First Listed],">="&($Q$2-7), unit_details[First Listed],"<="&$Q$2, unit_details[Beds],2, unit_details[Property Name],B6),"") | N8: =COUNTIFS(unit_details[Property Name], B6, unit_details[Beds], 2, unit_details[Leased Date], "") -> 4 | O8: =N8-(N8-K8+F8) -> -1 | P8: =IFERROR(AVERAGEIFS(unit_details[Asking Rent],unit_details[Property Name], B6, unit_details[Beds], 2, unit_details[Leased Date], ""),"") -> 1425 | Q8: =IFERROR(N8/SUMIFS(unit_mix_table['# Units],unit_mix_table[Beds],2,unit_mix_table[Property Name],B6),"")
E9: 3 BR | F9: =COUNTIFS(unit_details[Leased Date], ">=" & ($Q$2 - 7), unit_details[Leased Date], "<" & $Q$2, unit_details[Beds], 3, unit_details[Property Name], B6) -> 0 | G9: =COUNTIFS(unit_details[Leased Date], ">=" & ($Q$2 - 7), unit_details[Leased Date], "<" & $Q$2, unit_details[Beds], 3, unit_details[Property Name], B6) - COUNTIFS(unit_details[Leased Date], ">=" & ($Q$2 - 14), unit_details[Leased Date], "<=" & ($Q$2 - 7), unit_details[Beds], 3, unit_details[Property Name], B6) -> 0 | H9: =IFERROR(AVERAGEIFS( unit_details[Asking Rent], unit_details[Leased Date], ">=" & ($Q$2 - 7), unit_details[Leased Date], "<" & $Q$2, unit_details[Beds], 3, unit_details[Property Name], B6),"") | I9: =IFERROR( AVERAGEIFS(unit_details[Asking Rent], unit_details[Leased Date], ">=" & ($Q$2 - 7), unit_details[Leased Date], "<" & $Q$2, unit_details[Beds], 3, unit_details[Property Name], B6) - AVERAGEIFS(unit_details[Asking Rent], unit_details[Leased Date], ">=" & ($Q$2 - 14), unit_details[Leased Date], "<=" & ($Q$2 - 7), unit_details[Beds], 3, unit_details[Property Name], B6), 0) -> 0 | J9: =IFERROR(I9/AVERAGEIFS(unit_details[Asking Rent], unit_details[Leased Date], ">=" & ($Q$2 - 14), unit_details[Leased Date], "<=" & ($Q$2 - 7), unit_details[Beds], 3, unit_details[Property Name], B6),0) -> 0 | K9: =COUNTIFS(unit_details[First Listed], ">=" & ($Q$2 - 7), unit_details[First Listed], "<" & $Q$2, unit_details[Beds], 3, unit_details[Property Name], B6) -> 0 | L9: =COUNTIFS( unit_details[First Listed], ">=" & ($Q$2 - 7), unit_details[First Listed], "<" & $Q$2, unit_details[Beds], 3, unit_details[Property Name], B6 ) - COUNTIFS( unit_details[First Listed], ">=" & ($Q$2 - 14), unit_details[First Listed], "<=" & ($Q$2 - 7), unit_details[Beds], 3, unit_details[Property Name], B6 ) -> 0 | M9: =IFERROR(AVERAGEIFS(unit_details[Asking Rent],unit_details[First Listed],">="&($Q$2-7), unit_details[First Listed],"<="&$Q$2, unit_details[Beds],3, unit_details[Property Name],B6),"") | N9: =COUNTIFS(unit_details[Property Name], B6, unit_details[Beds], 3, unit_details[Leased Date], "") -> 0 | O9: =N9-(N9-K9+F9) -> 0 | P9: =IFERROR(AVERAGEIFS(unit_details[Asking Rent],unit_details[Property Name], B6, unit_details[Beds], 3, unit_details[Leased Date], ""),"") | Q9: =IFERROR(N9/SUMIFS(unit_mix_table['# Units],unit_mix_table[Beds],3,unit_mix_table[Property Name],B6),"")
B10: =IF(OFFSET('Rent Comparison'!$A$1,2,6)="{{h:comparables.#.building_name}}","",IF(OFFSET('Rent Comparison'!$A$1,2,6)=0,B11,OFFSET('Rent Comparison'!$A$1,2,6))) -> 211 Rich Street, Delta, CO 81416 | C10: =IF(ISBLANK(B10),"",IFERROR(INDEX(Specials!B:J,MATCH(B10&" - Active",Specials!I:I,0),2),"")) | E10: Studio | F10: =COUNTIFS(unit_details[Leased Date], ">=" & ($Q$2 - 7), unit_details[Leased Date], "<" & $Q$2, unit_details[Beds], 0, unit_details[Property Name], B10) -> 0 | G10: =COUNTIFS(unit_details[Leased Date], ">=" & ($Q$2 - 7), unit_details[Leased Date], "<" & $Q$2, unit_details[Beds], 0, unit_details[Property Name], B10) - COUNTIFS(unit_details[Leased Date], ">=" & ($Q$2 - 14), unit_details[Leased Date], "<=" & ($Q$2 - 7), unit_details[Beds], 0, unit_details[Property Name], B10) -> 0 | H10: =IFERROR(AVERAGEIFS(unit_details[Asking Rent],unit_details[Leased Date], ">=" & ($Q$2 - 7), unit_details[Leased Date], "<" & $Q$2, unit_details[Beds], 0, unit_details[Property Name], B10),"") | I10: =IFERROR( AVERAGEIFS(unit_details[Asking Rent], unit_details[Leased Date], ">=" & ($Q$2 - 7), unit_details[Leased Date], "<" & $Q$2, unit_details[Beds], 0, unit_details[Property Name], B10) - AVERAGEIFS(unit_details[Asking Rent], unit_details[Leased Date], ">=" & ($Q$2 - 14), unit_details[Leased Date], "<=" & ($Q$2 - 7), unit_details[Beds], 0, unit_details[Property Name], B10), 0) -> 0 | J10: =IFERROR(I10/AVERAGEIFS(unit_details[Asking Rent], unit_details[Leased Date], ">=" & ($Q$2 - 14), unit_details[Leased Date], "<=" & ($Q$2 - 7), unit_details[Beds], 0, unit_details[Property Name], B10),0) -> 0 | K10: =COUNTIFS(unit_details[First Listed], ">=" & ($Q$2 - 7), unit_details[First Listed], "<" & $Q$2, unit_details[Beds], 0, unit_details[Property Name], B10) -> 0 | L10: =COUNTIFS( unit_details[First Listed], ">=" & ($Q$2 - 7), unit_details[First Listed], "<" & $Q$2, unit_details[Beds], 0, unit_details[Property Name], B10 ) - COUNTIFS( unit_details[First Listed], ">=" & ($Q$2 - 14), unit_details[First Listed], "<=" & ($Q$2 - 7), unit_details[Beds], 0, unit_details[Property Name], B10 ) -> 0 | M10: =IFERROR(AVERAGEIFS(unit_details[Asking Rent],unit_details[First Listed],">="&($Q$2-7), unit_details[First Listed],"<="&$Q$2, unit_details[Beds],0, unit_details[Property Name],B10),"") | N10: =COUNTIFS(unit_details[Property Name], B10, unit_details[Beds], 0, unit_details[Leased Date], "") -> 0 | O10: =N10-(N10-K10+F10) -> 0 | P10: =IFERROR(AVERAGEIFS(unit_details[Asking Rent],unit_details[Property Name], B10, unit_details[Beds], 0, unit_details[Leased Date], ""),"") | Q10: =IFERROR(N10/SUMIFS(unit_mix_table['# Units],unit_mix_table[Beds],0,unit_mix_table[Property Name],B10),"")
B11: 211 Rich Street, Delta, CO 81416 | E11: 1 BR | F11: =COUNTIFS(unit_details[Leased Date], ">=" & ($Q$2 - 7), unit_details[Leased Date], "<" & $Q$2, unit_details[Beds], 1, unit_details[Property Name], B10) -> 0 | G11: =COUNTIFS(unit_details[Leased Date], ">=" & ($Q$2 - 7), unit_details[Leased Date], "<" & $Q$2, unit_details[Beds], 1, unit_details[Property Name], B10) - COUNTIFS(unit_details[Leased Date], ">=" & ($Q$2 - 14), unit_details[Leased Date], "<=" & ($Q$2 - 7), unit_details[Beds], 1, unit_details[Property Name], B10) -> 0 | H11: =IFERROR(AVERAGEIFS(unit_details[Asking Rent],unit_details[Leased Date], ">=" & ($Q$2 - 7), unit_details[Leased Date], "<" & $Q$2, unit_details[Beds], 1, unit_details[Property Name], B10),"") | I11: =IFERROR( AVERAGEIFS(unit_details[Asking Rent], unit_details[Leased Date], ">=" & ($Q$2 - 7), unit_details[Leased Date], "<" & $Q$2, unit_details[Beds], 1, unit_details[Property Name], B10) - AVERAGEIFS(unit_details[Asking Rent], unit_details[Leased Date], ">=" & ($Q$2 - 14), unit_details[Leased Date], "<=" & ($Q$2 - 7), unit_details[Beds], 1, unit_details[Property Name], B10), 0) -> 0 | J11: =IFERROR(I11/AVERAGEIFS(unit_details[Asking Rent], unit_details[Leased Date], ">=" & ($Q$2 - 14), unit_details[Leased Date], "<=" & ($Q$2 - 7), unit_details[Beds], 1, unit_details[Property Name], B10),0) -> 0 | K11: =COUNTIFS(unit_details[First Listed], ">=" & ($Q$2 - 7), unit_details[First Listed], "<" & $Q$2, unit_details[Beds], 1, unit_details[Property Name], B10) -> 0 | L11: =COUNTIFS( unit_details[First Listed], ">=" & ($Q$2 - 7), unit_details[First Listed], "<" & $Q$2, unit_details[Beds], 1, unit_details[Property Name], B10 ) - COUNTIFS( unit_details[First Listed], ">=" & ($Q$2 - 14), unit_details[First Listed], "<=" & ($Q$2 - 7), unit_details[Beds], 1, unit_details[Property Name], B10 ) -> 0 | M11: =IFERROR(AVERAGEIFS(unit_details[Asking Rent],unit_details[First Listed],">="&($Q$2-7), unit_details[First Listed],"<="&$Q$2, unit_details[Beds],1, unit_details[Property Name],B10),"") | N11: =COUNTIFS(unit_details[Property Name], B10, unit_details[Beds], 1, unit_details[Leased Date], "") -> 0 | O11: =N11-(N11-K11+F11) -> 0 | P11: =IFERROR(AVERAGEIFS(unit_details[Asking Rent],unit_details[Property Name], B10, unit_details[Beds], 1, unit_details[Leased Date], ""),"") | Q11: =IFERROR(N11/SUMIFS(unit_mix_table['# Units],unit_mix_table[Beds],1,unit_mix_table[Property Name],B10),"")
E12: 2 BR | F12: =COUNTIFS(unit_details[Leased Date], ">=" & ($Q$2 - 7), unit_details[Leased Date], "<" & $Q$2, unit_details[Beds], 2, unit_details[Property Name], B10) -> 0 | G12: =COUNTIFS(unit_details[Leased Date], ">=" & ($Q$2 - 7), unit_details[Leased Date], "<" & $Q$2, unit_details[Beds], 2, unit_details[Property Name], B10) - COUNTIFS(unit_details[Leased Date], ">=" & ($Q$2 - 14), unit_details[Leased Date], "<=" & ($Q$2 - 7), unit_details[Beds], 2, unit_details[Property Name], B10) -> 0 | H12: =IFERROR(AVERAGEIFS(unit_details[Asking Rent],unit_details[Leased Date], ">=" & ($Q$2 - 7), unit_details[Leased Date], "<" & $Q$2, unit_details[Beds], 2, unit_details[Property Name], B10),"") | I12: =IFERROR( AVERAGEIFS(unit_details[Asking Rent], unit_details[Leased Date], ">=" & ($Q$2 - 7), unit_details[Leased Date], "<" & $Q$2, unit_details[Beds], 2, unit_details[Property Name], B10) - AVERAGEIFS(unit_details[Asking Rent], unit_details[Leased Date], ">=" & ($Q$2 - 14), unit_details[Leased Date], "<=" & ($Q$2 - 7), unit_details[Beds], 2, unit_details[Property Name], B10), 0) -> 0 | J12: =IFERROR(I12/AVERAGEIFS(unit_details[Asking Rent], unit_details[Leased Date], ">=" & ($Q$2 - 14), unit_details[Leased Date], "<=" & ($Q$2 - 7), unit_details[Beds], 2, unit_details[Property Name], B10),0) -> 0 | K12: =COUNTIFS(unit_details[First Listed], ">=" & ($Q$2 - 7), unit_details[First Listed], "<" & $Q$2, unit_details[Beds], 2, unit_details[Property Name], B10) -> 0 | L12: =COUNTIFS( unit_details[First Listed], ">=" & ($Q$2 - 7), unit_details[First Listed], "<" & $Q$2, unit_details[Beds], 2, unit_details[Property Name], B10 ) - COUNTIFS( unit_details[First Listed], ">=" & ($Q$2 - 14), unit_details[First Listed], "<=" & ($Q$2 - 7), unit_details[Beds], 2, unit_details[Property Name], B10 ) -> 0 | M12: =IFERROR(AVERAGEIFS(unit_details[Asking Rent],unit_details[First Listed],">="&($Q$2-7), unit_details[First Listed],"<="&$Q$2, unit_details[Beds],2, unit_details[Property Name],B10),"") | N12: =COUNTIFS(unit_details[Property Name], B10, unit_details[Beds], 2, unit_details[Leased Date], "") -> 0 | O12: =N12-(N12-K12+F12) -> 0 | P12: =IFERROR(AVERAGEIFS(unit_details[Asking Rent],unit_details[Property Name], B10, unit_details[Beds], 2, unit_details[Leased Date], ""),"") | Q12: =IFERROR(N12/SUMIFS(unit_mix_table['# Units],unit_mix_table[Beds],2,unit_mix_table[Property Name],B10),"")
E13: 3 BR | F13: =COUNTIFS(unit_details[Leased Date], ">=" & ($Q$2 - 7), unit_details[Leased Date], "<" & $Q$2, unit_details[Beds], 3, unit_details[Property Name], B10) -> 0 | G13: =COUNTIFS(unit_details[Leased Date], ">=" & ($Q$2 - 7), unit_details[Leased Date], "<" & $Q$2, unit_details[Beds], 3, unit_details[Property Name], B10) - COUNTIFS(unit_details[Leased Date], ">=" & ($Q$2 - 14), unit_details[Leased Date], "<=" & ($Q$2 - 7), unit_details[Beds], 3, unit_details[Property Name], B10) -> 0 | H13: =IFERROR(AVERAGEIFS(unit_details[Asking Rent],unit_details[Leased Date], ">=" & ($Q$2 - 7), unit_details[Leased Date], "<" & $Q$2, unit_details[Beds], 3, unit_details[Property Name], B10),"") | I13: =IFERROR( AVERAGEIFS(unit_details[Asking Rent], unit_details[Leased Date], ">=" & ($Q$2 - 7), unit_details[Leased Date], "<" & $Q$2, unit_details[Beds], 3, unit_details[Property Name], B10) - AVERAGEIFS(unit_details[Asking Rent], unit_details[Leased Date], ">=" & ($Q$2 - 14), unit_details[Leased Date], "<=" & ($Q$2 - 7), unit_details[Beds], 3, unit_details[Property Name], B10), 0) -> 0 | J13: =IFERROR(I13/AVERAGEIFS(unit_details[Asking Rent], unit_details[Leased Date], ">=" & ($Q$2 - 14), unit_details[Leased Date], "<=" & ($Q$2 - 7), unit_details[Beds], 3, unit_details[Property Name], B10),0) -> 0 | K13: =COUNTIFS(unit_details[First Listed], ">=" & ($Q$2 - 7), unit_details[First Listed], "<" & $Q$2, unit_details[Beds], 3, unit_details[Property Name], B10) -> 0 | L13: =COUNTIFS( unit_details[First Listed], ">=" & ($Q$2 - 7), unit_details[First Listed], "<" & $Q$2, unit_details[Beds], 3, unit_details[Property Name], B10 ) - COUNTIFS( unit_details[First Listed], ">=" & ($Q$2 - 14), unit_details[First Listed], "<=" & ($Q$2 - 7), unit_details[Beds], 3, unit_details[Property Name], B10 ) -> 0 | M13: =IFERROR(AVERAGEIFS(unit_details[Asking Rent],unit_details[First Listed],">="&($Q$2-7), unit_details[First Listed],"<="&$Q$2, unit_details[Beds],3, unit_details[Property Name],B10),"") | N13: =COUNTIFS(unit_details[Property Name], B10, unit_details[Beds], 3, unit_details[Leased Date], "") -> 0 | O13: =N13-(N13-K13+F13) -> 0 | P13: =IFERROR(AVERAGEIFS(unit_details[Asking Rent],unit_details[Property Name], B10, unit_details[Beds], 3, unit_details[Leased Date], ""),"") | Q13: =IFERROR(N13/SUMIFS(unit_mix_table['# Units],unit_mix_table[Beds],3,unit_mix_table[Property Name],B10),"")
B14: =IF(ISBLANK(OFFSET('Rent Comparison'!$A$1,2,7)),"",IF(OFFSET('Rent Comparison'!$A$1,2,7)=0,B15,OFFSET('Rent Comparison'!$A$1,2,7))) | C14: =IF(ISBLANK(B14),"",IFERROR(INDEX(Specials!B:J,MATCH(B14&" - Active",Specials!I:I,0),2),"")) | E14: Studio | F14: =COUNTIFS(unit_details[Leased Date], ">=" & ($Q$2 - 7), unit_details[Leased Date], "<" & $Q$2, unit_details[Beds], 0, unit_details[Property Name], B14) -> 0 | G14: =COUNTIFS(unit_details[Leased Date], ">=" & ($Q$2 - 7), unit_details[Leased Date], "<" & $Q$2, unit_details[Beds], 0, unit_details[Property Name], B14) - COUNTIFS(unit_details[Leased Date], ">=" & ($Q$2 - 14), unit_details[Leased Date], "<=" & ($Q$2 - 7), unit_details[Beds], 0, unit_details[Property Name], B14) -> 0 | H14: =IFERROR(AVERAGEIFS(unit_details[Asking Rent],unit_details[Leased Date], ">=" & ($Q$2 - 7), unit_details[Leased Date], "<" & $Q$2, unit_details[Beds], 0, unit_details[Property Name], B14),"") | I14: =IFERROR( AVERAGEIFS(unit_details[Asking Rent], unit_details[Leased Date], ">=" & ($Q$2 - 7), unit_details[Leased Date], "<" & $Q$2, unit_details[Beds], 0, unit_details[Property Name], B14) - AVERAGEIFS(unit_details[Asking Rent], unit_details[Leased Date], ">=" & ($Q$2 - 14), unit_details[Leased Date], "<=" & ($Q$2 - 7), unit_details[Beds], 0, unit_details[Property Name], B14), 0) -> 0 | J14: =IFERROR(I14/AVERAGEIFS(unit_details[Asking Rent], unit_details[Leased Date], ">=" & ($Q$2 - 14), unit_details[Leased Date], "<=" & ($Q$2 - 7), unit_details[Beds], 0, unit_details[Property Name], B14),0) -> 0 | K14: =COUNTIFS(unit_details[First Listed], ">=" & ($Q$2 - 7), unit_details[First Listed], "<" & $Q$2, unit_details[Beds], 0, unit_details[Property Name], B14) -> 0 | L14: =COUNTIFS( unit_details[First Listed], ">=" & ($Q$2 - 7), unit_details[First Listed], "<" & $Q$2, unit_details[Beds], 0, unit_details[Property Name], B14 ) - COUNTIFS( unit_details[First Listed], ">=" & ($Q$2 - 14), unit_details[First Listed], "<=" & ($Q$2 - 7), unit_details[Beds], 0, unit_details[Property Name], B14 ) -> 0 | M14: =IFERROR(AVERAGEIFS(unit_details[Asking Rent],unit_details[First Listed],">="&($Q$2-7), unit_details[First Listed],"<="&$Q$2, unit_details[Beds],0, unit_details[Property Name],B14),"") | N14: =COUNTIFS(unit_details[Property Name], B14, unit_details[Beds], 0, unit_details[Leased Date], "") -> 0 | O14: =N14-(N14-K14+F14) -> 0 | P14: =IFERROR(AVERAGEIFS(unit_details[Asking Rent],unit_details[Property Name], B14, unit_details[Beds], 0, unit_details[Leased Date], ""),"") | Q14: =IFERROR(N14/SUMIFS(unit_mix_table['# Units],unit_mix_table[Beds],0,unit_mix_table[Property Name],B14),"")
B15: 920 East 7th Street, Delta, CO 81416 | E15: 1 BR | F15: =COUNTIFS(unit_details[Leased Date], ">=" & ($Q$2 - 7), unit_details[Leased Date], "<" & $Q$2, unit_details[Beds], 1, unit_details[Property Name], B14) -> 0 | G15: =COUNTIFS(unit_details[Leased Date], ">=" & ($Q$2 - 7), unit_details[Leased Date], "<" & $Q$2, unit_details[Beds], 1, unit_details[Property Name], B14) - COUNTIFS(unit_details[Leased Date], ">=" & ($Q$2 - 14), unit_details[Leased Date], "<=" & ($Q$2 - 7), unit_details[Beds], 1, unit_details[Property Name], B14) -> 0 | H15: =IFERROR(AVERAGEIFS(unit_details[Asking Rent],unit_details[Leased Date], ">=" & ($Q$2 - 7), unit_details[Leased Date], "<" & $Q$2, unit_details[Beds], 1, unit_details[Property Name], B14),"") | I15: =IFERROR( AVERAGEIFS(unit_details[Asking Rent], unit_details[Leased Date], ">=" & ($Q$2 - 7), unit_details[Leased Date], "<" & $Q$2, unit_details[Beds], 1, unit_details[Property Name], B14) - AVERAGEIFS(unit_details[Asking Rent], unit_details[Leased Date], ">=" & ($Q$2 - 14), unit_details[Leased Date], "<=" & ($Q$2 - 7), unit_details[Beds], 1, unit_details[Property Name], B14), 0) -> 0 | J15: =IFERROR(I15/AVERAGEIFS(unit_details[Asking Rent], unit_details[Leased Date], ">=" & ($Q$2 - 14), unit_details[Leased Date], "<=" & ($Q$2 - 7), unit_details[Beds], 1, unit_details[Property Name], B14),0) -> 0 | K15: =COUNTIFS(unit_details[First Listed], ">=" & ($Q$2 - 7), unit_details[First Listed], "<" & $Q$2, unit_details[Beds], 1, unit_details[Property Name], B14) -> 0 | L15: =COUNTIFS( unit_details[First Listed], ">=" & ($Q$2 - 7), unit_details[First Listed], "<" & $Q$2, unit_details[Beds], 1, unit_details[Property Name], B14 ) - COUNTIFS( unit_details[First Listed], ">=" & ($Q$2 - 14), unit_details[First Listed], "<=" & ($Q$2 - 7), unit_details[Beds], 1, unit_details[Property Name], B14 ) -> 0 | M15: =IFERROR(AVERAGEIFS(unit_details[Asking Rent],unit_details[First Listed],">="&($Q$2-7), unit_details[First Listed],"<="&$Q$2, unit_details[Beds],1, unit_details[Property Name],B14),"") | N15: =COUNTIFS(unit_details[Property Name], B14, unit_details[Beds], 1, unit_details[Leased Date], "") -> 7 | O15: =N15-(N15-K15+F15) -> 0 | P15: =IFERROR(AVERAGEIFS(unit_details[Asking Rent],unit_details[Property Name], B14, unit_details[Beds], 1, unit_details[Leased Date], ""),"") -> 1028.5714 | Q15: =IFERROR(N15/SUMIFS(unit_mix_table['# Units],unit_mix_table[Beds],1,unit_mix_table[Property Name],B14),"") -> 2.3333333
E16: 2 BR | F16: =COUNTIFS(unit_details[Leased Date], ">=" & ($Q$2 - 7), unit_details[Leased Date], "<" & $Q$2, unit_details[Beds], 2, unit_details[Property Name], B14) -> 0 | G16: =COUNTIFS(unit_details[Leased Date], ">=" & ($Q$2 - 7), unit_details[Leased Date], "<" & $Q$2, unit_details[Beds], 2, unit_details[Property Name], B14) - COUNTIFS(unit_details[Leased Date], ">=" & ($Q$2 - 14), unit_details[Leased Date], "<=" & ($Q$2 - 7), unit_details[Beds], 2, unit_details[Property Name], B14) -> 0 | H16: =IFERROR(AVERAGEIFS(unit_details[Asking Rent],unit_details[Leased Date], ">=" & ($Q$2 - 7), unit_details[Leased Date], "<" & $Q$2, unit_details[Beds], 2, unit_details[Property Name], B14),"") | I16: =IFERROR( AVERAGEIFS(unit_details[Asking Rent], unit_details[Leased Date], ">=" & ($Q$2 - 7), unit_details[Leased Date], "<" & $Q$2, unit_details[Beds], 2, unit_details[Property Name], B14) - AVERAGEIFS(unit_details[Asking Rent], unit_details[Leased Date], ">=" & ($Q$2 - 14), unit_details[Leased Date], "<=" & ($Q$2 - 7), unit_details[Beds], 2, unit_details[Property Name], B14), 0) -> 0 | J16: =IFERROR(I16/AVERAGEIFS(unit_details[Asking Rent], unit_details[Leased Date], ">=" & ($Q$2 - 14), unit_details[Leased Date], "<=" & ($Q$2 - 7), unit_details[Beds], 2, unit_details[Property Name], B14),0) -> 0 | K16: =COUNTIFS(unit_details[First Listed], ">=" & ($Q$2 - 7), unit_details[First Listed], "<" & $Q$2, unit_details[Beds], 2, unit_details[Property Name], B14) -> 0 | L16: =COUNTIFS( unit_details[First Listed], ">=" & ($Q$2 - 7), unit_details[First Listed], "<" & $Q$2, unit_details[Beds], 2, unit_details[Property Name], B14 ) - COUNTIFS( unit_details[First Listed], ">=" & ($Q$2 - 14), unit_details[First Listed], "<=" & ($Q$2 - 7), unit_details[Beds], 2, unit_details[Property Name], B14 ) -> 0 | M16: =IFERROR(AVERAGEIFS(unit_details[Asking Rent],unit_details[First Listed],">="&($Q$2-7), unit_details[First Listed],"<="&$Q$2, unit_details[Beds],2, unit_details[Property Name],B14),"") | N16: =COUNTIFS(unit_details[Property Name], B14, unit_details[Beds], 2, unit_details[Leased Date], "") -> 9 | O16: =N16-(N16-K16+F16) -> 0 | P16: =IFERROR(AVERAGEIFS(unit_details[Asking Rent],unit_details[Property Name], B14, unit_details[Beds], 2, unit_details[Leased Date], ""),"") -> 1211.1111 | Q16: =IFERROR(N16/SUMIFS(unit_mix_table['# Units],unit_mix_table[Beds],2,unit_mix_table[Property Name],B14),"") -> 1.5
E17: 3 BR | F17: =COUNTIFS(unit_details[Leased Date], ">=" & ($Q$2 - 7), unit_details[Leased Date], "<" & $Q$2, unit_details[Beds], 3, unit_details[Property Name], B14) -> 0 | G17: =COUNTIFS(unit_details[Leased Date], ">=" & ($Q$2 - 7), unit_details[Leased Date], "<" & $Q$2, unit_details[Beds], 3, unit_details[Property Name], B14) - COUNTIFS(unit_details[Leased Date], ">=" & ($Q$2 - 14), unit_details[Leased Date], "<=" & ($Q$2 - 7), unit_details[Beds], 3, unit_details[Property Name], B14) -> 0 | H17: =IFERROR(AVERAGEIFS(unit_details[Asking Rent],unit_details[Leased Date], ">=" & ($Q$2 - 7), unit_details[Leased Date], "<" & $Q$2, unit_details[Beds], 3, unit_details[Property Name], B14),"") | I17: =IFERROR( AVERAGEIFS(unit_details[Asking Rent], unit_details[Leased Date], ">=" & ($Q$2 - 7), unit_details[Leased Date], "<" & $Q$2, unit_details[Beds], 3, unit_details[Property Name], B14) - AVERAGEIFS(unit_details[Asking Rent], unit_details[Leased Date], ">=" & ($Q$2 - 14), unit_details[Leased Date], "<=" & ($Q$2 - 7), unit_details[Beds], 3, unit_details[Property Name], B14), 0) -> 0 | J17: =IFERROR(I17/AVERAGEIFS(unit_details[Asking Rent], unit_details[Leased Date], ">=" & ($Q$2 - 14), unit_details[Leased Date], "<=" & ($Q$2 - 7), unit_details[Beds], 3, unit_details[Property Name], B14),0) -> 0 | K17: =COUNTIFS(unit_details[First Listed], ">=" & ($Q$2 - 7), unit_details[First Listed], "<" & $Q$2, unit_details[Beds], 3, unit_details[Property Name], B14) -> 0 | L17: =COUNTIFS( unit_details[First Listed], ">=" & ($Q$2 - 7), unit_details[First Listed], "<" & $Q$2, unit_details[Beds], 3, unit_details[Property Name], B14 ) - COUNTIFS( unit_details[First Listed], ">=" & ($Q$2 - 14), unit_details[First Listed], "<=" & ($Q$2 - 7), unit_details[Beds], 3, unit_details[Property Name], B14 ) -> 0 | M17: =IFERROR(AVERAGEIFS(unit_details[Asking Rent],unit_details[First Listed],">="&($Q$2-7), unit_details[First Listed],"<="&$Q$2, unit_details[Beds],3, unit_details[Property Name],B14),"") | N17: =COUNTIFS(unit_details[Property Name], B14, unit_details[Beds], 3, unit_details[Leased Date], "") -> 0 | O17: =N17-(N17-K17+F17) -> 0 | P17: =IFERROR(AVERAGEIFS(unit_details[Asking Rent],unit_details[Property Name], B14, unit_details[Beds], 3, unit_details[Leased Date], ""),"") | Q17: =IFERROR(N17/SUMIFS(unit_mix_table['# Units],unit_mix_table[Beds],3,unit_mix_table[Property Name],B14),"")
B18: =IF(ISBLANK(OFFSET('Rent Comparison'!$A$1,2,8)),"",IF(OFFSET('Rent Comparison'!$A$1,2,8)=0,B19,OFFSET('Rent Comparison'!$A$1,2,8))) | C18: =IF(ISBLANK(B18),"",IFERROR(INDEX(Specials!B:J,MATCH(B18&" - Active",Specials!I:I,0),2),"")) | E18: Studio | F18: =COUNTIFS(unit_details[Leased Date], ">=" & ($Q$2 - 7), unit_details[Leased Date], "<" & $Q$2, unit_details[Beds], 0, unit_details[Property Name], B18) -> 0 | G18: =COUNTIFS(unit_details[Leased Date], ">=" & ($Q$2 - 7), unit_details[Leased Date], "<" & $Q$2, unit_details[Beds], 0, unit_details[Property Name], B18) - COUNTIFS(unit_details[Leased Date], ">=" & ($Q$2 - 14), unit_details[Leased Date], "<=" & ($Q$2 - 7), unit_details[Beds], 0, unit_details[Property Name], B18) -> 0 | H18: =IFERROR(AVERAGEIFS(unit_details[Asking Rent],unit_details[Leased Date], ">=" & ($Q$2 - 7), unit_details[Leased Date], "<" & $Q$2, unit_details[Beds], 0, unit_details[Property Name], B18),"") | I18: =IFERROR( AVERAGEIFS(unit_details[Asking Rent], unit_details[Leased Date], ">=" & ($Q$2 - 7), unit_details[Leased Date], "<" & $Q$2, unit_details[Beds], 0, unit_details[Property Name], B18) - AVERAGEIFS(unit_details[Asking Rent], unit_details[Leased Date], ">=" & ($Q$2 - 14), unit_details[Leased Date], "<=" & ($Q$2 - 7), unit_details[Beds], 0, unit_details[Property Name], B18), 0) -> 0 | J18: =IFERROR(I18/AVERAGEIFS(unit_details[Asking Rent], unit_details[Leased Date], ">=" & ($Q$2 - 14), unit_details[Leased Date], "<=" & ($Q$2 - 7), unit_details[Beds], 0, unit_details[Property Name], B18),0) -> 0 | K18: =COUNTIFS(unit_details[First Listed], ">=" & ($Q$2 - 7), unit_details[First Listed], "<" & $Q$2, unit_details[Beds], 0, unit_details[Property Name], B18) -> 0 | L18: =COUNTIFS( unit_details[First Listed], ">=" & ($Q$2 - 7), unit_details[First Listed], "<" & $Q$2, unit_details[Beds], 0, unit_details[Property Name], B18 ) - COUNTIFS( unit_details[First Listed], ">=" & ($Q$2 - 14), unit_details[First Listed], "<=" & ($Q$2 - 7), unit_details[Beds], 0, unit_details[Property Name], B18 ) -> 0 | M18: =IFERROR(AVERAGEIFS(unit_details[Asking Rent],unit_details[First Listed],">="&($Q$2-7), unit_details[First Listed],"<="&$Q$2, unit_details[Beds],0, unit_details[Property Name],B18),"") | N18: =COUNTIFS(unit_details[Property Name], B18, unit_details[Beds], 0, unit_details[Leased Date], "") -> 0 | O18: =N18-(N18-K18+F18) -> 0 | P18: =IFERROR(AVERAGEIFS(unit_details[Asking Rent],unit_details[Property Name], B18, unit_details[Beds], 0, unit_details[Leased Date], ""),"") | Q18: =IFERROR(N18/SUMIFS(unit_mix_table['# Units],unit_mix_table[Beds],0,unit_mix_table[Property Name],B18),"")
B19: 217 Rich Street, Delta, CO 81416 | E19: 1 BR | F19: =COUNTIFS(unit_details[Leased Date], ">=" & ($Q$2 - 7), unit_details[Leased Date], "<" & $Q$2, unit_details[Beds], 1, unit_details[Property Name], B18) -> 0 | G19: =COUNTIFS(unit_details[Leased Date], ">=" & ($Q$2 - 7), unit_details[Leased Date], "<" & $Q$2, unit_details[Beds], 1, unit_details[Property Name], B18) - COUNTIFS(unit_details[Leased Date], ">=" & ($Q$2 - 14), unit_details[Leased Date], "<=" & ($Q$2 - 7), unit_details[Beds], 1, unit_details[Property Name], B18) -> 0 | H19: =IFERROR(AVERAGEIFS(unit_details[Asking Rent],unit_details[Leased Date], ">=" & ($Q$2 - 7), unit_details[Leased Date], "<" & $Q$2, unit_details[Beds], 1, unit_details[Property Name], B18),"") | I19: =IFERROR( AVERAGEIFS(unit_details[Asking Rent], unit_details[Leased Date], ">=" & ($Q$2 - 7), unit_details[Leased Date], "<" & $Q$2, unit_details[Beds], 1, unit_details[Property Name], B18) - AVERAGEIFS(unit_details[Asking Rent], unit_details[Leased Date], ">=" & ($Q$2 - 14), unit_details[Leased Date], "<=" & ($Q$2 - 7), unit_details[Beds], 1, unit_details[Property Name], B18), 0) -> 0 | J19: =IFERROR(I19/AVERAGEIFS(unit_details[Asking Rent], unit_details[Leased Date], ">=" & ($Q$2 - 14), unit_details[Leased Date], "<=" & ($Q$2 - 7), unit_details[Beds], 1, unit_details[Property Name], B18),0) -> 0 | K19: =COUNTIFS(unit_details[First Listed], ">=" & ($Q$2 - 7), unit_details[First Listed], "<" & $Q$2, unit_details[Beds], 1, unit_details[Property Name], B18) -> 0 | L19: =COUNTIFS( unit_details[First Listed], ">=" & ($Q$2 - 7), unit_details[First Listed], "<" & $Q$2, unit_details[Beds], 1, unit_details[Property Name], B18 ) - COUNTIFS( unit_details[First Listed], ">=" & ($Q$2 - 14), unit_details[First Listed], "<=" & ($Q$2 - 7), unit_details[Beds], 1, unit_details[Property Name], B18 ) -> 0 | M19: =IFERROR(AVERAGEIFS(unit_details[Asking Rent],unit_details[First Listed],">="&($Q$2-7), unit_details[First Listed],"<="&$Q$2, unit_details[Beds],1, unit_details[Property Name],B18),"") | N19: =COUNTIFS(unit_details[Property Name], B18, unit_details[Beds], 1, unit_details[Leased Date], "") -> 7 | O19: =N19-(N19-K19+F19) -> 0 | P19: =IFERROR(AVERAGEIFS(unit_details[Asking Rent],unit_details[Property Name], B18, unit_details[Beds], 1, unit_details[Leased Date], ""),"") -> 1028.5714 | Q19: =IFERROR(N19/SUMIFS(unit_mix_table['# Units],unit_mix_table[Beds],1,unit_mix_table[Property Name],B18),"") -> 2.3333333
E20: 2 BR | F20: =COUNTIFS(unit_details[Leased Date], ">=" & ($Q$2 - 7), unit_details[Leased Date], "<" & $Q$2, unit_details[Beds], 2, unit_details[Property Name], B18) -> 0 | G20: =COUNTIFS(unit_details[Leased Date], ">=" & ($Q$2 - 7), unit_details[Leased Date], "<" & $Q$2, unit_details[Beds], 2, unit_details[Property Name], B18) - COUNTIFS(unit_details[Leased Date], ">=" & ($Q$2 - 14), unit_details[Leased Date], "<=" & ($Q$2 - 7), unit_details[Beds], 2, unit_details[Property Name], B18) -> 0 | H20: =IFERROR(AVERAGEIFS(unit_details[Asking Rent],unit_details[Leased Date], ">=" & ($Q$2 - 7), unit_details[Leased Date], "<" & $Q$2, unit_details[Beds], 2, unit_details[Property Name], B18),"") | I20: =IFERROR( AVERAGEIFS(unit_details[Asking Rent], unit_details[Leased Date], ">=" & ($Q$2 - 7), unit_details[Leased Date], "<" & $Q$2, unit_details[Beds], 2, unit_details[Property Name], B18) - AVERAGEIFS(unit_details[Asking Rent], unit_details[Leased Date], ">=" & ($Q$2 - 14), unit_details[Leased Date], "<=" & ($Q$2 - 7), unit_details[Beds], 2, unit_details[Property Name], B18), 0) -> 0 | J20: =IFERROR(I20/AVERAGEIFS(unit_details[Asking Rent], unit_details[Leased Date], ">=" & ($Q$2 - 14), unit_details[Leased Date], "<=" & ($Q$2 - 7), unit_details[Beds], 2, unit_details[Property Name], B18),0) -> 0 | K20: =COUNTIFS(unit_details[First Listed], ">=" & ($Q$2 - 7), unit_details[First Listed], "<" & $Q$2, unit_details[Beds], 2, unit_details[Property Name], B18) -> 0 | L20: =COUNTIFS( unit_details[First Listed], ">=" & ($Q$2 - 7), unit_details[First Listed], "<" & $Q$2, unit_details[Beds], 2, unit_details[Property Name], B18 ) - COUNTIFS( unit_details[First Listed], ">=" & ($Q$2 - 14), unit_details[First Listed], "<=" & ($Q$2 - 7), unit_details[Beds], 2, unit_details[Property Name], B18 ) -> 0 | M20: =IFERROR(AVERAGEIFS(unit_details[Asking Rent],unit_details[First Listed],">="&($Q$2-7), unit_details[First Listed],"<="&$Q$2, unit_details[Beds],2, unit_details[Property Name],B18),"") | N20: =COUNTIFS(unit_details[Property Name], B18, unit_details[Beds], 2, unit_details[Leased Date], "") -> 9 | O20: =N20-(N20-K20+F20) -> 0 | P20: =IFERROR(AVERAGEIFS(unit_details[Asking Rent],unit_details[Property Name], B18, unit_details[Beds], 2, unit_details[Leased Date], ""),"") -> 1211.1111 | Q20: =IFERROR(N20/SUMIFS(unit_mix_table['# Units],unit_mix_table[Beds],2,unit_mix_table[Property Name],B18),"") -> 1.5
E21: 3 BR | F21: =COUNTIFS(unit_details[Leased Date], ">=" & ($Q$2 - 7), unit_details[Leased Date], "<" & $Q$2, unit_details[Beds], 3, unit_details[Property Name], B18) -> 0 | G21: =COUNTIFS(unit_details[Leased Date], ">=" & ($Q$2 - 7), unit_details[Leased Date], "<" & $Q$2, unit_details[Beds], 3, unit_details[Property Name], B18) - COUNTIFS(unit_details[Leased Date], ">=" & ($Q$2 - 14), unit_details[Leased Date], "<=" & ($Q$2 - 7), unit_details[Beds], 3, unit_details[Property Name], B18) -> 0 | H21: =IFERROR(AVERAGEIFS(unit_details[Asking Rent],unit_details[Leased Date], ">=" & ($Q$2 - 7), unit_details[Leased Date], "<" & $Q$2, unit_details[Beds], 3, unit_details[Property Name], B18),"") | I21: =IFERROR( AVERAGEIFS(unit_details[Asking Rent], unit_details[Leased Date], ">=" & ($Q$2 - 7), unit_details[Leased Date], "<" & $Q$2, unit_details[Beds], 3, unit_details[Property Name], B18) - AVERAGEIFS(unit_details[Asking Rent], unit_details[Leased Date], ">=" & ($Q$2 - 14), unit_details[Leased Date], "<=" & ($Q$2 - 7), unit_details[Beds], 3, unit_details[Property Name], B18), 0) -> 0 | J21: =IFERROR(I21/AVERAGEIFS(unit_details[Asking Rent], unit_details[Leased Date], ">=" & ($Q$2 - 14), unit_details[Leased Date], "<=" & ($Q$2 - 7), unit_details[Beds], 3, unit_details[Property Name], B18),0) -> 0 | K21: =COUNTIFS(unit_details[First Listed], ">=" & ($Q$2 - 7), unit_details[First Listed], "<" & $Q$2, unit_details[Beds], 3, unit_details[Property Name], B18) -> 0 | L21: =COUNTIFS( unit_details[First Listed], ">=" & ($Q$2 - 7), unit_details[First Listed], "<" & $Q$2, unit_details[Beds], 3, unit_details[Property Name], B18 ) - COUNTIFS( unit_details[First Listed], ">=" & ($Q$2 - 14), unit_details[First Listed], "<=" & ($Q$2 - 7), unit_details[Beds], 3, unit_details[Property Name], B18 ) -> 0 | M21: =IFERROR(AVERAGEIFS(unit_details[Asking Rent],unit_details[First Listed],">="&($Q$2-7), unit_details[First Listed],"<="&$Q$2, unit_details[Beds],3, unit_details[Property Name],B18),"") | N21: =COUNTIFS(unit_details[Property Name], B18, unit_details[Beds], 3, unit_details[Leased Date], "") -> 0 | O21: =N21-(N21-K21+F21) -> 0 | P21: =IFERROR(AVERAGEIFS(unit_details[Asking Rent],unit_details[Property Name], B18, unit_details[Beds], 3, unit_details[Leased Date], ""),"") | Q21: =IFERROR(N21/SUMIFS(unit_mix_table['# Units],unit_mix_table[Beds],3,unit_mix_table[Property Name],B18),"")
B22: =IF(ISBLANK(OFFSET('Rent Comparison'!$A$1,2,9)),"",IF(OFFSET('Rent Comparison'!$A$1,2,9)=0,B23,OFFSET('Rent Comparison'!$A$1,2,9))) | C22: =IF(ISBLANK(B22),"",IFERROR(INDEX(Specials!B:J,MATCH(B22&" - Active",Specials!I:I,0),2),"")) | E22: Studio | F22: =COUNTIFS(unit_details[Leased Date], ">=" & ($Q$2 - 7), unit_details[Leased Date], "<" & $Q$2, unit_details[Beds], 0, unit_details[Property Name], B22) -> 0 | G22: =COUNTIFS(unit_details[Leased Date], ">=" & ($Q$2 - 7), unit_details[Leased Date], "<" & $Q$2, unit_details[Beds], 0, unit_details[Property Name], B22) - COUNTIFS(unit_details[Leased Date], ">=" & ($Q$2 - 14), unit_details[Leased Date], "<=" & ($Q$2 - 7), unit_details[Beds], 0, unit_details[Property Name], B22) -> 0 | H22: =IFERROR(AVERAGEIFS(unit_details[Asking Rent],unit_details[Leased Date], ">=" & ($Q$2 - 7), unit_details[Leased Date], "<" & $Q$2, unit_details[Beds], 0, unit_details[Property Name], B22),"") | I22: =IFERROR( AVERAGEIFS(unit_details[Asking Rent], unit_details[Leased Date], ">=" & ($Q$2 - 7), unit_details[Leased Date], "<" & $Q$2, unit_details[Beds], 0, unit_details[Property Name], B22) - AVERAGEIFS(unit_details[Asking Rent], unit_details[Leased Date], ">=" & ($Q$2 - 14), unit_details[Leased Date], "<=" & ($Q$2 - 7), unit_details[Beds], 0, unit_details[Property Name], B22), 0) -> 0 | J22: =IFERROR(I22/AVERAGEIFS(unit_details[Asking Rent], unit_details[Leased Date], ">=" & ($Q$2 - 14), unit_details[Leased Date], "<=" & ($Q$2 - 7), unit_details[Beds], 0, unit_details[Property Name], B22),0) -> 0 | K22: =COUNTIFS(unit_details[First Listed], ">=" & ($Q$2 - 7), unit_details[First Listed], "<" & $Q$2, unit_details[Beds], 0, unit_details[Property Name], B22) -> 0 | L22: =COUNTIFS( unit_details[First Listed], ">=" & ($Q$2 - 7), unit_details[First Listed], "<" & $Q$2, unit_details[Beds], 0, unit_details[Property Name], B22 ) - COUNTIFS( unit_details[First Listed], ">=" & ($Q$2 - 14), unit_details[First Listed], "<=" & ($Q$2 - 7), unit_details[Beds], 0, unit_details[Property Name], B22 ) -> 0 | M22: =IFERROR(AVERAGEIFS(unit_details[Asking Rent],unit_details[First Listed],">="&($Q$2-7), unit_details[First Listed],"<="&$Q$2, unit_details[Beds],0, unit_details[Property Name],B22),"") | N22: =COUNTIFS(unit_details[Property Name], B22, unit_details[Beds], 0, unit_details[Leased Date], "") -> 0 | O22: =N22-(N22-K22+F22) -> 0 | P22: =IFERROR(AVERAGEIFS(unit_details[Asking Rent],unit_details[Property Name], B22, unit_details[Beds], 0, unit_details[Leased Date], ""),"") | Q22: =IFERROR(N22/SUMIFS(unit_mix_table['# Units],unit_mix_table[Beds],0,unit_mix_table[Property Name],B22),"")
B23: 240 Meeker Street, Delta, CO 81416 | E23: 1 BR | F23: =COUNTIFS(unit_details[Leased Date], ">=" & ($Q$2 - 7), unit_details[Leased Date], "<" & $Q$2, unit_details[Beds], 1, unit_details[Property Name], B22) -> 0 | G23: =COUNTIFS(unit_details[Leased Date], ">=" & ($Q$2 - 7), unit_details[Leased Date], "<" & $Q$2, unit_details[Beds], 1, unit_details[Property Name], B22) - COUNTIFS(unit_details[Leased Date], ">=" & ($Q$2 - 14), unit_details[Leased Date], "<=" & ($Q$2 - 7), unit_details[Beds], 1, unit_details[Property Name], B22) -> 0 | H23: =IFERROR(AVERAGEIFS(unit_details[Asking Rent],unit_details[Leased Date], ">=" & ($Q$2 - 7), unit_details[Leased Date], "<" & $Q$2, unit_details[Beds], 1, unit_details[Property Name], B22),"") | I23: =IFERROR( AVERAGEIFS(unit_details[Asking Rent], unit_details[Leased Date], ">=" & ($Q$2 - 7), unit_details[Leased Date], "<" & $Q$2, unit_details[Beds], 1, unit_details[Property Name], B22) - AVERAGEIFS(unit_details[Asking Rent], unit_details[Leased Date], ">=" & ($Q$2 - 14), unit_details[Leased Date], "<=" & ($Q$2 - 7), unit_details[Beds], 1, unit_details[Property Name], B22), 0) -> 0 | J23: =IFERROR(I23/AVERAGEIFS(unit_details[Asking Rent], unit_details[Leased Date], ">=" & ($Q$2 - 14), unit_details[Leased Date], "<=" & ($Q$2 - 7), unit_details[Beds], 1, unit_details[Property Name], B22),0) -> 0 | K23: =COUNTIFS(unit_details[First Listed], ">=" & ($Q$2 - 7), unit_details[First Listed], "<" & $Q$2, unit_details[Beds], 1, unit_details[Property Name], B22) -> 0 | L23: =COUNTIFS( unit_details[First Listed], ">=" & ($Q$2 - 7), unit_details[First Listed], "<" & $Q$2, unit_details[Beds], 1, unit_details[Property Name], B22 ) - COUNTIFS( unit_details[First Listed], ">=" & ($Q$2 - 14), unit_details[First Listed], "<=" & ($Q$2 - 7), unit_details[Beds], 1, unit_details[Property Name], B22 ) -> 0 | M23: =IFERROR(AVERAGEIFS(unit_details[Asking Rent],unit_details[First Listed],">="&($Q$2-7), unit_details[First Listed],"<="&$Q$2, unit_details[Beds],1, unit_details[Property Name],B22),"") | N23: =COUNTIFS(unit_details[Property Name], B22, unit_details[Beds], 1, unit_details[Leased Date], "") -> 7 | O23: =N23-(N23-K23+F23) -> 0 | P23: =IFERROR(AVERAGEIFS(unit_details[Asking Rent],unit_details[Property Name], B22, unit_details[Beds], 1, unit_details[Leased Date], ""),"") -> 1028.5714 | Q23: =IFERROR(N23/SUMIFS(unit_mix_table['# Units],unit_mix_table[Beds],1,unit_mix_table[Property Name],B22),"") -> 2.3333333
E24: 2 BR | F24: =COUNTIFS(unit_details[Leased Date], ">=" & ($Q$2 - 7), unit_details[Leased Date], "<" & $Q$2, unit_details[Beds], 2, unit_details[Property Name], B22) -> 0 | G24: =COUNTIFS(unit_details[Leased Date], ">=" & ($Q$2 - 7), unit_details[Leased Date], "<" & $Q$2, unit_details[Beds], 2, unit_details[Property Name], B22) - COUNTIFS(unit_details[Leased Date], ">=" & ($Q$2 - 14), unit_details[Leased Date], "<=" & ($Q$2 - 7), unit_details[Beds], 2, unit_details[Property Name], B22) -> 0 | H24: =IFERROR(AVERAGEIFS(unit_details[Asking Rent],unit_details[Leased Date], ">=" & ($Q$2 - 7), unit_details[Leased Date], "<" & $Q$2, unit_details[Beds], 2, unit_details[Property Name], B22),"") | I24: =IFERROR( AVERAGEIFS(unit_details[Asking Rent], unit_details[Leased Date], ">=" & ($Q$2 - 7), unit_details[Leased Date], "<" & $Q$2, unit_details[Beds], 2, unit_details[Property Name], B22) - AVERAGEIFS(unit_details[Asking Rent], unit_details[Leased Date], ">=" & ($Q$2 - 14), unit_details[Leased Date], "<=" & ($Q$2 - 7), unit_details[Beds], 2, unit_details[Property Name], B22), 0) -> 0 | J24: =IFERROR(I24/AVERAGEIFS(unit_details[Asking Rent], unit_details[Leased Date], ">=" & ($Q$2 - 14), unit_details[Leased Date], "<=" & ($Q$2 - 7), unit_details[Beds], 2, unit_details[Property Name], B22),0) -> 0 | K24: =COUNTIFS(unit_details[First Listed], ">=" & ($Q$2 - 7), unit_details[First Listed], "<" & $Q$2, unit_details[Beds], 2, unit_details[Property Name], B22) -> 0 | L24: =COUNTIFS( unit_details[First Listed], ">=" & ($Q$2 - 7), unit_details[First Listed], "<" & $Q$2, unit_details[Beds], 2, unit_details[Property Name], B22 ) - COUNTIFS( unit_details[First Listed], ">=" & ($Q$2 - 14), unit_details[First Listed], "<=" & ($Q$2 - 7), unit_details[Beds], 2, unit_details[Property Name], B22 ) -> 0 | M24: =IFERROR(AVERAGEIFS(unit_details[Asking Rent],unit_details[First Listed],">="&($Q$2-7), unit_details[First Listed],"<="&$Q$2, unit_details[Beds],2, unit_details[Property Name],B22),"") | N24: =COUNTIFS(unit_details[Property Name], B22, unit_details[Beds], 2, unit_details[Leased Date], "") -> 9 | O24: =N24-(N24-K24+F24) -> 0 | P24: =IFERROR(AVERAGEIFS(unit_details[Asking Rent],unit_details[Property Name], B22, unit_details[Beds], 2, unit_details[Leased Date], ""),"") -> 1211.1111 | Q24: =IFERROR(N24/SUMIFS(unit_mix_table['# Units],unit_mix_table[Beds],2,unit_mix_table[Property Name],B22),"") -> 1.5
B25: https://areabest.net | E25: 3 BR | F25: =COUNTIFS(unit_details[Leased Date], ">=" & ($Q$2 - 7), unit_details[Leased Date], "<" & $Q$2, unit_details[Beds], 3, unit_details[Property Name], B22) -> 0 | G25: =COUNTIFS(unit_details[Leased Date], ">=" & ($Q$2 - 7), unit_details[Leased Date], "<" & $Q$2, unit_details[Beds], 3, unit_details[Property Name], B22) - COUNTIFS(unit_details[Leased Date], ">=" & ($Q$2 - 14), unit_details[Leased Date], "<=" & ($Q$2 - 7), unit_details[Beds], 3, unit_details[Property Name], B22) -> 0 | H25: =IFERROR(AVERAGEIFS(unit_details[Asking Rent],unit_details[Leased Date], ">=" & ($Q$2 - 7), unit_details[Leased Date], "<" & $Q$2, unit_details[Beds], 3, unit_details[Property Name], B22),"") | I25: =IFERROR( AVERAGEIFS(unit_details[Asking Rent], unit_details[Leased Date], ">=" & ($Q$2 - 7), unit_details[Leased Date], "<" & $Q$2, unit_details[Beds], 3, unit_details[Property Name], B22) - AVERAGEIFS(unit_details[Asking Rent], unit_details[Leased Date], ">=" & ($Q$2 - 14), unit_details[Leased Date], "<=" & ($Q$2 - 7), unit_details[Beds], 3, unit_details[Property Name], B22), 0) -> 0 | J25: =IFERROR(I25/AVERAGEIFS(unit_details[Asking Rent], unit_details[Leased Date], ">=" & ($Q$2 - 14), unit_details[Leased Date], "<=" & ($Q$2 - 7), unit_details[Beds], 3, unit_details[Property Name], B22),0) -> 0 | K25: =COUNTIFS(unit_details[First Listed], ">=" & ($Q$2 - 7), unit_details[First Listed], "<" & $Q$2, unit_details[Beds], 3, unit_details[Property Name], B22) -> 0 | L25: =COUNTIFS( unit_details[First Listed], ">=" & ($Q$2 - 7), unit_details[First Listed], "<" & $Q$2, unit_details[Beds], 3, unit_details[Property Name], B22 ) - COUNTIFS( unit_details[First Listed], ">=" & ($Q$2 - 14), unit_details[First Listed], "<=" & ($Q$2 - 7), unit_details[Beds], 3, unit_details[Property Name], B22 ) -> 0 | M25: =IFERROR(AVERAGEIFS(unit_details[Asking Rent],unit_details[First Listed],">="&($Q$2-7), unit_details[First Listed],"<="&$Q$2, unit_details[Beds],3, unit_details[Property Name],B22),"") | N25: =COUNTIFS(unit_details[Property Name], B22, unit_details[Beds], 3, unit_details[Leased Date], "") -> 0 | O25: =N25-(N25-K25+F25) -> 0 | P25: =IFERROR(AVERAGEIFS(unit_details[Asking Rent],unit_details[Property Name], B22, unit_details[Beds], 3, unit_details[Leased Date], ""),"") | Q25: =IFERROR(N25/SUMIFS(unit_mix_table['# Units],unit_mix_table[Beds],3,unit_mix_table[Property Name],B22),"")
B26: =IF(ISBLANK(OFFSET('Rent Comparison'!$A$1,2,10)),"",IF(OFFSET('Rent Comparison'!$A$1,2,10)=0,B27,OFFSET('Rent Comparison'!$A$1,2,10))) | C26: =IF(ISBLANK(B26),"",IFERROR(INDEX(Specials!B:J,MATCH(B26&" - Active",Specials!I:I,0),2),"")) | E26: Studio | F26: =COUNTIFS(unit_details[Leased Date], ">=" & ($Q$2 - 7), unit_details[Leased Date], "<" & $Q$2, unit_details[Beds], 0, unit_details[Property Name], B26) -> 0 | G26: =COUNTIFS(unit_details[Leased Date], ">=" & ($Q$2 - 7), unit_details[Leased Date], "<" & $Q$2, unit_details[Beds], 0, unit_details[Property Name], B26) - COUNTIFS(unit_details[Leased Date], ">=" & ($Q$2 - 14), unit_details[Leased Date], "<=" & ($Q$2 - 7), unit_details[Beds], 0, unit_details[Property Name], B26) -> 0 | H26: =IFERROR(AVERAGEIFS(unit_details[Asking Rent],unit_details[Leased Date], ">=" & ($Q$2 - 7), unit_details[Leased Date], "<" & $Q$2, unit_details[Beds], 0, unit_details[Property Name], B26),"") | I26: =IFERROR( AVERAGEIFS(unit_details[Asking Rent], unit_details[Leased Date], ">=" & ($Q$2 - 7), unit_details[Leased Date], "<" & $Q$2, unit_details[Beds], 0, unit_details[Property Name], B26) - AVERAGEIFS(unit_details[Asking Rent], unit_details[Leased Date], ">=" & ($Q$2 - 14), unit_details[Leased Date], "<=" & ($Q$2 - 7), unit_details[Beds], 0, unit_details[Property Name], B26), 0) -> 0 | J26: =IFERROR(I26/AVERAGEIFS(unit_details[Asking Rent], unit_details[Leased Date], ">=" & ($Q$2 - 14), unit_details[Leased Date], "<=" & ($Q$2 - 7), unit_details[Beds], 0, unit_details[Property Name], B26),0) -> 0 | K26: =COUNTIFS(unit_details[First Listed], ">=" & ($Q$2 - 7), unit_details[First Listed], "<" & $Q$2, unit_details[Beds], 0, unit_details[Property Name], B26) -> 0 | L26: =COUNTIFS( unit_details[First Listed], ">=" & ($Q$2 - 7), unit_details[First Listed], "<" & $Q$2, unit_details[Beds], 0, unit_details[Property Name], B26 ) - COUNTIFS( unit_details[First Listed], ">=" & ($Q$2 - 14), unit_details[First Listed], "<=" & ($Q$2 - 7), unit_details[Beds], 0, unit_details[Property Name], B26 ) -> 0 | M26: =IFERROR(AVERAGEIFS(unit_details[Asking Rent],unit_details[First Listed],">="&($Q$2-7), unit_details[First Listed],"<="&$Q$2, unit_details[Beds],0, unit_details[Property Name],B26),"") | N26: =COUNTIFS(unit_details[Property Name], B26, unit_details[Beds], 0, unit_details[Leased Date], "") -> 0 | O26: =N26-(N26-K26+F26) -> 0 | P26: =IFERROR(AVERAGEIFS(unit_details[Asking Rent],unit_details[Property Name], B26, unit_details[Beds], 0, unit_details[Leased Date], ""),"") | Q26: =IFERROR(N26/SUMIFS(unit_mix_table['# Units],unit_mix_table[Beds],0,unit_mix_table[Property Name],B26),"")
B27: 260 Meeker Street, Delta, CO 81416 | E27: 1 BR | F27: =COUNTIFS(unit_details[Leased Date], ">=" & ($Q$2 - 7), unit_details[Leased Date], "<" & $Q$2, unit_details[Beds], 1, unit_details[Property Name], B26) -> 0 | G27: =COUNTIFS(unit_details[Leased Date], ">=" & ($Q$2 - 7), unit_details[Leased Date], "<" & $Q$2, unit_details[Beds], 1, unit_details[Property Name], B26) - COUNTIFS(unit_details[Leased Date], ">=" & ($Q$2 - 14), unit_details[Leased Date], "<=" & ($Q$2 - 7), unit_details[Beds], 1, unit_details[Property Name], B26) -> 0 | H27: =IFERROR(AVERAGEIFS(unit_details[Asking Rent],unit_details[Leased Date], ">=" & ($Q$2 - 7), unit_details[Leased Date], "<" & $Q$2, unit_details[Beds], 1, unit_details[Property Name], B26),"") | I27: =IFERROR( AVERAGEIFS(unit_details[Asking Rent], unit_details[Leased Date], ">=" & ($Q$2 - 7), unit_details[Leased Date], "<" & $Q$2, unit_details[Beds], 1, unit_details[Property Name], B26) - AVERAGEIFS(unit_details[Asking Rent], unit_details[Leased Date], ">=" & ($Q$2 - 14), unit_details[Leased Date], "<=" & ($Q$2 - 7), unit_details[Beds], 1, unit_details[Property Name], B26), 0) -> 0 | J27: =IFERROR(I27/AVERAGEIFS(unit_details[Asking Rent], unit_details[Leased Date], ">=" & ($Q$2 - 14), unit_details[Leased Date], "<=" & ($Q$2 - 7), unit_details[Beds], 1, unit_details[Property Name], B26),0) -> 0 | K27: =COUNTIFS(unit_details[First Listed], ">=" & ($Q$2 - 7), unit_details[First Listed], "<" & $Q$2, unit_details[Beds], 1, unit_details[Property Name], B26) -> 0 | L27: =COUNTIFS( unit_details[First Listed], ">=" & ($Q$2 - 7), unit_details[First Listed], "<" & $Q$2, unit_details[Beds], 1, unit_details[Property Name], B26 ) - COUNTIFS( unit_details[First Listed], ">=" & ($Q$2 - 14), unit_details[First Listed], "<=" & ($Q$2 - 7), unit_details[Beds], 1, unit_details[Property Name], B26 ) -> 0 | M27: =IFERROR(AVERAGEIFS(unit_details[Asking Rent],unit_details[First Listed],">="&($Q$2-7), unit_details[First Listed],"<="&$Q$2, unit_details[Beds],1, unit_details[Property Name],B26),"") | N27: =COUNTIFS(unit_details[Property Name], B26, unit_details[Beds], 1, unit_details[Leased Date], "") -> 7 | O27: =N27-(N27-K27+F27) -> 0 | P27: =IFERROR(AVERAGEIFS(unit_details[Asking Rent],unit_details[Property Name], B26, unit_details[Beds], 1, unit_details[Leased Date], ""),"") -> 1028.5714 | Q27: =IFERROR(N27/SUMIFS(unit_mix_table['# Units],unit_mix_table[Beds],1,unit_mix_table[Property Name],B26),"") -> 2.3333333
E28: 2 BR | F28: =COUNTIFS(unit_details[Leased Date], ">=" & ($Q$2 - 7), unit_details[Leased Date], "<" & $Q$2, unit_details[Beds], 2, unit_details[Property Name], B26) -> 0 | G28: =COUNTIFS(unit_details[Leased Date], ">=" & ($Q$2 - 7), unit_details[Leased Date], "<" & $Q$2, unit_details[Beds], 2, unit_details[Property Name], B26) - COUNTIFS(unit_details[Leased Date], ">=" & ($Q$2 - 14), unit_details[Leased Date], "<=" & ($Q$2 - 7), unit_details[Beds], 2, unit_details[Property Name], B26) -> 0 | H28: =IFERROR(AVERAGEIFS(unit_details[Asking Rent],unit_details[Leased Date], ">=" & ($Q$2 - 7), unit_details[Leased Date], "<" & $Q$2, unit_details[Beds], 2, unit_details[Property Name], B26),"") | I28: =IFERROR( AVERAGEIFS(unit_details[Asking Rent], unit_details[Leased Date], ">=" & ($Q$2 - 7), unit_details[Leased Date], "<" & $Q$2, unit_details[Beds], 2, unit_details[Property Name], B26) - AVERAGEIFS(unit_details[Asking Rent], unit_details[Leased Date], ">=" & ($Q$2 - 14), unit_details[Leased Date], "<=" & ($Q$2 - 7), unit_details[Beds], 2, unit_details[Property Name], B26), 0) -> 0 | J28: =IFERROR(I28/AVERAGEIFS(unit_details[Asking Rent], unit_details[Leased Date], ">=" & ($Q$2 - 14), unit_details[Leased Date], "<=" & ($Q$2 - 7), unit_details[Beds], 2, unit_details[Property Name], B26),0) -> 0 | K28: =COUNTIFS(unit_details[First Listed], ">=" & ($Q$2 - 7), unit_details[First Listed], "<" & $Q$2, unit_details[Beds], 2, unit_details[Property Name], B26) -> 0 | L28: =COUNTIFS( unit_details[First Listed], ">=" & ($Q$2 - 7), unit_details[First Listed], "<" & $Q$2, unit_details[Beds], 2, unit_details[Property Name], B26 ) - COUNTIFS( unit_details[First Listed], ">=" & ($Q$2 - 14), unit_details[First Listed], "<=" & ($Q$2 - 7), unit_details[Beds], 2, unit_details[Property Name], B26 ) -> 0 | M28: =IFERROR(AVERAGEIFS(unit_details[Asking Rent],unit_details[First Listed],">="&($Q$2-7), unit_details[First Listed],"<="&$Q$2, unit_details[Beds],2, unit_details[Property Name],B26),"") | N28: =COUNTIFS(unit_details[Property Name], B26, unit_details[Beds], 2, unit_details[Leased Date], "") -> 9 | O28: =N28-(N28-K28+F28) -> 0 | P28: =IFERROR(AVERAGEIFS(unit_details[Asking Rent],unit_details[Property Name], B26, unit_details[Beds], 2, unit_details[Leased Date], ""),"") -> 1211.1111 | Q28: =IFERROR(N28/SUMIFS(unit_mix_table['# Units],unit_mix_table[Beds],2,unit_mix_table[Property Name],B26),"") -> 1.5
B29: https://areabest.net | E29: 3 BR | F29: =COUNTIFS(unit_details[Leased Date], ">=" & ($Q$2 - 7), unit_details[Leased Date], "<" & $Q$2, unit_details[Beds], 3, unit_details[Property Name], B26) -> 0 | G29: =COUNTIFS(unit_details[Leased Date], ">=" & ($Q$2 - 7), unit_details[Leased Date], "<" & $Q$2, unit_details[Beds], 3, unit_details[Property Name], B26) - COUNTIFS(unit_details[Leased Date], ">=" & ($Q$2 - 14), unit_details[Leased Date], "<=" & ($Q$2 - 7), unit_details[Beds], 3, unit_details[Property Name], B26) -> 0 | H29: =IFERROR(AVERAGEIFS(unit_details[Asking Rent],unit_details[Leased Date], ">=" & ($Q$2 - 7), unit_details[Leased Date], "<" & $Q$2, unit_details[Beds], 3, unit_details[Property Name], B26),"") | I29: =IFERROR( AVERAGEIFS(unit_details[Asking Rent], unit_details[Leased Date], ">=" & ($Q$2 - 7), unit_details[Leased Date], "<" & $Q$2, unit_details[Beds], 3, unit_details[Property Name], B26) - AVERAGEIFS(unit_details[Asking Rent], unit_details[Leased Date], ">=" & ($Q$2 - 14), unit_details[Leased Date], "<=" & ($Q$2 - 7), unit_details[Beds], 3, unit_details[Property Name], B26), 0) -> 0 | J29: =IFERROR(I29/AVERAGEIFS(unit_details[Asking Rent], unit_details[Leased Date], ">=" & ($Q$2 - 14), unit_details[Leased Date], "<=" & ($Q$2 - 7), unit_details[Beds], 3, unit_details[Property Name], B26),0) -> 0 | K29: =COUNTIFS(unit_details[First Listed], ">=" & ($Q$2 - 7), unit_details[First Listed], "<" & $Q$2, unit_details[Beds], 3, unit_details[Property Name], B26) -> 0 | L29: =COUNTIFS( unit_details[First Listed], ">=" & ($Q$2 - 7), unit_details[First Listed], "<" & $Q$2, unit_details[Beds], 3, unit_details[Property Name], B26 ) - COUNTIFS( unit_details[First Listed], ">=" & ($Q$2 - 14), unit_details[First Listed], "<=" & ($Q$2 - 7), unit_details[Beds], 3, unit_details[Property Name], B26 ) -> 0 | M29: =IFERROR(AVERAGEIFS(unit_details[Asking Rent],unit_details[First Listed],">="&($Q$2-7), unit_details[First Listed],"<="&$Q$2, unit_details[Beds],3, unit_details[Property Name],B26),"") | N29: =COUNTIFS(unit_details[Property Name], B26, unit_details[Beds], 3, unit_details[Leased Date], "") -> 0 | O29: =N29-(N29-K29+F29) -> 0 | P29: =IFERROR(AVERAGEIFS(unit_details[Asking Rent],unit_details[Property Name], B26, unit_details[Beds], 3, unit_details[Leased Date], ""),"") | Q29: =IFERROR(N29/SUMIFS(unit_mix_table['# Units],unit_mix_table[Beds],3,unit_mix_table[Property Name],B26),"")
B30: =IF(ISBLANK(OFFSET('Rent Comparison'!$A$1,2,11)),"",IF(OFFSET('Rent Comparison'!$A$1,2,11)=0,B31,OFFSET('Rent Comparison'!$A$1,2,11))) -> 816 Dodge St, Delta CO | C30: =IF(ISBLANK(B30),"",IFERROR(INDEX(Specials!B:J,MATCH(B30&" - Active",Specials!I:I,0),2),"")) | E30: Studio | F30: =COUNTIFS(unit_details[Leased Date], ">=" & ($Q$2 - 7), unit_details[Leased Date], "<" & $Q$2, unit_details[Beds], 0, unit_details[Property Name], B30) -> 0 | G30: =COUNTIFS(unit_details[Leased Date], ">=" & ($Q$2 - 7), unit_details[Leased Date], "<" & $Q$2, unit_details[Beds], 0, unit_details[Property Name], B30) - COUNTIFS(unit_details[Leased Date], ">=" & ($Q$2 - 14), unit_details[Leased Date], "<=" & ($Q$2 - 7), unit_details[Beds], 0, unit_details[Property Name], B30) -> 0 | H30: =IFERROR(AVERAGEIFS(unit_details[Asking Rent],unit_details[Leased Date], ">=" & ($Q$2 - 7), unit_details[Leased Date], "<" & $Q$2, unit_details[Beds], 0, unit_details[Property Name], B30),"") | I30: =IFERROR( AVERAGEIFS(unit_details[Asking Rent], unit_details[Leased Date], ">=" & ($Q$2 - 7), unit_details[Leased Date], "<" & $Q$2, unit_details[Beds], 0, unit_details[Property Name], B30) - AVERAGEIFS(unit_details[Asking Rent], unit_details[Leased Date], ">=" & ($Q$2 - 14), unit_details[Leased Date], "<=" & ($Q$2 - 7), unit_details[Beds], 0, unit_details[Property Name], B30), 0) -> 0 | J30: =IFERROR(I30/AVERAGEIFS(unit_details[Asking Rent], unit_details[Leased Date], ">=" & ($Q$2 - 14), unit_details[Leased Date], "<=" & ($Q$2 - 7), unit_details[Beds], 0, unit_details[Property Name], B30),0) -> 0 | K30: =COUNTIFS(unit_details[First Listed], ">=" & ($Q$2 - 7), unit_details[First Listed], "<" & $Q$2, unit_details[Beds], 0, unit_details[Property Name], B30) -> 0 | L30: =COUNTIFS( unit_details[First Listed], ">=" & ($Q$2 - 7), unit_details[First Listed], "<" & $Q$2, unit_details[Beds], 0, unit_details[Property Name], B30 ) - COUNTIFS( unit_details[First Listed], ">=" & ($Q$2 - 14), unit_details[First Listed], "<=" & ($Q$2 - 7), unit_details[Beds], 0, unit_details[Property Name], B30 ) -> 0 | M30: =IFERROR(AVERAGEIFS(unit_details[Asking Rent],unit_details[First Listed],">="&($Q$2-7), unit_details[First Listed],"<="&$Q$2, unit_details[Beds],0, unit_details[Property Name],B30),"") | N30: =COUNTIFS(unit_details[Property Name], B30, unit_details[Beds], 0, unit_details[Leased Date], "") -> 0 | O30: =N30-(N30-K30+F30) -> 0 | P30: =IFERROR(AVERAGEIFS(unit_details[Asking Rent],unit_details[Property Name], B30, unit_details[Beds], 0, unit_details[Leased Date], ""),"") | Q30: =IFERROR(N30/SUMIFS(unit_mix_table['# Units],unit_mix_table[Beds],0,unit_mix_table[Property Name],B30),"")
B31: 816 Dodge Street, Delta, CO 81416 | E31: 1 BR | F31: =COUNTIFS(unit_details[Leased Date], ">=" & ($Q$2 - 7), unit_details[Leased Date], "<" & $Q$2, unit_details[Beds], 1, unit_details[Property Name], B30) -> 0 | G31: =COUNTIFS(unit_details[Leased Date], ">=" & ($Q$2 - 7), unit_details[Leased Date], "<" & $Q$2, unit_details[Beds], 1, unit_details[Property Name], B30) - COUNTIFS(unit_details[Leased Date], ">=" & ($Q$2 - 14), unit_details[Leased Date], "<=" & ($Q$2 - 7), unit_details[Beds], 1, unit_details[Property Name], B30) -> 0 | H31: =IFERROR(AVERAGEIFS(unit_details[Asking Rent],unit_details[Leased Date], ">=" & ($Q$2 - 7), unit_details[Leased Date], "<" & $Q$2, unit_details[Beds], 1, unit_details[Property Name], B30),"") | I31: =IFERROR( AVERAGEIFS(unit_details[Asking Rent], unit_details[Leased Date], ">=" & ($Q$2 - 7), unit_details[Leased Date], "<" & $Q$2, unit_details[Beds], 1, unit_details[Property Name], B30) - AVERAGEIFS(unit_details[Asking Rent], unit_details[Leased Date], ">=" & ($Q$2 - 14), unit_details[Leased Date], "<=" & ($Q$2 - 7), unit_details[Beds], 1, unit_details[Property Name], B30), 0) -> 0 | J31: =IFERROR(I31/AVERAGEIFS(unit_details[Asking Rent], unit_details[Leased Date], ">=" & ($Q$2 - 14), unit_details[Leased Date], "<=" & ($Q$2 - 7), unit_details[Beds], 1, unit_details[Property Name], B30),0) -> 0 | K31: =COUNTIFS(unit_details[First Listed], ">=" & ($Q$2 - 7), unit_details[First Listed], "<" & $Q$2, unit_details[Beds], 1, unit_details[Property Name], B30) -> 0 | L31: =COUNTIFS( unit_details[First Listed], ">=" & ($Q$2 - 7), unit_details[First Listed], "<" & $Q$2, unit_details[Beds], 1, unit_details[Property Name], B30 ) - COUNTIFS( unit_details[First Listed], ">=" & ($Q$2 - 14), unit_details[First Listed], "<=" & ($Q$2 - 7), unit_details[Beds], 1, unit_details[Property Name], B30 ) -> 0 | M31: =IFERROR(AVERAGEIFS(unit_details[Asking Rent],unit_details[First Listed],">="&($Q$2-7), unit_details[First Listed],"<="&$Q$2, unit_details[Beds],1, unit_details[Property Name],B30),"") | N31: =COUNTIFS(unit_details[Property Name], B30, unit_details[Beds], 1, unit_details[Leased Date], "") -> 0 | O31: =N31-(N31-K31+F31) -> 0 | P31: =IFERROR(AVERAGEIFS(unit_details[Asking Rent],unit_details[Property Name], B30, unit_details[Beds], 1, unit_details[Leased Date], ""),"") | Q31: =IFERROR(N31/SUMIFS(unit_mix_table['# Units],unit_mix_table[Beds],1,unit_mix_table[Property Name],B30),"")
E32: 2 BR | F32: =COUNTIFS(unit_details[Leased Date], ">=" & ($Q$2 - 7), unit_details[Leased Date], "<" & $Q$2, unit_details[Beds], 2, unit_details[Property Name], B30) -> 0 | G32: =COUNTIFS(unit_details[Leased Date], ">=" & ($Q$2 - 7), unit_details[Leased Date], "<" & $Q$2, unit_details[Beds], 2, unit_details[Property Name], B30) - COUNTIFS(unit_details[Leased Date], ">=" & ($Q$2 - 14), unit_details[Leased Date], "<=" & ($Q$2 - 7), unit_details[Beds], 2, unit_details[Property Name], B30) -> 0 | H32: =IFERROR(AVERAGEIFS(unit_details[Asking Rent],unit_details[Leased Date], ">=" & ($Q$2 - 7), unit_details[Leased Date], "<" & $Q$2, unit_details[Beds], 2, unit_details[Property Name], B30),"") | I32: =IFERROR( AVERAGEIFS(unit_details[Asking Rent], unit_details[Leased Date], ">=" & ($Q$2 - 7), unit_details[Leased Date], "<" & $Q$2, unit_details[Beds], 2, unit_details[Property Name], B30) - AVERAGEIFS(unit_details[Asking Rent], unit_details[Leased Date], ">=" & ($Q$2 - 14), unit_details[Leased Date], "<=" & ($Q$2 - 7), unit_details[Beds], 2, unit_details[Property Name], B30), 0) -> 0 | J32: =IFERROR(I32/AVERAGEIFS(unit_details[Asking Rent], unit_details[Leased Date], ">=" & ($Q$2 - 14), unit_details[Leased Date], "<=" & ($Q$2 - 7), unit_details[Beds], 2, unit_details[Property Name], B30),0) -> 0 | K32: =COUNTIFS(unit_details[First Listed], ">=" & ($Q$2 - 7), unit_details[First Listed], "<" & $Q$2, unit_details[Beds], 2, unit_details[Property Name], B30) -> 0 | L32: =COUNTIFS( unit_details[First Listed], ">=" & ($Q$2 - 7), unit_details[First Listed], "<" & $Q$2, unit_details[Beds], 2, unit_details[Property Name], B30 ) - COUNTIFS( unit_details[First Listed], ">=" & ($Q$2 - 14), unit_details[First Listed], "<=" & ($Q$2 - 7), unit_details[Beds], 2, unit_details[Property Name], B30 ) -> 0 | M32: =IFERROR(AVERAGEIFS(unit_details[Asking Rent],unit_details[First Listed],">="&($Q$2-7), unit_details[First Listed],"<="&$Q$2, unit_details[Beds],2, unit_details[Property Name],B30),"") | N32: =COUNTIFS(unit_details[Property Name], B30, unit_details[Beds], 2, unit_details[Leased Date], "") -> 0 | O32: =N32-(N32-K32+F32) -> 0 | P32: =IFERROR(AVERAGEIFS(unit_details[Asking Rent],unit_details[Property Name], B30, unit_details[Beds], 2, unit_details[Leased Date], ""),"") | Q32: =IFERROR(N32/SUMIFS(unit_mix_table['# Units],unit_mix_table[Beds],2,unit_mix_table[Property Name],B30),"")
E33: 3 BR | F33: =COUNTIFS(unit_details[Leased Date], ">=" & ($Q$2 - 7), unit_details[Leased Date], "<" & $Q$2, unit_details[Beds], 3, unit_details[Property Name], B30) -> 0 | G33: =COUNTIFS(unit_details[Leased Date], ">=" & ($Q$2 - 7), unit_details[Leased Date], "<" & $Q$2, unit_details[Beds], 3, unit_details[Property Name], B30) - COUNTIFS(unit_details[Leased Date], ">=" & ($Q$2 - 14), unit_details[Leased Date], "<=" & ($Q$2 - 7), unit_details[Beds], 3, unit_details[Property Name], B30) -> 0 | H33: =IFERROR(AVERAGEIFS(unit_details[Asking Rent],unit_details[Leased Date], ">=" & ($Q$2 - 7), unit_details[Leased Date], "<" & $Q$2, unit_details[Beds], 3, unit_details[Property Name], B30),"") | I33: =IFERROR( AVERAGEIFS(unit_details[Asking Rent], unit_details[Leased Date], ">=" & ($Q$2 - 7), unit_details[Leased Date], "<" & $Q$2, unit_details[Beds], 3, unit_details[Property Name], B30) - AVERAGEIFS(unit_details[Asking Rent], unit_details[Leased Date], ">=" & ($Q$2 - 14), unit_details[Leased Date], "<=" & ($Q$2 - 7), unit_details[Beds], 3, unit_details[Property Name], B30), 0) -> 0 | J33: =IFERROR(I33/AVERAGEIFS(unit_details[Asking Rent], unit_details[Leased Date], ">=" & ($Q$2 - 14), unit_details[Leased Date], "<=" & ($Q$2 - 7), unit_details[Beds], 3, unit_details[Property Name], B30),0) -> 0 | K33: =COUNTIFS(unit_details[First Listed], ">=" & ($Q$2 - 7), unit_details[First Listed], "<" & $Q$2, unit_details[Beds], 3, unit_details[Property Name], B30) -> 0 | L33: =COUNTIFS( unit_details[First Listed], ">=" & ($Q$2 - 7), unit_details[First Listed], "<" & $Q$2, unit_details[Beds], 3, unit_details[Property Name], B30 ) - COUNTIFS( unit_details[First Listed], ">=" & ($Q$2 - 14), unit_details[First Listed], "<=" & ($Q$2 - 7), unit_details[Beds], 3, unit_details[Property Name], B30 ) -> 0 | M33: =IFERROR(AVERAGEIFS(unit_details[Asking Rent],unit_details[First Listed],">="&($Q$2-7), unit_details[First Listed],"<="&$Q$2, unit_details[Beds],3, unit_details[Property Name],B30),"") | N33: =COUNTIFS(unit_details[Property Name], B30, unit_details[Beds], 3, unit_details[Leased Date], "") -> 0 | O33: =N33-(N33-K33+F33) -> 0 | P33: =IFERROR(AVERAGEIFS(unit_details[Asking Rent],unit_details[Property Name], B30, unit_details[Beds], 3, unit_details[Leased Date], ""),"") | Q33: =IFERROR(N33/SUMIFS(unit_mix_table['# Units],unit_mix_table[Beds],3,unit_mix_table[Property Name],B30),"")
B34: =IF(ISBLANK(OFFSET('Rent Comparison'!$A$1,2,12)),"",IF(OFFSET('Rent Comparison'!$A$1,2,12)=0,B35,OFFSET('Rent Comparison'!$A$1,2,12))) | C34: =IF(ISBLANK(B34),"",IFERROR(INDEX(Specials!B:J,MATCH(B34&" - Active",Specials!I:I,0),2),"")) | E34: Studio | F34: =COUNTIFS(unit_details[Leased Date], ">=" & ($Q$2 - 7), unit_details[Leased Date], "<" & $Q$2, unit_details[Beds], 0, unit_details[Property Name], B34) -> 0 | G34: =COUNTIFS(unit_details[Leased Date], ">=" & ($Q$2 - 7), unit_details[Leased Date], "<" & $Q$2, unit_details[Beds], 0, unit_details[Property Name], B34) - COUNTIFS(unit_details[Leased Date], ">=" & ($Q$2 - 14), unit_details[Leased Date], "<=" & ($Q$2 - 7), unit_details[Beds], 0, unit_details[Property Name], B34) -> 0 | H34: =IFERROR(AVERAGEIFS(unit_details[Asking Rent],unit_details[Leased Date], ">=" & ($Q$2 - 7), unit_details[Leased Date], "<" & $Q$2, unit_details[Beds], 0, unit_details[Property Name], B34),"") | I34: =IFERROR( AVERAGEIFS(unit_details[Asking Rent], unit_details[Leased Date], ">=" & ($Q$2 - 7), unit_details[Leased Date], "<" & $Q$2, unit_details[Beds], 0, unit_details[Property Name], B34) - AVERAGEIFS(unit_details[Asking Rent], unit_details[Leased Date], ">=" & ($Q$2 - 14), unit_details[Leased Date], "<=" & ($Q$2 - 7), unit_details[Beds], 0, unit_details[Property Name], B34), 0) -> 0 | J34: =IFERROR(I34/AVERAGEIFS(unit_details[Asking Rent], unit_details[Leased Date], ">=" & ($Q$2 - 14), unit_details[Leased Date], "<=" & ($Q$2 - 7), unit_details[Beds], 0, unit_details[Property Name], B34),0) -> 0 | K34: =COUNTIFS(unit_details[First Listed], ">=" & ($Q$2 - 7), unit_details[First Listed], "<" & $Q$2, unit_details[Beds], 0, unit_details[Property Name], B34) -> 0 | L34: =COUNTIFS( unit_details[First Listed], ">=" & ($Q$2 - 7), unit_details[First Listed], "<" & $Q$2, unit_details[Beds], 0, unit_details[Property Name], B34 ) - COUNTIFS( unit_details[First Listed], ">=" & ($Q$2 - 14), unit_details[First Listed], "<=" & ($Q$2 - 7), unit_details[Beds], 0, unit_details[Property Name], B34 ) -> 0 | M34: =IFERROR(AVERAGEIFS(unit_details[Asking Rent],unit_details[First Listed],">="&($Q$2-7), unit_details[First Listed],"<="&$Q$2, unit_details[Beds],0, unit_details[Property Name],B34),"") | N34: =COUNTIFS(unit_details[Property Name], B34, unit_details[Beds], 0, unit_details[Leased Date], "") -> 0 | O34: =N34-(N34-K34+F34) -> 0 | P34: =IFERROR(AVERAGEIFS(unit_details[Asking Rent],unit_details[Property Name], B34, unit_details[Beds], 0, unit_details[Leased Date], ""),"") | Q34: =IFERROR(N34/SUMIFS(unit_mix_table['# Units],unit_mix_table[Beds],0,unit_mix_table[Property Name],B34),"")
B35: 215 Rich Street, Delta, CO 81416 | E35: 1 BR | F35: =COUNTIFS(unit_details[Leased Date], ">=" & ($Q$2 - 7), unit_details[Leased Date], "<" & $Q$2, unit_details[Beds], 1, unit_details[Property Name], B34) -> 0 | G35: =COUNTIFS(unit_details[Leased Date], ">=" & ($Q$2 - 7), unit_details[Leased Date], "<" & $Q$2, unit_details[Beds], 1, unit_details[Property Name], B34) - COUNTIFS(unit_details[Leased Date], ">=" & ($Q$2 - 14), unit_details[Leased Date], "<=" & ($Q$2 - 7), unit_details[Beds], 1, unit_details[Property Name], B34) -> 0 | H35: =IFERROR(AVERAGEIFS(unit_details[Asking Rent],unit_details[Leased Date], ">=" & ($Q$2 - 7), unit_details[Leased Date], "<" & $Q$2, unit_details[Beds], 1, unit_details[Property Name], B34),"") | I35: =IFERROR( AVERAGEIFS(unit_details[Asking Rent], unit_details[Leased Date], ">=" & ($Q$2 - 7), unit_details[Leased Date], "<" & $Q$2, unit_details[Beds], 1, unit_details[Property Name], B34) - AVERAGEIFS(unit_details[Asking Rent], unit_details[Leased Date], ">=" & ($Q$2 - 14), unit_details[Leased Date], "<=" & ($Q$2 - 7), unit_details[Beds], 1, unit_details[Property Name], B34), 0) -> 0 | J35: =IFERROR(I35/AVERAGEIFS(unit_details[Asking Rent], unit_details[Leased Date], ">=" & ($Q$2 - 14), unit_details[Leased Date], "<=" & ($Q$2 - 7), unit_details[Beds], 1, unit_details[Property Name], B34),0) -> 0 | K35: =COUNTIFS(unit_details[First Listed], ">=" & ($Q$2 - 7), unit_details[First Listed], "<" & $Q$2, unit_details[Beds], 1, unit_details[Property Name], B34) -> 0 | L35: =COUNTIFS( unit_details[First Listed], ">=" & ($Q$2 - 7), unit_details[First Listed], "<" & $Q$2, unit_details[Beds], 1, unit_details[Property Name], B34 ) - COUNTIFS( unit_details[First Listed], ">=" & ($Q$2 - 14), unit_details[First Listed], "<=" & ($Q$2 - 7), unit_details[Beds], 1, unit_details[Property Name], B34 ) -> 0 | M35: =IFERROR(AVERAGEIFS(unit_details[Asking Rent],unit_details[First Listed],">="&($Q$2-7), unit_details[First Listed],"<="&$Q$2, unit_details[Beds],1, unit_details[Property Name],B34),"") | N35: =COUNTIFS(unit_details[Property Name], B34, unit_details[Beds], 1, unit_details[Leased Date], "") -> 7 | O35: =N35-(N35-K35+F35) -> 0 | P35: =IFERROR(AVERAGEIFS(unit_details[Asking Rent],unit_details[Property Name], B34, unit_details[Beds], 1, unit_details[Leased Date], ""),"") -> 1028.5714 | Q35: =IFERROR(N35/SUMIFS(unit_mix_table['# Units],unit_mix_table[Beds],1,unit_mix_table[Property Name],B34),"") -> 2.3333333
E36: 2 BR | F36: =COUNTIFS(unit_details[Leased Date], ">=" & ($Q$2 - 7), unit_details[Leased Date], "<" & $Q$2, unit_details[Beds], 2, unit_details[Property Name], B34) -> 0 | G36: =COUNTIFS(unit_details[Leased Date], ">=" & ($Q$2 - 7), unit_details[Leased Date], "<" & $Q$2, unit_details[Beds], 2, unit_details[Property Name], B34) - COUNTIFS(unit_details[Leased Date], ">=" & ($Q$2 - 14), unit_details[Leased Date], "<=" & ($Q$2 - 7), unit_details[Beds], 2, unit_details[Property Name], B34) -> 0 | H36: =IFERROR(AVERAGEIFS(unit_details[Asking Rent],unit_details[Leased Date], ">=" & ($Q$2 - 7), unit_details[Leased Date], "<" & $Q$2, unit_details[Beds], 2, unit_details[Property Name], B34),"") | I36: =IFERROR( AVERAGEIFS(unit_details[Asking Rent], unit_details[Leased Date], ">=" & ($Q$2 - 7), unit_details[Leased Date], "<" & $Q$2, unit_details[Beds], 2, unit_details[Property Name], B34) - AVERAGEIFS(unit_details[Asking Rent], unit_details[Leased Date], ">=" & ($Q$2 - 14), unit_details[Leased Date], "<=" & ($Q$2 - 7), unit_details[Beds], 2, unit_details[Property Name], B34), 0) -> 0 | J36: =IFERROR(I36/AVERAGEIFS(unit_details[Asking Rent], unit_details[Leased Date], ">=" & ($Q$2 - 14), unit_details[Leased Date], "<=" & ($Q$2 - 7), unit_details[Beds], 2, unit_details[Property Name], B34),0) -> 0 | K36: =COUNTIFS(unit_details[First Listed], ">=" & ($Q$2 - 7), unit_details[First Listed], "<" & $Q$2, unit_details[Beds], 2, unit_details[Property Name], B34) -> 0 | L36: =COUNTIFS( unit_details[First Listed], ">=" & ($Q$2 - 7), unit_details[First Listed], "<" & $Q$2, unit_details[Beds], 2, unit_details[Property Name], B34 ) - COUNTIFS( unit_details[First Listed], ">=" & ($Q$2 - 14), unit_details[First Listed], "<=" & ($Q$2 - 7), unit_details[Beds], 2, unit_details[Property Name], B34 ) -> 0 | M36: =IFERROR(AVERAGEIFS(unit_details[Asking Rent],unit_details[First Listed],">="&($Q$2-7), unit_details[First Listed],"<="&$Q$2, unit_details[Beds],2, unit_details[Property Name],B34),"") | N36: =COUNTIFS(unit_details[Property Name], B34, unit_details[Beds], 2, unit_details[Leased Date], "") -> 9 | O36: =N36-(N36-K36+F36) -> 0 | P36: =IFERROR(AVERAGEIFS(unit_details[Asking Rent],unit_details[Property Name], B34, unit_details[Beds], 2, unit_details[Leased Date], ""),"") -> 1211.1111 | Q36: =IFERROR(N36/SUMIFS(unit_mix_table['# Units],unit_mix_table[Beds],2,unit_mix_table[Property Name],B34),"") -> 1.5
E37: 3 BR | F37: =COUNTIFS(unit_details[Leased Date], ">=" & ($Q$2 - 7), unit_details[Leased Date], "<" & $Q$2, unit_details[Beds], 3, unit_details[Property Name], B34) -> 0 | G37: =COUNTIFS(unit_details[Leased Date], ">=" & ($Q$2 - 7), unit_details[Leased Date], "<" & $Q$2, unit_details[Beds], 3, unit_details[Property Name], B34) - COUNTIFS(unit_details[Leased Date], ">=" & ($Q$2 - 14), unit_details[Leased Date], "<=" & ($Q$2 - 7), unit_details[Beds], 3, unit_details[Property Name], B34) -> 0 | H37: =IFERROR(AVERAGEIFS(unit_details[Asking Rent],unit_details[Leased Date], ">=" & ($Q$2 - 7), unit_details[Leased Date], "<" & $Q$2, unit_details[Beds], 3, unit_details[Property Name], B34),"") | I37: =IFERROR( AVERAGEIFS(unit_details[Asking Rent], unit_details[Leased Date], ">=" & ($Q$2 - 7), unit_details[Leased Date], "<" & $Q$2, unit_details[Beds], 3, unit_details[Property Name], B34) - AVERAGEIFS(unit_details[Asking Rent], unit_details[Leased Date], ">=" & ($Q$2 - 14), unit_details[Leased Date], "<=" & ($Q$2 - 7), unit_details[Beds], 3, unit_details[Property Name], B34), 0) -> 0 | J37: =IFERROR(I37/AVERAGEIFS(unit_details[Asking Rent], unit_details[Leased Date], ">=" & ($Q$2 - 14), unit_details[Leased Date], "<=" & ($Q$2 - 7), unit_details[Beds], 3, unit_details[Property Name], B34),0) -> 0 | K37: =COUNTIFS(unit_details[First Listed], ">=" & ($Q$2 - 7), unit_details[First Listed], "<" & $Q$2, unit_details[Beds], 3, unit_details[Property Name], B34) -> 0 | L37: =COUNTIFS( unit_details[First Listed], ">=" & ($Q$2 - 7), unit_details[First Listed], "<" & $Q$2, unit_details[Beds], 3, unit_details[Property Name], B34 ) - COUNTIFS( unit_details[First Listed], ">=" & ($Q$2 - 14), unit_details[First Listed], "<=" & ($Q$2 - 7), unit_details[Beds], 3, unit_details[Property Name], B34 ) -> 0 | M37: =IFERROR(AVERAGEIFS(unit_details[Asking Rent],unit_details[First Listed],">="&($Q$2-7), unit_details[First Listed],"<="&$Q$2, unit_details[Beds],3, unit_details[Property Name],B34),"") | N37: =COUNTIFS(unit_details[Property Name], B34, unit_details[Beds], 3, unit_details[Leased Date], "") -> 0 | O37: =N37-(N37-K37+F37) -> 0 | P37: =IFERROR(AVERAGEIFS(unit_details[Asking Rent],unit_details[Property Name], B34, unit_details[Beds], 3, unit_details[Leased Date], ""),"") | Q37: =IFERROR(N37/SUMIFS(unit_mix_table['# Units],unit_mix_table[Beds],3,unit_mix_table[Property Name],B34),"")
B38: =IF(ISBLANK(OFFSET('Rent Comparison'!$A$1,2,13)),"",IF(OFFSET('Rent Comparison'!$A$1,2,13)=0,B39,OFFSET('Rent Comparison'!$A$1,2,13))) | C38: =IF(ISBLANK(B38),"",IFERROR(INDEX(Specials!B:J,MATCH(B38&" - Active",Specials!I:I,0),2),"")) | E38: Studio | F38: =COUNTIFS(unit_details[Leased Date], ">=" & ($Q$2 - 7), unit_details[Leased Date], "<" & $Q$2, unit_details[Beds], 0, unit_details[Property Name], B38) -> 0 | G38: =COUNTIFS(unit_details[Leased Date], ">=" & ($Q$2 - 7), unit_details[Leased Date], "<" & $Q$2, unit_details[Beds], 0, unit_details[Property Name], B38) - COUNTIFS(unit_details[Leased Date], ">=" & ($Q$2 - 14), unit_details[Leased Date], "<=" & ($Q$2 - 7), unit_details[Beds], 0, unit_details[Property Name], B38) -> 0 | H38: =IFERROR(AVERAGEIFS(unit_details[Asking Rent],unit_details[Leased Date], ">=" & ($Q$2 - 7), unit_details[Leased Date], "<" & $Q$2, unit_details[Beds], 0, unit_details[Property Name], B38),"") | I38: =IFERROR( AVERAGEIFS(unit_details[Asking Rent], unit_details[Leased Date], ">=" & ($Q$2 - 7), unit_details[Leased Date], "<" & $Q$2, unit_details[Beds], 0, unit_details[Property Name], B38) - AVERAGEIFS(unit_details[Asking Rent], unit_details[Leased Date], ">=" & ($Q$2 - 14), unit_details[Leased Date], "<=" & ($Q$2 - 7), unit_details[Beds], 0, unit_details[Property Name], B38), 0) -> 0 | J38: =IFERROR(I38/AVERAGEIFS(unit_details[Asking Rent], unit_details[Leased Date], ">=" & ($Q$2 - 14), unit_details[Leased Date], "<=" & ($Q$2 - 7), unit_details[Beds], 0, unit_details[Property Name], B38),0) -> 0 | K38: =COUNTIFS(unit_details[First Listed], ">=" & ($Q$2 - 7), unit_details[First Listed], "<" & $Q$2, unit_details[Beds], 0, unit_details[Property Name], B38) -> 0 | L38: =COUNTIFS( unit_details[First Listed], ">=" & ($Q$2 - 7), unit_details[First Listed], "<" & $Q$2, unit_details[Beds], 0, unit_details[Property Name], B38 ) - COUNTIFS( unit_details[First Listed], ">=" & ($Q$2 - 14), unit_details[First Listed], "<=" & ($Q$2 - 7), unit_details[Beds], 0, unit_details[Property Name], B38 ) -> 0 | M38: =IFERROR(AVERAGEIFS(unit_details[Asking Rent],unit_details[First Listed],">="&($Q$2-7), unit_details[First Listed],"<="&$Q$2, unit_details[Beds],0, unit_details[Property Name],B38),"") | N38: =COUNTIFS(unit_details[Property Name], B38, unit_details[Beds], 0, unit_details[Leased Date], "") -> 0 | O38: =N38-(N38-K38+F38) -> 0 | P38: =IFERROR(AVERAGEIFS(unit_details[Asking Rent],unit_details[Property Name], B38, unit_details[Beds], 0, unit_details[Leased Date], ""),"") | Q38: =IFERROR(N38/SUMIFS(unit_mix_table['# Units],unit_mix_table[Beds],0,unit_mix_table[Property Name],B38),"")
B39: 1311 Bluff Street, Delta, CO 81416 | E39: 1 BR | F39: =COUNTIFS(unit_details[Leased Date], ">=" & ($Q$2 - 7), unit_details[Leased Date], "<" & $Q$2, unit_details[Beds], 1, unit_details[Property Name], B38) -> 0 | G39: =COUNTIFS(unit_details[Leased Date], ">=" & ($Q$2 - 7), unit_details[Leased Date], "<" & $Q$2, unit_details[Beds], 1, unit_details[Property Name], B38) - COUNTIFS(unit_details[Leased Date], ">=" & ($Q$2 - 14), unit_details[Leased Date], "<=" & ($Q$2 - 7), unit_details[Beds], 1, unit_details[Property Name], B38) -> 0 | H39: =IFERROR(AVERAGEIFS(unit_details[Asking Rent],unit_details[Leased Date], ">=" & ($Q$2 - 7), unit_details[Leased Date], "<" & $Q$2, unit_details[Beds], 1, unit_details[Property Name], B38),"") | I39: =IFERROR( AVERAGEIFS(unit_details[Asking Rent], unit_details[Leased Date], ">=" & ($Q$2 - 7), unit_details[Leased Date], "<" & $Q$2, unit_details[Beds], 1, unit_details[Property Name], B38) - AVERAGEIFS(unit_details[Asking Rent], unit_details[Leased Date], ">=" & ($Q$2 - 14), unit_details[Leased Date], "<=" & ($Q$2 - 7), unit_details[Beds], 1, unit_details[Property Name], B38), 0) -> 0 | J39: =IFERROR(I39/AVERAGEIFS(unit_details[Asking Rent], unit_details[Leased Date], ">=" & ($Q$2 - 14), unit_details[Leased Date], "<=" & ($Q$2 - 7), unit_details[Beds], 1, unit_details[Property Name], B38),0) -> 0 | K39: =COUNTIFS(unit_details[First Listed], ">=" & ($Q$2 - 7), unit_details[First Listed], "<" & $Q$2, unit_details[Beds], 1, unit_details[Property Name], B38) -> 0 | L39: =COUNTIFS( unit_details[First Listed], ">=" & ($Q$2 - 7), unit_details[First Listed], "<" & $Q$2, unit_details[Beds], 1, unit_details[Property Name], B38 ) - COUNTIFS( unit_details[First Listed], ">=" & ($Q$2 - 14), unit_details[First Listed], "<=" & ($Q$2 - 7), unit_details[Beds], 1, unit_details[Property Name], B38 ) -> 0 | M39: =IFERROR(AVERAGEIFS(unit_details[Asking Rent],unit_details[First Listed],">="&($Q$2-7), unit_details[First Listed],"<="&$Q$2, unit_details[Beds],1, unit_details[Property Name],B38),"") | N39: =COUNTIFS(unit_details[Property Name], B38, unit_details[Beds], 1, unit_details[Leased Date], "") -> 7 | O39: =N39-(N39-K39+F39) -> 0 | P39: =IFERROR(AVERAGEIFS(unit_details[Asking Rent],unit_details[Property Name], B38, unit_details[Beds], 1, unit_details[Leased Date], ""),"") -> 1028.5714 | Q39: =IFERROR(N39/SUMIFS(unit_mix_table['# Units],unit_mix_table[Beds],1,unit_mix_table[Property Name],B38),"") -> 2.3333333
E40: 2 BR | F40: =COUNTIFS(unit_details[Leased Date], ">=" & ($Q$2 - 7), unit_details[Leased Date], "<" & $Q$2, unit_details[Beds], 2, unit_details[Property Name], B38) -> 0 | G40: =COUNTIFS(unit_details[Leased Date], ">=" & ($Q$2 - 7), unit_details[Leased Date], "<" & $Q$2, unit_details[Beds], 2, unit_details[Property Name], B38) - COUNTIFS(unit_details[Leased Date], ">=" & ($Q$2 - 14), unit_details[Leased Date], "<=" & ($Q$2 - 7), unit_details[Beds], 2, unit_details[Property Name], B38) -> 0 | H40: =IFERROR(AVERAGEIFS(unit_details[Asking Rent],unit_details[Leased Date], ">=" & ($Q$2 - 7), unit_details[Leased Date], "<" & $Q$2, unit_details[Beds], 2, unit_details[Property Name], B38),"") | I40: =IFERROR( AVERAGEIFS(unit_details[Asking Rent], unit_details[Leased Date], ">=" & ($Q$2 - 7), unit_details[Leased Date], "<" & $Q$2, unit_details[Beds], 2, unit_details[Property Name], B38) - AVERAGEIFS(unit_details[Asking Rent], unit_details[Leased Date], ">=" & ($Q$2 - 14), unit_details[Leased Date], "<=" & ($Q$2 - 7), unit_details[Beds], 2, unit_details[Property Name], B38), 0) -> 0 | J40: =IFERROR(I40/AVERAGEIFS(unit_details[Asking Rent], unit_details[Leased Date], ">=" & ($Q$2 - 14), unit_details[Leased Date], "<=" & ($Q$2 - 7), unit_details[Beds], 2, unit_details[Property Name], B38),0) -> 0 | K40: =COUNTIFS(unit_details[First Listed], ">=" & ($Q$2 - 7), unit_details[First Listed], "<" & $Q$2, unit_details[Beds], 2, unit_details[Property Name], B38) -> 0 | L40: =COUNTIFS( unit_details[First Listed], ">=" & ($Q$2 - 7), unit_details[First Listed], "<" & $Q$2, unit_details[Beds], 2, unit_details[Property Name], B38 ) - COUNTIFS( unit_details[First Listed], ">=" & ($Q$2 - 14), unit_details[First Listed], "<=" & ($Q$2 - 7), unit_details[Beds], 2, unit_details[Property Name], B38 ) -> 0 | M40: =IFERROR(AVERAGEIFS(unit_details[Asking Rent],unit_details[First Listed],">="&($Q$2-7), unit_details[First Listed],"<="&$Q$2, unit_details[Beds],2, unit_details[Property Name],B38),"") | N40: =COUNTIFS(unit_details[Property Name], B38, unit_details[Beds], 2, unit_details[Leased Date], "") -> 9 | O40: =N40-(N40-K40+F40) -> 0 | P40: =IFERROR(AVERAGEIFS(unit_details[Asking Rent],unit_details[Property Name], B38, unit_details[Beds], 2, unit_details[Leased Date], ""),"") -> 1211.1111 | Q40: =IFERROR(N40/SUMIFS(unit_mix_table['# Units],unit_mix_table[Beds],2,unit_mix_table[Property Name],B38),"") -> 1.5
E41: 3 BR | F41: =COUNTIFS(unit_details[Leased Date], ">=" & ($Q$2 - 7), unit_details[Leased Date], "<" & $Q$2, unit_details[Beds], 3, unit_details[Property Name], B38) -> 0 | G41: =COUNTIFS(unit_details[Leased Date], ">=" & ($Q$2 - 7), unit_details[Leased Date], "<" & $Q$2, unit_details[Beds], 3, unit_details[Property Name], B38) - COUNTIFS(unit_details[Leased Date], ">=" & ($Q$2 - 14), unit_details[Leased Date], "<=" & ($Q$2 - 7), unit_details[Beds], 3, unit_details[Property Name], B38) -> 0 | H41: =IFERROR(AVERAGEIFS(unit_details[Asking Rent],unit_details[Leased Date], ">=" & ($Q$2 - 7), unit_details[Leased Date], "<" & $Q$2, unit_details[Beds], 3, unit_details[Property Name], B38),"") | I41: =IFERROR( AVERAGEIFS(unit_details[Asking Rent], unit_details[Leased Date], ">=" & ($Q$2 - 7), unit_details[Leased Date], "<" & $Q$2, unit_details[Beds], 3, unit_details[Property Name], B38) - AVERAGEIFS(unit_details[Asking Rent], unit_details[Leased Date], ">=" & ($Q$2 - 14), unit_details[Leased Date], "<=" & ($Q$2 - 7), unit_details[Beds], 3, unit_details[Property Name], B38), 0) -> 0 | J41: =IFERROR(I41/AVERAGEIFS(unit_details[Asking Rent], unit_details[Leased Date], ">=" & ($Q$2 - 14), unit_details[Leased Date], "<=" & ($Q$2 - 7), unit_details[Beds], 3, unit_details[Property Name], B38),0) -> 0 | K41: =COUNTIFS(unit_details[First Listed], ">=" & ($Q$2 - 7), unit_details[First Listed], "<" & $Q$2, unit_details[Beds], 3, unit_details[Property Name], B38) -> 0 | L41: =COUNTIFS( unit_details[First Listed], ">=" & ($Q$2 - 7), unit_details[First Listed], "<" & $Q$2, unit_details[Beds], 3, unit_details[Property Name], B38 ) - COUNTIFS( unit_details[First Listed], ">=" & ($Q$2 - 14), unit_details[First Listed], "<=" & ($Q$2 - 7), unit_details[Beds], 3, unit_details[Property Name], B38 ) -> 0 | M41: =IFERROR(AVERAGEIFS(unit_details[Asking Rent],unit_details[First Listed],">="&($Q$2-7), unit_details[First Listed],"<="&$Q$2, unit_details[Beds],3, unit_details[Property Name],B38),"") | N41: =COUNTIFS(unit_details[Property Name], B38, unit_details[Beds], 3, unit_details[Leased Date], "") -> 0 | O41: =N41-(N41-K41+F41) -> 0 | P41: =IFERROR(AVERAGEIFS(unit_details[Asking Rent],unit_details[Property Name], B38, unit_details[Beds], 3, unit_details[Leased Date], ""),"") | Q41: =IFERROR(N41/SUMIFS(unit_mix_table['# Units],unit_mix_table[Beds],3,unit_mix_table[Property Name],B38),"")
B42: =IF(ISBLANK(OFFSET('Rent Comparison'!$A$1,2,14)),"",IF(OFFSET('Rent Comparison'!$A$1,2,14)=0,B43,OFFSET('Rent Comparison'!$A$1,2,14))) | C42: =IF(ISBLANK(B42),"",IFERROR(INDEX(Specials!B:J,MATCH(B42&" - Active",Specials!I:I,0),2),"")) | E42: Studio | F42: =COUNTIFS(unit_details[Leased Date], ">=" & ($Q$2 - 7), unit_details[Leased Date], "<" & $Q$2, unit_details[Beds], 0, unit_details[Property Name], B42) -> 0 | G42: =COUNTIFS(unit_details[Leased Date], ">=" & ($Q$2 - 7), unit_details[Leased Date], "<" & $Q$2, unit_details[Beds], 0, unit_details[Property Name], B42) - COUNTIFS(unit_details[Leased Date], ">=" & ($Q$2 - 14), unit_details[Leased Date], "<=" & ($Q$2 - 7), unit_details[Beds], 0, unit_details[Property Name], B42) -> 0 | H42: =IFERROR(AVERAGEIFS(unit_details[Asking Rent],unit_details[Leased Date], ">=" & ($Q$2 - 7), unit_details[Leased Date], "<" & $Q$2, unit_details[Beds], 0, unit_details[Property Name], B42),"") | I42: =IFERROR( AVERAGEIFS(unit_details[Asking Rent], unit_details[Leased Date], ">=" & ($Q$2 - 7), unit_details[Leased Date], "<" & $Q$2, unit_details[Beds], 0, unit_details[Property Name], B42) - AVERAGEIFS(unit_details[Asking Rent], unit_details[Leased Date], ">=" & ($Q$2 - 14), unit_details[Leased Date], "<=" & ($Q$2 - 7), unit_details[Beds], 0, unit_details[Property Name], B42), 0) -> 0 | J42: =IFERROR(I42/AVERAGEIFS(unit_details[Asking Rent], unit_details[Leased Date], ">=" & ($Q$2 - 14), unit_details[Leased Date], "<=" & ($Q$2 - 7), unit_details[Beds], 0, unit_details[Property Name], B42),0) -> 0 | K42: =COUNTIFS(unit_details[First Listed], ">=" & ($Q$2 - 7), unit_details[First Listed], "<" & $Q$2, unit_details[Beds], 0, unit_details[Property Name], B42) -> 0 | L42: =COUNTIFS( unit_details[First Listed], ">=" & ($Q$2 - 7), unit_details[First Listed], "<" & $Q$2, unit_details[Beds], 0, unit_details[Property Name], B42 ) - COUNTIFS( unit_details[First Listed], ">=" & ($Q$2 - 14), unit_details[First Listed], "<=" & ($Q$2 - 7), unit_details[Beds], 0, unit_details[Property Name], B42 ) -> 0 | M42: =IFERROR(AVERAGEIFS(unit_details[Asking Rent],unit_details[First Listed],">="&($Q$2-7), unit_details[First Listed],"<="&$Q$2, unit_details[Beds],0, unit_details[Property Name],B42),"") | N42: =COUNTIFS(unit_details[Property Name], B42, unit_details[Beds], 0, unit_details[Leased Date], "") -> 0 | O42: =N42-(N42-K42+F42) -> 0 | P42: =IFERROR(AVERAGEIFS(unit_details[Asking Rent],unit_details[Property Name], B42, unit_details[Beds], 0, unit_details[Leased Date], ""),"") | Q42: =IFERROR(N42/SUMIFS(unit_mix_table['# Units],unit_mix_table[Beds],0,unit_mix_table[Property Name],B42),"")
B43: 1381 East 3rd Street, Delta, CO 81416 | E43: 1 BR | F43: =COUNTIFS(unit_details[Leased Date], ">=" & ($Q$2 - 7), unit_details[Leased Date], "<" & $Q$2, unit_details[Beds], 1, unit_details[Property Name], B42) -> 0 | G43: =COUNTIFS(unit_details[Leased Date], ">=" & ($Q$2 - 7), unit_details[Leased Date], "<" & $Q$2, unit_details[Beds], 1, unit_details[Property Name], B42) - COUNTIFS(unit_details[Leased Date], ">=" & ($Q$2 - 14), unit_details[Leased Date], "<=" & ($Q$2 - 7), unit_details[Beds], 1, unit_details[Property Name], B42) -> 0 | H43: =IFERROR(AVERAGEIFS(unit_details[Asking Rent],unit_details[Leased Date], ">=" & ($Q$2 - 7), unit_details[Leased Date], "<" & $Q$2, unit_details[Beds], 1, unit_details[Property Name], B42),"") | I43: =IFERROR( AVERAGEIFS(unit_details[Asking Rent], unit_details[Leased Date], ">=" & ($Q$2 - 7), unit_details[Leased Date], "<" & $Q$2, unit_details[Beds], 1, unit_details[Property Name], B42) - AVERAGEIFS(unit_details[Asking Rent], unit_details[Leased Date], ">=" & ($Q$2 - 14), unit_details[Leased Date], "<=" & ($Q$2 - 7), unit_details[Beds], 1, unit_details[Property Name], B42), 0) -> 0 | J43: =IFERROR(I43/AVERAGEIFS(unit_details[Asking Rent], unit_details[Leased Date], ">=" & ($Q$2 - 14), unit_details[Leased Date], "<=" & ($Q$2 - 7), unit_details[Beds], 1, unit_details[Property Name], B42),0) -> 0 | K43: =COUNTIFS(unit_details[First Listed], ">=" & ($Q$2 - 7), unit_details[First Listed], "<" & $Q$2, unit_details[Beds], 1, unit_details[Property Name], B42) -> 0 | L43: =COUNTIFS( unit_details[First Listed], ">=" & ($Q$2 - 7), unit_details[First Listed], "<" & $Q$2, unit_details[Beds], 1, unit_details[Property Name], B42 ) - COUNTIFS( unit_details[First Listed], ">=" & ($Q$2 - 14), unit_details[First Listed], "<=" & ($Q$2 - 7), unit_details[Beds], 1, unit_details[Property Name], B42 ) -> 0 | M43: =IFERROR(AVERAGEIFS(unit_details[Asking Rent],unit_details[First Listed],">="&($Q$2-7), unit_details[First Listed],"<="&$Q$2, unit_details[Beds],1, unit_details[Property Name],B42),"") | N43: =COUNTIFS(unit_details[Property Name], B42, unit_details[Beds], 1, unit_details[Leased Date], "") -> 7 | O43: =N43-(N43-K43+F43) -> 0 | P43: =IFERROR(AVERAGEIFS(unit_details[Asking Rent],unit_details[Property Name], B42, unit_details[Beds], 1, unit_details[Leased Date], ""),"") -> 1028.5714 | Q43: =IFERROR(N43/SUMIFS(unit_mix_table['# Units],unit_mix_table[Beds],1,unit_mix_table[Property Name],B42),"") -> 2.3333333
E44: 2 BR | F44: =COUNTIFS(unit_details[Leased Date], ">=" & ($Q$2 - 7), unit_details[Leased Date], "<" & $Q$2, unit_details[Beds], 2, unit_details[Property Name], B42) -> 0 | G44: =COUNTIFS(unit_details[Leased Date], ">=" & ($Q$2 - 7), unit_details[Leased Date], "<" & $Q$2, unit_details[Beds], 2, unit_details[Property Name], B42) - COUNTIFS(unit_details[Leased Date], ">=" & ($Q$2 - 14), unit_details[Leased Date], "<=" & ($Q$2 - 7), unit_details[Beds], 2, unit_details[Property Name], B42) -> 0 | H44: =IFERROR(AVERAGEIFS(unit_details[Asking Rent],unit_details[Leased Date], ">=" & ($Q$2 - 7), unit_details[Leased Date], "<" & $Q$2, unit_details[Beds], 2, unit_details[Property Name], B42),"") | I44: =IFERROR( AVERAGEIFS(unit_details[Asking Rent], unit_details[Leased Date], ">=" & ($Q$2 - 7), unit_details[Leased Date], "<" & $Q$2, unit_details[Beds], 2, unit_details[Property Name], B42) - AVERAGEIFS(unit_details[Asking Rent], unit_details[Leased Date], ">=" & ($Q$2 - 14), unit_details[Leased Date], "<=" & ($Q$2 - 7), unit_details[Beds], 2, unit_details[Property Name], B42), 0) -> 0 | J44: =IFERROR(I44/AVERAGEIFS(unit_details[Asking Rent], unit_details[Leased Date], ">=" & ($Q$2 - 14), unit_details[Leased Date], "<=" & ($Q$2 - 7), unit_details[Beds], 2, unit_details[Property Name], B42),0) -> 0 | K44: =COUNTIFS(unit_details[First Listed], ">=" & ($Q$2 - 7), unit_details[First Listed], "<" & $Q$2, unit_details[Beds], 2, unit_details[Property Name], B42) -> 0 | L44: =COUNTIFS( unit_details[First Listed], ">=" & ($Q$2 - 7), unit_details[First Listed], "<" & $Q$2, unit_details[Beds], 2, unit_details[Property Name], B42 ) - COUNTIFS( unit_details[First Listed], ">=" & ($Q$2 - 14), unit_details[First Listed], "<=" & ($Q$2 - 7), unit_details[Beds], 2, unit_details[Property Name], B42 ) -> 0 | M44: =IFERROR(AVERAGEIFS(unit_details[Asking Rent],unit_details[First Listed],">="&($Q$2-7), unit_details[First Listed],"<="&$Q$2, unit_details[Beds],2, unit_details[Property Name],B42),"") | N44: =COUNTIFS(unit_details[Property Name], B42, unit_details[Beds], 2, unit_details[Leased Date], "") -> 9 | O44: =N44-(N44-K44+F44) -> 0 | P44: =IFERROR(AVERAGEIFS(unit_details[Asking Rent],unit_details[Property Name], B42, unit_details[Beds], 2, unit_details[Leased Date], ""),"") -> 1211.1111 | Q44: =IFERROR(N44/SUMIFS(unit_mix_table['# Units],unit_mix_table[Beds],2,unit_mix_table[Property Name],B42),"") -> 1.5
B45: https://areabest.net | E45: 3 BR | F45: =COUNTIFS(unit_details[Leased Date], ">=" & ($Q$2 - 7), unit_details[Leased Date], "<" & $Q$2, unit_details[Beds], 3, unit_details[Property Name], B42) -> 0 | G45: =COUNTIFS(unit_details[Leased Date], ">=" & ($Q$2 - 7), unit_details[Leased Date], "<" & $Q$2, unit_details[Beds], 3, unit_details[Property Name], B42) - COUNTIFS(unit_details[Leased Date], ">=" & ($Q$2 - 14), unit_details[Leased Date], "<=" & ($Q$2 - 7), unit_details[Beds], 3, unit_details[Property Name], B42) -> 0 | H45: =IFERROR(AVERAGEIFS(unit_details[Asking Rent],unit_details[Leased Date], ">=" & ($Q$2 - 7), unit_details[Leased Date], "<" & $Q$2, unit_details[Beds], 3, unit_details[Property Name], B42),"") | I45: =IFERROR( AVERAGEIFS(unit_details[Asking Rent], unit_details[Leased Date], ">=" & ($Q$2 - 7), unit_details[Leased Date], "<" & $Q$2, unit_details[Beds], 3, unit_details[Property Name], B42) - AVERAGEIFS(unit_details[Asking Rent], unit_details[Leased Date], ">=" & ($Q$2 - 14), unit_details[Leased Date], "<=" & ($Q$2 - 7), unit_details[Beds], 3, unit_details[Property Name], B42), 0) -> 0 | J45: =IFERROR(I45/AVERAGEIFS(unit_details[Asking Rent], unit_details[Leased Date], ">=" & ($Q$2 - 14), unit_details[Leased Date], "<=" & ($Q$2 - 7), unit_details[Beds], 3, unit_details[Property Name], B42),0) -> 0 | K45: =COUNTIFS(unit_details[First Listed], ">=" & ($Q$2 - 7), unit_details[First Listed], "<" & $Q$2, unit_details[Beds], 3, unit_details[Property Name], B42) -> 0 | L45: =COUNTIFS( unit_details[First Listed], ">=" & ($Q$2 - 7), unit_details[First Listed], "<" & $Q$2, unit_details[Beds], 3, unit_details[Property Name], B42 ) - COUNTIFS( unit_details[First Listed], ">=" & ($Q$2 - 14), unit_details[First Listed], "<=" & ($Q$2 - 7), unit_details[Beds], 3, unit_details[Property Name], B42 ) -> 0 | M45: =IFERROR(AVERAGEIFS(unit_details[Asking Rent],unit_details[First Listed],">="&($Q$2-7), unit_details[First Listed],"<="&$Q$2, unit_details[Beds],3, unit_details[Property Name],B42),"") | N45: =COUNTIFS(unit_details[Property Name], B42, unit_details[Beds], 3, unit_details[Leased Date], "") -> 0 | O45: =N45-(N45-K45+F45) -> 0 | P45: =IFERROR(AVERAGEIFS(unit_details[Asking Rent],unit_details[Property Name], B42, unit_details[Beds], 3, unit_details[Leased Date], ""),"") | Q45: =IFERROR(N45/SUMIFS(unit_mix_table['# Units],unit_mix_table[Beds],3,unit_mix_table[Property Name],B42),"")
B46: =IF(ISBLANK(OFFSET('Rent Comparison'!$A$1,2,15)),"",IF(OFFSET('Rent Comparison'!$A$1,2,15)=0,B47,OFFSET('Rent Comparison'!$A$1,2,15))) | C46: =IF(ISBLANK(B46),"",IFERROR(INDEX(Specials!B:J,MATCH(B46&" - Active",Specials!I:I,0),2),"")) | E46: Studio | F46: =COUNTIFS(unit_details[Leased Date], ">=" & ($Q$2 - 7), unit_details[Leased Date], "<" & $Q$2, unit_details[Beds], 0, unit_details[Property Name], B46) -> 0 | G46: =COUNTIFS(unit_details[Leased Date], ">=" & ($Q$2 - 7), unit_details[Leased Date], "<" & $Q$2, unit_details[Beds], 0, unit_details[Property Name], B46) - COUNTIFS(unit_details[Leased Date], ">=" & ($Q$2 - 14), unit_details[Leased Date], "<=" & ($Q$2 - 7), unit_details[Beds], 0, unit_details[Property Name], B46) -> 0 | H46: =IFERROR(AVERAGEIFS(unit_details[Asking Rent],unit_details[Leased Date], ">=" & ($Q$2 - 7), unit_details[Leased Date], "<" & $Q$2, unit_details[Beds], 0, unit_details[Property Name], B46),"") | I46: =IFERROR( AVERAGEIFS(unit_details[Asking Rent], unit_details[Leased Date], ">=" & ($Q$2 - 7), unit_details[Leased Date], "<" & $Q$2, unit_details[Beds], 0, unit_details[Property Name], B46) - AVERAGEIFS(unit_details[Asking Rent], unit_details[Leased Date], ">=" & ($Q$2 - 14), unit_details[Leased Date], "<=" & ($Q$2 - 7), unit_details[Beds], 0, unit_details[Property Name], B46), 0) -> 0 | J46: =IFERROR(I46/AVERAGEIFS(unit_details[Asking Rent], unit_details[Leased Date], ">=" & ($Q$2 - 14), unit_details[Leased Date], "<=" & ($Q$2 - 7), unit_details[Beds], 0, unit_details[Property Name], B46),0) -> 0 | K46: =COUNTIFS(unit_details[First Listed], ">=" & ($Q$2 - 7), unit_details[First Listed], "<" & $Q$2, unit_details[Beds], 0, unit_details[Property Name], B46) -> 0 | L46: =COUNTIFS( unit_details[First Listed], ">=" & ($Q$2 - 7), unit_details[First Listed], "<" & $Q$2, unit_details[Beds], 0, unit_details[Property Name], B46 ) - COUNTIFS( unit_details[First Listed], ">=" & ($Q$2 - 14), unit_details[First Listed], "<=" & ($Q$2 - 7), unit_details[Beds], 0, unit_details[Property Name], B46 ) -> 0 | M46: =IFERROR(AVERAGEIFS(unit_details[Asking Rent],unit_details[First Listed],">="&($Q$2-7), unit_details[First Listed],"<="&$Q$2, unit_details[Beds],0, unit_details[Property Name],B46),"") | N46: =COUNTIFS(unit_details[Property Name], B46, unit_details[Beds], 0, unit_details[Leased Date], "") -> 0 | O46: =N46-(N46-K46+F46) -> 0 | P46: =IFERROR(AVERAGEIFS(unit_details[Asking Rent],unit_details[Property Name], B46, unit_details[Beds], 0, unit_details[Leased Date], ""),"") | Q46: =IFERROR(N46/SUMIFS(unit_mix_table['# Units],unit_mix_table[Beds],0,unit_mix_table[Property Name],B46),"")
B47: 316 East 10th Street, Delta, CO 81416 | E47: 1 BR | F47: =COUNTIFS(unit_details[Leased Date], ">=" & ($Q$2 - 7), unit_details[Leased Date], "<" & $Q$2, unit_details[Beds], 1, unit_details[Property Name], B46) -> 0 | G47: =COUNTIFS(unit_details[Leased Date], ">=" & ($Q$2 - 7), unit_details[Leased Date], "<" & $Q$2, unit_details[Beds], 1, unit_details[Property Name], B46) - COUNTIFS(unit_details[Leased Date], ">=" & ($Q$2 - 14), unit_details[Leased Date], "<=" & ($Q$2 - 7), unit_details[Beds], 1, unit_details[Property Name], B46) -> 0 | H47: =IFERROR(AVERAGEIFS(unit_details[Asking Rent],unit_details[Leased Date], ">=" & ($Q$2 - 7), unit_details[Leased Date], "<" & $Q$2, unit_details[Beds], 1, unit_details[Property Name], B46),"") | I47: =IFERROR( AVERAGEIFS(unit_details[Asking Rent], unit_details[Leased Date], ">=" & ($Q$2 - 7), unit_details[Leased Date], "<" & $Q$2, unit_details[Beds], 1, unit_details[Property Name], B46) - AVERAGEIFS(unit_details[Asking Rent], unit_details[Leased Date], ">=" & ($Q$2 - 14), unit_details[Leased Date], "<=" & ($Q$2 - 7), unit_details[Beds], 1, unit_details[Property Name], B46), 0) -> 0 | J47: =IFERROR(I47/AVERAGEIFS(unit_details[Asking Rent], unit_details[Leased Date], ">=" & ($Q$2 - 14), unit_details[Leased Date], "<=" & ($Q$2 - 7), unit_details[Beds], 1, unit_details[Property Name], B46),0) -> 0 | K47: =COUNTIFS(unit_details[First Listed], ">=" & ($Q$2 - 7), unit_details[First Listed], "<" & $Q$2, unit_details[Beds], 1, unit_details[Property Name], B46) -> 0 | L47: =COUNTIFS( unit_details[First Listed], ">=" & ($Q$2 - 7), unit_details[First Listed], "<" & $Q$2, unit_details[Beds], 1, unit_details[Property Name], B46 ) - COUNTIFS( unit_details[First Listed], ">=" & ($Q$2 - 14), unit_details[First Listed], "<=" & ($Q$2 - 7), unit_details[Beds], 1, unit_details[Property Name], B46 ) -> 0 | M47: =IFERROR(AVERAGEIFS(unit_details[Asking Rent],unit_details[First Listed],">="&($Q$2-7), unit_details[First Listed],"<="&$Q$2, unit_details[Beds],1, unit_details[Property Name],B46),"") | N47: =COUNTIFS(unit_details[Property Name], B46, unit_details[Beds], 1, unit_details[Leased Date], "") -> 7 | O47: =N47-(N47-K47+F47) -> 0 | P47: =IFERROR(AVERAGEIFS(unit_details[Asking Rent],unit_details[Property Name], B46, unit_details[Beds], 1, unit_details[Leased Date], ""),"") -> 1028.5714 | Q47: =IFERROR(N47/SUMIFS(unit_mix_table['# Units],unit_mix_table[Beds],1,unit_mix_table[Property Name],B46),"") -> 2.3333333
E48: 2 BR | F48: =COUNTIFS(unit_details[Leased Date], ">=" & ($Q$2 - 7), unit_details[Leased Date], "<" & $Q$2, unit_details[Beds], 2, unit_details[Property Name], B46) -> 0 | G48: =COUNTIFS(unit_details[Leased Date], ">=" & ($Q$2 - 7), unit_details[Leased Date], "<" & $Q$2, unit_details[Beds], 2, unit_details[Property Name], B46) - COUNTIFS(unit_details[Leased Date], ">=" & ($Q$2 - 14), unit_details[Leased Date], "<=" & ($Q$2 - 7), unit_details[Beds], 2, unit_details[Property Name], B46) -> 0 | H48: =IFERROR(AVERAGEIFS(unit_details[Asking Rent],unit_details[Leased Date], ">=" & ($Q$2 - 7), unit_details[Leased Date], "<" & $Q$2, unit_details[Beds], 2, unit_details[Property Name], B46),"") | I48: =IFERROR( AVERAGEIFS(unit_details[Asking Rent], unit_details[Leased Date], ">=" & ($Q$2 - 7), unit_details[Leased Date], "<" & $Q$2, unit_details[Beds], 2, unit_details[Property Name], B46) - AVERAGEIFS(unit_details[Asking Rent], unit_details[Leased Date], ">=" & ($Q$2 - 14), unit_details[Leased Date], "<=" & ($Q$2 - 7), unit_details[Beds], 2, unit_details[Property Name], B46), 0) -> 0 | J48: =IFERROR(I48/AVERAGEIFS(unit_details[Asking Rent], unit_details[Leased Date], ">=" & ($Q$2 - 14), unit_details[Leased Date], "<=" & ($Q$2 - 7), unit_details[Beds], 2, unit_details[Property Name], B46),0) -> 0 | K48: =COUNTIFS(unit_details[First Listed], ">=" & ($Q$2 - 7), unit_details[First Listed], "<" & $Q$2, unit_details[Beds], 2, unit_details[Property Name], B46) -> 0 | L48: =COUNTIFS( unit_details[First Listed], ">=" & ($Q$2 - 7), unit_details[First Listed], "<" & $Q$2, unit_details[Beds], 2, unit_details[Property Name], B46 ) - COUNTIFS( unit_details[First Listed], ">=" & ($Q$2 - 14), unit_details[First Listed], "<=" & ($Q$2 - 7), unit_details[Beds], 2, unit_details[Property Name], B46 ) -> 0 | M48: =IFERROR(AVERAGEIFS(unit_details[Asking Rent],unit_details[First Listed],">="&($Q$2-7), unit_details[First Listed],"<="&$Q$2, unit_details[Beds],2, unit_details[Property Name],B46),"") | N48: =COUNTIFS(unit_details[Property Name], B46, unit_details[Beds], 2, unit_details[Leased Date], "") -> 9 | O48: =N48-(N48-K48+F48) -> 0 | P48: =IFERROR(AVERAGEIFS(unit_details[Asking Rent],unit_details[Property Name], B46, unit_details[Beds], 2, unit_details[Leased Date], ""),"") -> 1211.1111 | Q48: =IFERROR(N48/SUMIFS(unit_mix_table['# Units],unit_mix_table[Beds],2,unit_mix_table[Property Name],B46),"") -> 1.5
E49: 3 BR | F49: =COUNTIFS(unit_details[Leased Date], ">=" & ($Q$2 - 7), unit_details[Leased Date], "<" & $Q$2, unit_details[Beds], 3, unit_details[Property Name], B46) -> 0 | G49: =COUNTIFS(unit_details[Leased Date], ">=" & ($Q$2 - 7), unit_details[Leased Date], "<" & $Q$2, unit_details[Beds], 3, unit_details[Property Name], B46) - COUNTIFS(unit_details[Leased Date], ">=" & ($Q$2 - 14), unit_details[Leased Date], "<=" & ($Q$2 - 7), unit_details[Beds], 3, unit_details[Property Name], B46) -> 0 | H49: =IFERROR(AVERAGEIFS(unit_details[Asking Rent],unit_details[Leased Date], ">=" & ($Q$2 - 7), unit_details[Leased Date], "<" & $Q$2, unit_details[Beds], 3, unit_details[Property Name], B46),"") | I49: =IFERROR( AVERAGEIFS(unit_details[Asking Rent], unit_details[Leased Date], ">=" & ($Q$2 - 7), unit_details[Leased Date], "<" & $Q$2, unit_details[Beds], 3, unit_details[Property Name], B46) - AVERAGEIFS(unit_details[Asking Rent], unit_details[Leased Date], ">=" & ($Q$2 - 14), unit_details[Leased Date], "<=" & ($Q$2 - 7), unit_details[Beds], 3, unit_details[Property Name], B46), 0) -> 0 | J49: =IFERROR(I49/AVERAGEIFS(unit_details[Asking Rent], unit_details[Leased Date], ">=" & ($Q$2 - 14), unit_details[Leased Date], "<=" & ($Q$2 - 7), unit_details[Beds], 3, unit_details[Property Name], B46),0) -> 0 | K49: =COUNTIFS(unit_details[First Listed], ">=" & ($Q$2 - 7), unit_details[First Listed], "<" & $Q$2, unit_details[Beds], 3, unit_details[Property Name], B46) -> 0 | L49: =COUNTIFS( unit_details[First Listed], ">=" & ($Q$2 - 7), unit_details[First Listed], "<" & $Q$2, unit_details[Beds], 3, unit_details[Property Name], B46 ) - COUNTIFS( unit_details[First Listed], ">=" & ($Q$2 - 14), unit_details[First Listed], "<=" & ($Q$2 - 7), unit_details[Beds], 3, unit_details[Property Name], B46 ) -> 0 | M49: =IFERROR(AVERAGEIFS(unit_details[Asking Rent],unit_details[First Listed],">="&($Q$2-7), unit_details[First Listed],"<="&$Q$2, unit_details[Beds],3, unit_details[Property Name],B46),"") | N49: =COUNTIFS(unit_details[Property Name], B46, unit_details[Beds], 3, unit_details[Leased Date], "") -> 0 | O49: =N49-(N49-K49+F49) -> 0 | P49: =IFERROR(AVERAGEIFS(unit_details[Asking Rent],unit_details[Property Name], B46, unit_details[Beds], 3, unit_details[Leased Date], ""),"") | Q49: =IFERROR(N49/SUMIFS(unit_mix_table['# Units],unit_mix_table[Beds],3,unit_mix_table[Property Name],B46),"")
B50: =IF(ISBLANK(OFFSET('Rent Comparison'!$A$1,2,16)),"",IF(OFFSET('Rent Comparison'!$A$1,2,16)=0,B51,OFFSET('Rent Comparison'!$A$1,2,16))) | C50: =IF(ISBLANK(B50),"",IFERROR(INDEX(Specials!B:J,MATCH(B50&" - Active",Specials!I:I,0),2),"")) | E50: Studio | F50: =COUNTIFS(unit_details[Leased Date], ">=" & ($Q$2 - 7), unit_details[Leased Date], "<" & $Q$2, unit_details[Beds], 0, unit_details[Property Name], B50) -> 0 | G50: =COUNTIFS(unit_details[Leased Date], ">=" & ($Q$2 - 7), unit_details[Leased Date], "<" & $Q$2, unit_details[Beds], 0, unit_details[Property Name], B50) - COUNTIFS(unit_details[Leased Date], ">=" & ($Q$2 - 14), unit_details[Leased Date], "<=" & ($Q$2 - 7), unit_details[Beds], 0, unit_details[Property Name], B50) -> 0 | H50: =IFERROR(AVERAGEIFS(unit_details[Asking Rent],unit_details[Leased Date], ">=" & ($Q$2 - 7), unit_details[Leased Date], "<" & $Q$2, unit_details[Beds], 0, unit_details[Property Name], B50),"") | I50: =IFERROR( AVERAGEIFS(unit_details[Asking Rent], unit_details[Leased Date], ">=" & ($Q$2 - 7), unit_details[Leased Date], "<" & $Q$2, unit_details[Beds], 0, unit_details[Property Name], B50) - AVERAGEIFS(unit_details[Asking Rent], unit_details[Leased Date], ">=" & ($Q$2 - 14), unit_details[Leased Date], "<=" & ($Q$2 - 7), unit_details[Beds], 0, unit_details[Property Name], B50), 0) -> 0 | J50: =IFERROR(I50/AVERAGEIFS(unit_details[Asking Rent], unit_details[Leased Date], ">=" & ($Q$2 - 14), unit_details[Leased Date], "<=" & ($Q$2 - 7), unit_details[Beds], 0, unit_details[Property Name], B50),0) -> 0 | K50: =COUNTIFS(unit_details[First Listed], ">=" & ($Q$2 - 7), unit_details[First Listed], "<" & $Q$2, unit_details[Beds], 0, unit_details[Property Name], B50) -> 0 | L50: =COUNTIFS( unit_details[First Listed], ">=" & ($Q$2 - 7), unit_details[First Listed], "<" & $Q$2, unit_details[Beds], 0, unit_details[Property Name], B50 ) - COUNTIFS( unit_details[First Listed], ">=" & ($Q$2 - 14), unit_details[First Listed], "<=" & ($Q$2 - 7), unit_details[Beds], 0, unit_details[Property Name], B50 ) -> 0 | M50: =IFERROR(AVERAGEIFS(unit_details[Asking Rent],unit_details[First Listed],">="&($Q$2-7), unit_details[First Listed],"<="&$Q$2, unit_details[Beds],0, unit_details[Property Name],B50),"") | N50: =COUNTIFS(unit_details[Property Name], B50, unit_details[Beds], 0, unit_details[Leased Date], "") -> 0 | O50: =N50-(N50-K50+F50) -> 0 | P50: =IFERROR(AVERAGEIFS(unit_details[Asking Rent],unit_details[Property Name], B50, unit_details[Beds], 0, unit_details[Leased Date], ""),"") | Q50: =IFERROR(N50/SUMIFS(unit_mix_table['# Units],unit_mix_table[Beds],0,unit_mix_table[Property Name],B50),"")
B51: 240 West 4th Street, Delta, CO 81416 | E51: 1 BR | F51: =COUNTIFS(unit_details[Leased Date], ">=" & ($Q$2 - 7), unit_details[Leased Date], "<" & $Q$2, unit_details[Beds], 1, unit_details[Property Name], B50) -> 0 | G51: =COUNTIFS(unit_details[Leased Date], ">=" & ($Q$2 - 7), unit_details[Leased Date], "<" & $Q$2, unit_details[Beds], 1, unit_details[Property Name], B50) - COUNTIFS(unit_details[Leased Date], ">=" & ($Q$2 - 14), unit_details[Leased Date], "<=" & ($Q$2 - 7), unit_details[Beds], 1, unit_details[Property Name], B50) -> 0 | H51: =IFERROR(AVERAGEIFS(unit_details[Asking Rent],unit_details[Leased Date], ">=" & ($Q$2 - 7), unit_details[Leased Date], "<" & $Q$2, unit_details[Beds], 1, unit_details[Property Name], B50),"") | I51: =IFERROR( AVERAGEIFS(unit_details[Asking Rent], unit_details[Leased Date], ">=" & ($Q$2 - 7), unit_details[Leased Date], "<" & $Q$2, unit_details[Beds], 1, unit_details[Property Name], B50) - AVERAGEIFS(unit_details[Asking Rent], unit_details[Leased Date], ">=" & ($Q$2 - 14), unit_details[Leased Date], "<=" & ($Q$2 - 7), unit_details[Beds], 1, unit_details[Property Name], B50), 0) -> 0 | J51: =IFERROR(I51/AVERAGEIFS(unit_details[Asking Rent], unit_details[Leased Date], ">=" & ($Q$2 - 14), unit_details[Leased Date], "<=" & ($Q$2 - 7), unit_details[Beds], 1, unit_details[Property Name], B50),0) -> 0 | K51: =COUNTIFS(unit_details[First Listed], ">=" & ($Q$2 - 7), unit_details[First Listed], "<" & $Q$2, unit_details[Beds], 1, unit_details[Property Name], B50) -> 0 | L51: =COUNTIFS( unit_details[First Listed], ">=" & ($Q$2 - 7), unit_details[First Listed], "<" & $Q$2, unit_details[Beds], 1, unit_details[Property Name], B50 ) - COUNTIFS( unit_details[First Listed], ">=" & ($Q$2 - 14), unit_details[First Listed], "<=" & ($Q$2 - 7), unit_details[Beds], 1, unit_details[Property Name], B50 ) -> 0 | M51: =IFERROR(AVERAGEIFS(unit_details[Asking Rent],unit_details[First Listed],">="&($Q$2-7), unit_details[First Listed],"<="&$Q$2, unit_details[Beds],1, unit_details[Property Name],B50),"") | N51: =COUNTIFS(unit_details[Property Name], B50, unit_details[Beds], 1, unit_details[Leased Date], "") -> 7 | O51: =N51-(N51-K51+F51) -> 0 | P51: =IFERROR(AVERAGEIFS(unit_details[Asking Rent],unit_details[Property Name], B50, unit_details[Beds], 1, unit_details[Leased Date], ""),"") -> 1028.5714 | Q51: =IFERROR(N51/SUMIFS(unit_mix_table['# Units],unit_mix_table[Beds],1,unit_mix_table[Property Name],B50),"") -> 2.3333333
E52: 2 BR | F52: =COUNTIFS(unit_details[Leased Date], ">=" & ($Q$2 - 7), unit_details[Leased Date], "<" & $Q$2, unit_details[Beds], 2, unit_details[Property Name], B50) -> 0 | G52: =COUNTIFS(unit_details[Leased Date], ">=" & ($Q$2 - 7), unit_details[Leased Date], "<" & $Q$2, unit_details[Beds], 2, unit_details[Property Name], B50) - COUNTIFS(unit_details[Leased Date], ">=" & ($Q$2 - 14), unit_details[Leased Date], "<=" & ($Q$2 - 7), unit_details[Beds], 2, unit_details[Property Name], B50) -> 0 | H52: =IFERROR(AVERAGEIFS(unit_details[Asking Rent],unit_details[Leased Date], ">=" & ($Q$2 - 7), unit_details[Leased Date], "<" & $Q$2, unit_details[Beds], 2, unit_details[Property Name], B50),"") | I52: =IFERROR( AVERAGEIFS(unit_details[Asking Rent], unit_details[Leased Date], ">=" & ($Q$2 - 7), unit_details[Leased Date], "<" & $Q$2, unit_details[Beds], 2, unit_details[Property Name], B50) - AVERAGEIFS(unit_details[Asking Rent], unit_details[Leased Date], ">=" & ($Q$2 - 14), unit_details[Leased Date], "<=" & ($Q$2 - 7), unit_details[Beds], 2, unit_details[Property Name], B50), 0) -> 0 | J52: =IFERROR(I52/AVERAGEIFS(unit_details[Asking Rent], unit_details[Leased Date], ">=" & ($Q$2 - 14), unit_details[Leased Date], "<=" & ($Q$2 - 7), unit_details[Beds], 2, unit_details[Property Name], B50),0) -> 0 | K52: =COUNTIFS(unit_details[First Listed], ">=" & ($Q$2 - 7), unit_details[First Listed], "<" & $Q$2, unit_details[Beds], 2, unit_details[Property Name], B50) -> 0 | L52: =COUNTIFS( unit_details[First Listed], ">=" & ($Q$2 - 7), unit_details[First Listed], "<" & $Q$2, unit_details[Beds], 2, unit_details[Property Name], B50 ) - COUNTIFS( unit_details[First Listed], ">=" & ($Q$2 - 14), unit_details[First Listed], "<=" & ($Q$2 - 7), unit_details[Beds], 2, unit_details[Property Name], B50 ) -> 0 | M52: =IFERROR(AVERAGEIFS(unit_details[Asking Rent],unit_details[First Listed],">="&($Q$2-7), unit_details[First Listed],"<="&$Q$2, unit_details[Beds],2, unit_details[Property Name],B50),"") | N52: =COUNTIFS(unit_details[Property Name], B50, unit_details[Beds], 2, unit_details[Leased Date], "") -> 9 | O52: =N52-(N52-K52+F52) -> 0 | P52: =IFERROR(AVERAGEIFS(unit_details[Asking Rent],unit_details[Property Name], B50, unit_details[Beds], 2, unit_details[Leased Date], ""),"") -> 1211.1111 | Q52: =IFERROR(N52/SUMIFS(unit_mix_table['# Units],unit_mix_table[Beds],2,unit_mix_table[Property Name],B50),"") -> 1.5
B53: https://areabest.net | E53: 3 BR | F53: =COUNTIFS(unit_details[Leased Date], ">=" & ($Q$2 - 7), unit_details[Leased Date], "<" & $Q$2, unit_details[Beds], 3, unit_details[Property Name], B50) -> 0 | G53: =COUNTIFS(unit_details[Leased Date], ">=" & ($Q$2 - 7), unit_details[Leased Date], "<" & $Q$2, unit_details[Beds], 3, unit_details[Property Name], B50) - COUNTIFS(unit_details[Leased Date], ">=" & ($Q$2 - 14), unit_details[Leased Date], "<=" & ($Q$2 - 7), unit_details[Beds], 3, unit_details[Property Name], B50) -> 0 | H53: =IFERROR(AVERAGEIFS(unit_details[Asking Rent],unit_details[Leased Date], ">=" & ($Q$2 - 7), unit_details[Leased Date], "<" & $Q$2, unit_details[Beds], 3, unit_details[Property Name], B50),"") | I53: =IFERROR( AVERAGEIFS(unit_details[Asking Rent], unit_details[Leased Date], ">=" & ($Q$2 - 7), unit_details[Leased Date], "<" & $Q$2, unit_details[Beds], 3, unit_details[Property Name], B50) - AVERAGEIFS(unit_details[Asking Rent], unit_details[Leased Date], ">=" & ($Q$2 - 14), unit_details[Leased Date], "<=" & ($Q$2 - 7), unit_details[Beds], 3, unit_details[Property Name], B50), 0) -> 0 | J53: =IFERROR(I53/AVERAGEIFS(unit_details[Asking Rent], unit_details[Leased Date], ">=" & ($Q$2 - 14), unit_details[Leased Date], "<=" & ($Q$2 - 7), unit_details[Beds], 3, unit_details[Property Name], B50),0) -> 0 | K53: =COUNTIFS(unit_details[First Listed], ">=" & ($Q$2 - 7), unit_details[First Listed], "<" & $Q$2, unit_details[Beds], 3, unit_details[Property Name], B50) -> 0 | L53: =COUNTIFS( unit_details[First Listed], ">=" & ($Q$2 - 7), unit_details[First Listed], "<" & $Q$2, unit_details[Beds], 3, unit_details[Property Name], B50 ) - COUNTIFS( unit_details[First Listed], ">=" & ($Q$2 - 14), unit_details[First Listed], "<=" & ($Q$2 - 7), unit_details[Beds], 3, unit_details[Property Name], B50 ) -> 0 | M53: =IFERROR(AVERAGEIFS(unit_details[Asking Rent],unit_details[First Listed],">="&($Q$2-7), unit_details[First Listed],"<="&$Q$2, unit_details[Beds],3, unit_details[Property Name],B50),"") | N53: =COUNTIFS(unit_details[Property Name], B50, unit_details[Beds], 3, unit_details[Leased Date], "") -> 0 | O53: =N53-(N53-K53+F53) -> 0 | P53: =IFERROR(AVERAGEIFS(unit_details[Asking Rent],unit_details[Property Name], B50, unit_details[Beds], 3, unit_details[Leased Date], ""),"") | Q53: =IFERROR(N53/SUMIFS(unit_mix_table['# Units],unit_mix_table[Beds],3,unit_mix_table[Property Name],B50),"")
B54: =IF(ISBLANK(OFFSET('Rent Comparison'!$A$1,2,17)),"",IF(OFFSET('Rent Comparison'!$A$1,2,17)=0,B55,OFFSET('Rent Comparison'!$A$1,2,17))) | C54: =IF(ISBLANK(B54),"",IFERROR(INDEX(Specials!B:J,MATCH(B54&" - Active",Specials!I:I,0),2),"")) | E54: Studio | F54: =COUNTIFS(unit_details[Leased Date], ">=" & ($Q$2 - 7), unit_details[Leased Date], "<" & $Q$2, unit_details[Beds], 0, unit_details[Property Name], B54) -> 0 | G54: =COUNTIFS(unit_details[Leased Date], ">=" & ($Q$2 - 7), unit_details[Leased Date], "<" & $Q$2, unit_details[Beds], 0, unit_details[Property Name], B54) - COUNTIFS(unit_details[Leased Date], ">=" & ($Q$2 - 14), unit_details[Leased Date], "<=" & ($Q$2 - 7), unit_details[Beds], 0, unit_details[Property Name], B54) -> 0 | H54: =IFERROR(AVERAGEIFS(unit_details[Asking Rent],unit_details[Leased Date], ">=" & ($Q$2 - 7), unit_details[Leased Date], "<" & $Q$2, unit_details[Beds], 0, unit_details[Property Name], B54),"") | I54: =IFERROR( AVERAGEIFS(unit_details[Asking Rent], unit_details[Leased Date], ">=" & ($Q$2 - 7), unit_details[Leased Date], "<" & $Q$2, unit_details[Beds], 0, unit_details[Property Name], B54) - AVERAGEIFS(unit_details[Asking Rent], unit_details[Leased Date], ">=" & ($Q$2 - 14), unit_details[Leased Date], "<=" & ($Q$2 - 7), unit_details[Beds], 0, unit_details[Property Name], B54), 0) -> 0 | J54: =IFERROR(I54/AVERAGEIFS(unit_details[Asking Rent], unit_details[Leased Date], ">=" & ($Q$2 - 14), unit_details[Leased Date], "<=" & ($Q$2 - 7), unit_details[Beds], 0, unit_details[Property Name], B54),0) -> 0 | K54: =COUNTIFS(unit_details[First Listed], ">=" & ($Q$2 - 7), unit_details[First Listed], "<" & $Q$2, unit_details[Beds], 0, unit_details[Property Name], B54) -> 0 | L54: =COUNTIFS( unit_details[First Listed], ">=" & ($Q$2 - 7), unit_details[First Listed], "<" & $Q$2, unit_details[Beds], 0, unit_details[Property Name], B54 ) - COUNTIFS( unit_details[First Listed], ">=" & ($Q$2 - 14), unit_details[First Listed], "<=" & ($Q$2 - 7), unit_details[Beds], 0, unit_details[Property Name], B54 ) -> 0 | M54: =IFERROR(AVERAGEIFS(unit_details[Asking Rent],unit_details[First Listed],">="&($Q$2-7), unit_details[First Listed],"<="&$Q$2, unit_details[Beds],0, unit_details[Property Name],B54),"") | N54: =COUNTIFS(unit_details[Property Name], B54, unit_details[Beds], 0, unit_details[Leased Date], "") -> 0 | O54: =N54-(N54-K54+F54) -> 0 | P54: =IFERROR(AVERAGEIFS(unit_details[Asking Rent],unit_details[Property Name], B54, unit_details[Beds], 0, unit_details[Leased Date], ""),"") | Q54: =IFERROR(N54/SUMIFS(unit_mix_table['# Units],unit_mix_table[Beds],0,unit_mix_table[Property Name],B54),"")
B55: 1776 Clearview Drive, Delta, CO 81416 | E55: 1 BR | F55: =COUNTIFS(unit_details[Leased Date], ">=" & ($Q$2 - 7), unit_details[Leased Date], "<" & $Q$2, unit_details[Beds], 1, unit_details[Property Name], B54) -> 0 | G55: =COUNTIFS(unit_details[Leased Date], ">=" & ($Q$2 - 7), unit_details[Leased Date], "<" & $Q$2, unit_details[Beds], 1, unit_details[Property Name], B54) - COUNTIFS(unit_details[Leased Date], ">=" & ($Q$2 - 14), unit_details[Leased Date], "<=" & ($Q$2 - 7), unit_details[Beds], 1, unit_details[Property Name], B54) -> 0 | H55: =IFERROR(AVERAGEIFS(unit_details[Asking Rent],unit_details[Leased Date], ">=" & ($Q$2 - 7), unit_details[Leased Date], "<" & $Q$2, unit_details[Beds], 1, unit_details[Property Name], B54),"") | I55: =IFERROR( AVERAGEIFS(unit_details[Asking Rent], unit_details[Leased Date], ">=" & ($Q$2 - 7), unit_details[Leased Date], "<" & $Q$2, unit_details[Beds], 1, unit_details[Property Name], B54) - AVERAGEIFS(unit_details[Asking Rent], unit_details[Leased Date], ">=" & ($Q$2 - 14), unit_details[Leased Date], "<=" & ($Q$2 - 7), unit_details[Beds], 1, unit_details[Property Name], B54), 0) -> 0 | J55: =IFERROR(I55/AVERAGEIFS(unit_details[Asking Rent], unit_details[Leased Date], ">=" & ($Q$2 - 14), unit_details[Leased Date], "<=" & ($Q$2 - 7), unit_details[Beds], 1, unit_details[Property Name], B54),0) -> 0 | K55: =COUNTIFS(unit_details[First Listed], ">=" & ($Q$2 - 7), unit_details[First Listed], "<" & $Q$2, unit_details[Beds], 1, unit_details[Property Name], B54) -> 0 | L55: =COUNTIFS( unit_details[First Listed], ">=" & ($Q$2 - 7), unit_details[First Listed], "<" & $Q$2, unit_details[Beds], 1, unit_details[Property Name], B54 ) - COUNTIFS( unit_details[First Listed], ">=" & ($Q$2 - 14), unit_details[First Listed], "<=" & ($Q$2 - 7), unit_details[Beds], 1, unit_details[Property Name], B54 ) -> 0 | M55: =IFERROR(AVERAGEIFS(unit_details[Asking Rent],unit_details[First Listed],">="&($Q$2-7), unit_details[First Listed],"<="&$Q$2, unit_details[Beds],1, unit_details[Property Name],B54),"") | N55: =COUNTIFS(unit_details[Property Name], B54, unit_details[Beds], 1, unit_details[Leased Date], "") -> 7 | O55: =N55-(N55-K55+F55) -> 0 | P55: =IFERROR(AVERAGEIFS(unit_details[Asking Rent],unit_details[Property Name], B54, unit_details[Beds], 1, unit_details[Leased Date], ""),"") -> 1028.5714 | Q55: =IFERROR(N55/SUMIFS(unit_mix_table['# Units],unit_mix_table[Beds],1,unit_mix_table[Property Name],B54),"") -> 2.3333333
E56: 2 BR | F56: =COUNTIFS(unit_details[Leased Date], ">=" & ($Q$2 - 7), unit_details[Leased Date], "<" & $Q$2, unit_details[Beds], 2, unit_details[Property Name], B54) -> 0 | G56: =COUNTIFS(unit_details[Leased Date], ">=" & ($Q$2 - 7), unit_details[Leased Date], "<" & $Q$2, unit_details[Beds], 2, unit_details[Property Name], B54) - COUNTIFS(unit_details[Leased Date], ">=" & ($Q$2 - 14), unit_details[Leased Date], "<=" & ($Q$2 - 7), unit_details[Beds], 2, unit_details[Property Name], B54) -> 0 | H56: =IFERROR(AVERAGEIFS(unit_details[Asking Rent],unit_details[Leased Date], ">=" & ($Q$2 - 7), unit_details[Leased Date], "<" & $Q$2, unit_details[Beds], 2, unit_details[Property Name], B54),"") | I56: =IFERROR( AVERAGEIFS(unit_details[Asking Rent], unit_details[Leased Date], ">=" & ($Q$2 - 7), unit_details[Leased Date], "<" & $Q$2, unit_details[Beds], 2, unit_details[Property Name], B54) - AVERAGEIFS(unit_details[Asking Rent], unit_details[Leased Date], ">=" & ($Q$2 - 14), unit_details[Leased Date], "<=" & ($Q$2 - 7), unit_details[Beds], 2, unit_details[Property Name], B54), 0) -> 0 | J56: =IFERROR(I56/AVERAGEIFS(unit_details[Asking Rent], unit_details[Leased Date], ">=" & ($Q$2 - 14), unit_details[Leased Date], "<=" & ($Q$2 - 7), unit_details[Beds], 2, unit_details[Property Name], B54),0) -> 0 | K56: =COUNTIFS(unit_details[First Listed], ">=" & ($Q$2 - 7), unit_details[First Listed], "<" & $Q$2, unit_details[Beds], 2, unit_details[Property Name], B54) -> 0 | L56: =COUNTIFS( unit_details[First Listed], ">=" & ($Q$2 - 7), unit_details[First Listed], "<" & $Q$2, unit_details[Beds], 2, unit_details[Property Name], B54 ) - COUNTIFS( unit_details[First Listed], ">=" & ($Q$2 - 14), unit_details[First Listed], "<=" & ($Q$2 - 7), unit_details[Beds], 2, unit_details[Property Name], B54 ) -> 0 | M56: =IFERROR(AVERAGEIFS(unit_details[Asking Rent],unit_details[First Listed],">="&($Q$2-7), unit_details[First Listed],"<="&$Q$2, unit_details[Beds],2, unit_details[Property Name],B54),"") | N56: =COUNTIFS(unit_details[Property Name], B54, unit_details[Beds], 2, unit_details[Leased Date], "") -> 9 | O56: =N56-(N56-K56+F56) -> 0 | P56: =IFERROR(AVERAGEIFS(unit_details[Asking Rent],unit_details[Property Name], B54, unit_details[Beds], 2, unit_details[Leased Date], ""),"") -> 1211.1111 | Q56: =IFERROR(N56/SUMIFS(unit_mix_table['# Units],unit_mix_table[Beds],2,unit_mix_table[Property Name],B54),"") -> 1.5
E57: 3 BR | F57: =COUNTIFS(unit_details[Leased Date], ">=" & ($Q$2 - 7), unit_details[Leased Date], "<" & $Q$2, unit_details[Beds], 3, unit_details[Property Name], B54) -> 0 | G57: =COUNTIFS(unit_details[Leased Date], ">=" & ($Q$2 - 7), unit_details[Leased Date], "<" & $Q$2, unit_details[Beds], 3, unit_details[Property Name], B54) - COUNTIFS(unit_details[Leased Date], ">=" & ($Q$2 - 14), unit_details[Leased Date], "<=" & ($Q$2 - 7), unit_details[Beds], 3, unit_details[Property Name], B54) -> 0 | H57: =IFERROR(AVERAGEIFS(unit_details[Asking Rent],unit_details[Leased Date], ">=" & ($Q$2 - 7), unit_details[Leased Date], "<" & $Q$2, unit_details[Beds], 3, unit_details[Property Name], B54),"") | I57: =IFERROR( AVERAGEIFS(unit_details[Asking Rent], unit_details[Leased Date], ">=" & ($Q$2 - 7), unit_details[Leased Date], "<" & $Q$2, unit_details[Beds], 3, unit_details[Property Name], B54) - AVERAGEIFS(unit_details[Asking Rent], unit_details[Leased Date], ">=" & ($Q$2 - 14), unit_details[Leased Date], "<=" & ($Q$2 - 7), unit_details[Beds], 3, unit_details[Property Name], B54), 0) -> 0 | J57: =IFERROR(I57/AVERAGEIFS(unit_details[Asking Rent], unit_details[Leased Date], ">=" & ($Q$2 - 14), unit_details[Leased Date], "<=" & ($Q$2 - 7), unit_details[Beds], 3, unit_details[Property Name], B54),0) -> 0 | K57: =COUNTIFS(unit_details[First Listed], ">=" & ($Q$2 - 7), unit_details[First Listed], "<" & $Q$2, unit_details[Beds], 3, unit_details[Property Name], B54) -> 0 | L57: =COUNTIFS( unit_details[First Listed], ">=" & ($Q$2 - 7), unit_details[First Listed], "<" & $Q$2, unit_details[Beds], 3, unit_details[Property Name], B54 ) - COUNTIFS( unit_details[First Listed], ">=" & ($Q$2 - 14), unit_details[First Listed], "<=" & ($Q$2 - 7), unit_details[Beds], 3, unit_details[Property Name], B54 ) -> 0 | M57: =IFERROR(AVERAGEIFS(unit_details[Asking Rent],unit_details[First Listed],">="&($Q$2-7), unit_details[First Listed],"<="&$Q$2, unit_details[Beds],3, unit_details[Property Name],B54),"") | N57: =COUNTIFS(unit_details[Property Name], B54, unit_details[Beds], 3, unit_details[Leased Date], "") -> 0 | O57: =N57-(N57-K57+F57) -> 0 | P57: =IFERROR(AVERAGEIFS(unit_details[Asking Rent],unit_details[Property Name], B54, unit_details[Beds], 3, unit_details[Leased Date], ""),"") | Q57: =IFERROR(N57/SUMIFS(unit_mix_table['# Units],unit_mix_table[Beds],3,unit_mix_table[Property Name],B54),"")
B58: =IF(ISBLANK(OFFSET('Rent Comparison'!$A$1,2,18)),"",IF(OFFSET('Rent Comparison'!$A$1,2,18)=0,B59,OFFSET('Rent Comparison'!$A$1,2,18))) | C58: =IF(ISBLANK(B58),"",IFERROR(INDEX(Specials!B:J,MATCH(B58&" - Active",Specials!I:I,0),2),"")) | E58: Studio | F58: =COUNTIFS(unit_details[Leased Date], ">=" & ($Q$2 - 7), unit_details[Leased Date], "<" & $Q$2, unit_details[Beds], 0, unit_details[Property Name], B58) -> 0 | G58: =COUNTIFS(unit_details[Leased Date], ">=" & ($Q$2 - 7), unit_details[Leased Date], "<" & $Q$2, unit_details[Beds], 0, unit_details[Property Name], B58) - COUNTIFS(unit_details[Leased Date], ">=" & ($Q$2 - 14), unit_details[Leased Date], "<=" & ($Q$2 - 7), unit_details[Beds], 0, unit_details[Property Name], B58) -> 0 | H58: =IFERROR(AVERAGEIFS(unit_details[Asking Rent],unit_details[Leased Date], ">=" & ($Q$2 - 7), unit_details[Leased Date], "<" & $Q$2, unit_details[Beds], 0, unit_details[Property Name], B58),"") | I58: =IFERROR( AVERAGEIFS(unit_details[Asking Rent], unit_details[Leased Date], ">=" & ($Q$2 - 7), unit_details[Leased Date], "<" & $Q$2, unit_details[Beds], 0, unit_details[Property Name], B58) - AVERAGEIFS(unit_details[Asking Rent], unit_details[Leased Date], ">=" & ($Q$2 - 14), unit_details[Leased Date], "<=" & ($Q$2 - 7), unit_details[Beds], 0, unit_details[Property Name], B58), 0) -> 0 | J58: =IFERROR(I58/AVERAGEIFS(unit_details[Asking Rent], unit_details[Leased Date], ">=" & ($Q$2 - 14), unit_details[Leased Date], "<=" & ($Q$2 - 7), unit_details[Beds], 0, unit_details[Property Name], B58),0) -> 0 | K58: =COUNTIFS(unit_details[First Listed], ">=" & ($Q$2 - 7), unit_details[First Listed], "<" & $Q$2, unit_details[Beds], 0, unit_details[Property Name], B58) -> 0 | L58: =COUNTIFS( unit_details[First Listed], ">=" & ($Q$2 - 7), unit_details[First Listed], "<" & $Q$2, unit_details[Beds], 0, unit_details[Property Name], B58 ) - COUNTIFS( unit_details[First Listed], ">=" & ($Q$2 - 14), unit_details[First Listed], "<=" & ($Q$2 - 7), unit_details[Beds], 0, unit_details[Property Name], B58 ) -> 0 | M58: =IFERROR(AVERAGEIFS(unit_details[Asking Rent],unit_details[First Listed],">="&($Q$2-7), unit_details[First Listed],"<="&$Q$2, unit_details[Beds],0, unit_details[Property Name],B58),"") | N58: =COUNTIFS(unit_details[Property Name], B58, unit_details[Beds], 0, unit_details[Leased Date], "") -> 0 | O58: =N58-(N58-K58+F58) -> 0 | P58: =IFERROR(AVERAGEIFS(unit_details[Asking Rent],unit_details[Property Name], B58, unit_details[Beds], 0, unit_details[Leased Date], ""),"") | Q58: =IFERROR(N58/SUMIFS(unit_mix_table['# Units],unit_mix_table[Beds],0,unit_mix_table[Property Name],B58),"")
B59: 1304 Howard Street, Delta, CO 81416 | E59: 1 BR | F59: =COUNTIFS(unit_details[Leased Date], ">=" & ($Q$2 - 7), unit_details[Leased Date], "<" & $Q$2, unit_details[Beds], 1, unit_details[Property Name], B58) -> 0 | G59: =COUNTIFS(unit_details[Leased Date], ">=" & ($Q$2 - 7), unit_details[Leased Date], "<" & $Q$2, unit_details[Beds], 1, unit_details[Property Name], B58) - COUNTIFS(unit_details[Leased Date], ">=" & ($Q$2 - 14), unit_details[Leased Date], "<=" & ($Q$2 - 7), unit_details[Beds], 1, unit_details[Property Name], B58) -> 0 | H59: =IFERROR(AVERAGEIFS(unit_details[Asking Rent],unit_details[Leased Date], ">=" & ($Q$2 - 7), unit_details[Leased Date], "<" & $Q$2, unit_details[Beds], 1, unit_details[Property Name], B58),"") | I59: =IFERROR( AVERAGEIFS(unit_details[Asking Rent], unit_details[Leased Date], ">=" & ($Q$2 - 7), unit_details[Leased Date], "<" & $Q$2, unit_details[Beds], 1, unit_details[Property Name], B58) - AVERAGEIFS(unit_details[Asking Rent], unit_details[Leased Date], ">=" & ($Q$2 - 14), unit_details[Leased Date], "<=" & ($Q$2 - 7), unit_details[Beds], 1, unit_details[Property Name], B58), 0) -> 0 | J59: =IFERROR(I59/AVERAGEIFS(unit_details[Asking Rent], unit_details[Leased Date], ">=" & ($Q$2 - 14), unit_details[Leased Date], "<=" & ($Q$2 - 7), unit_details[Beds], 1, unit_details[Property Name], B58),0) -> 0 | K59: =COUNTIFS(unit_details[First Listed], ">=" & ($Q$2 - 7), unit_details[First Listed], "<" & $Q$2, unit_details[Beds], 1, unit_details[Property Name], B58) -> 0 | L59: =COUNTIFS( unit_details[First Listed], ">=" & ($Q$2 - 7), unit_details[First Listed], "<" & $Q$2, unit_details[Beds], 1, unit_details[Property Name], B58 ) - COUNTIFS( unit_details[First Listed], ">=" & ($Q$2 - 14), unit_details[First Listed], "<=" & ($Q$2 - 7), unit_details[Beds], 1, unit_details[Property Name], B58 ) -> 0 | M59: =IFERROR(AVERAGEIFS(unit_details[Asking Rent],unit_details[First Listed],">="&($Q$2-7), unit_details[First Listed],"<="&$Q$2, unit_details[Beds],1, unit_details[Property Name],B58),"") | N59: =COUNTIFS(unit_details[Property Name], B58, unit_details[Beds], 1, unit_details[Leased Date], "") -> 7 | O59: =N59-(N59-K59+F59) -> 0 | P59: =IFERROR(AVERAGEIFS(unit_details[Asking Rent],unit_details[Property Name], B58, unit_details[Beds], 1, unit_details[Leased Date], ""),"") -> 1028.5714 | Q59: =IFERROR(N59/SUMIFS(unit_mix_table['# Units],unit_mix_table[Beds],1,unit_mix_table[Property Name],B58),"") -> 2.3333333
E60: 2 BR | F60: =COUNTIFS(unit_details[Leased Date], ">=" & ($Q$2 - 7), unit_details[Leased Date], "<" & $Q$2, unit_details[Beds], 2, unit_details[Property Name], B58) -> 0 | G60: =COUNTIFS(unit_details[Leased Date], ">=" & ($Q$2 - 7), unit_details[Leased Date], "<" & $Q$2, unit_details[Beds], 2, unit_details[Property Name], B58) - COUNTIFS(unit_details[Leased Date], ">=" & ($Q$2 - 14), unit_details[Leased Date], "<=" & ($Q$2 - 7), unit_details[Beds], 2, unit_details[Property Name], B58) -> 0 | H60: =IFERROR(AVERAGEIFS(unit_details[Asking Rent],unit_details[Leased Date], ">=" & ($Q$2 - 7), unit_details[Leased Date], "<" & $Q$2, unit_details[Beds], 2, unit_details[Property Name], B58),"") | I60: =IFERROR( AVERAGEIFS(unit_details[Asking Rent], unit_details[Leased Date], ">=" & ($Q$2 - 7), unit_details[Leased Date], "<" & $Q$2, unit_details[Beds], 2, unit_details[Property Name], B58) - AVERAGEIFS(unit_details[Asking Rent], unit_details[Leased Date], ">=" & ($Q$2 - 14), unit_details[Leased Date], "<=" & ($Q$2 - 7), unit_details[Beds], 2, unit_details[Property Name], B58), 0) -> 0 | J60: =IFERROR(I60/AVERAGEIFS(unit_details[Asking Rent], unit_details[Leased Date], ">=" & ($Q$2 - 14), unit_details[Leased Date], "<=" & ($Q$2 - 7), unit_details[Beds], 2, unit_details[Property Name], B58),0) -> 0 | K60: =COUNTIFS(unit_details[First Listed], ">=" & ($Q$2 - 7), unit_details[First Listed], "<" & $Q$2, unit_details[Beds], 2, unit_details[Property Name], B58) -> 0 | L60: =COUNTIFS( unit_details[First Listed], ">=" & ($Q$2 - 7), unit_details[First Listed], "<" & $Q$2, unit_details[Beds], 2, unit_details[Property Name], B58 ) - COUNTIFS( unit_details[First Listed], ">=" & ($Q$2 - 14), unit_details[First Listed], "<=" & ($Q$2 - 7), unit_details[Beds], 2, unit_details[Property Name], B58 ) -> 0 | M60: =IFERROR(AVERAGEIFS(unit_details[Asking Rent],unit_details[First Listed],">="&($Q$2-7), unit_details[First Listed],"<="&$Q$2, unit_details[Beds],2, unit_details[Property Name],B58),"") | N60: =COUNTIFS(unit_details[Property Name], B58, unit_details[Beds], 2, unit_details[Leased Date], "") -> 9 | O60: =N60-(N60-K60+F60) -> 0 | P60: =IFERROR(AVERAGEIFS(unit_details[Asking Rent],unit_details[Property Name], B58, unit_details[Beds], 2, unit_details[Leased Date], ""),"") -> 1211.1111 | Q60: =IFERROR(N60/SUMIFS(unit_mix_table['# Units],unit_mix_table[Beds],2,unit_mix_table[Property Name],B58),"") -> 1.5
E61: 3 BR | F61: =COUNTIFS(unit_details[Leased Date], ">=" & ($Q$2 - 7), unit_details[Leased Date], "<" & $Q$2, unit_details[Beds], 3, unit_details[Property Name], B58) -> 0 | G61: =COUNTIFS(unit_details[Leased Date], ">=" & ($Q$2 - 7), unit_details[Leased Date], "<" & $Q$2, unit_details[Beds], 3, unit_details[Property Name], B58) - COUNTIFS(unit_details[Leased Date], ">=" & ($Q$2 - 14), unit_details[Leased Date], "<=" & ($Q$2 - 7), unit_details[Beds], 3, unit_details[Property Name], B58) -> 0 | H61: =IFERROR(AVERAGEIFS(unit_details[Asking Rent],unit_details[Leased Date], ">=" & ($Q$2 - 7), unit_details[Leased Date], "<" & $Q$2, unit_details[Beds], 3, unit_details[Property Name], B58),"") | I61: =IFERROR( AVERAGEIFS(unit_details[Asking Rent], unit_details[Leased Date], ">=" & ($Q$2 - 7), unit_details[Leased Date], "<" & $Q$2, unit_details[Beds], 3, unit_details[Property Name], B58) - AVERAGEIFS(unit_details[Asking Rent], unit_details[Leased Date], ">=" & ($Q$2 - 14), unit_details[Leased Date], "<=" & ($Q$2 - 7), unit_details[Beds], 3, unit_details[Property Name], B58), 0) -> 0 | J61: =IFERROR(I61/AVERAGEIFS(unit_details[Asking Rent], unit_details[Leased Date], ">=" & ($Q$2 - 14), unit_details[Leased Date], "<=" & ($Q$2 - 7), unit_details[Beds], 3, unit_details[Property Name], B58),0) -> 0 | K61: =COUNTIFS(unit_details[First Listed], ">=" & ($Q$2 - 7), unit_details[First Listed], "<" & $Q$2, unit_details[Beds], 3, unit_details[Property Name], B58) -> 0 | L61: =COUNTIFS( unit_details[First Listed], ">=" & ($Q$2 - 7), unit_details[First Listed], "<" & $Q$2, unit_details[Beds], 3, unit_details[Property Name], B58 ) - COUNTIFS( unit_details[First Listed], ">=" & ($Q$2 - 14), unit_details[First Listed], "<=" & ($Q$2 - 7), unit_details[Beds], 3, unit_details[Property Name], B58 ) -> 0 | M61: =IFERROR(AVERAGEIFS(unit_details[Asking Rent],unit_details[First Listed],">="&($Q$2-7), unit_details[First Listed],"<="&$Q$2, unit_details[Beds],3, unit_details[Property Name],B58),"") | N61: =COUNTIFS(unit_details[Property Name], B58, unit_details[Beds], 3, unit_details[Leased Date], "") -> 0 | O61: =N61-(N61-K61+F61) -> 0 | P61: =IFERROR(AVERAGEIFS(unit_details[Asking Rent],unit_details[Property Name], B58, unit_details[Beds], 3, unit_details[Leased Date], ""),"") | Q61: =IFERROR(N61/SUMIFS(unit_mix_table['# Units],unit_mix_table[Beds],3,unit_mix_table[Property Name],B58),"")
B62: =IF(ISBLANK(OFFSET('Rent Comparison'!$A$1,2,19)),"",IF(OFFSET('Rent Comparison'!$A$1,2,19)=0,B63,OFFSET('Rent Comparison'!$A$1,2,19))) | C62: =IF(ISBLANK(B62),"",IFERROR(INDEX(Specials!B:J,MATCH(B62&" - Active",Specials!I:I,0),2),"")) | E62: Studio | F62: =COUNTIFS(unit_details[Leased Date], ">=" & ($Q$2 - 7), unit_details[Leased Date], "<" & $Q$2, unit_details[Beds], 0, unit_details[Property Name], B62) -> 0 | G62: =COUNTIFS(unit_details[Leased Date], ">=" & ($Q$2 - 7), unit_details[Leased Date], "<" & $Q$2, unit_details[Beds], 0, unit_details[Property Name], B62) - COUNTIFS(unit_details[Leased Date], ">=" & ($Q$2 - 14), unit_details[Leased Date], "<=" & ($Q$2 - 7), unit_details[Beds], 0, unit_details[Property Name], B62) -> 0 | H62: =IFERROR(AVERAGEIFS(unit_details[Asking Rent],unit_details[Leased Date], ">=" & ($Q$2 - 7), unit_details[Leased Date], "<" & $Q$2, unit_details[Beds], 0, unit_details[Property Name], B62),"") | I62: =IFERROR( AVERAGEIFS(unit_details[Asking Rent], unit_details[Leased Date], ">=" & ($Q$2 - 7), unit_details[Leased Date], "<" & $Q$2, unit_details[Beds], 0, unit_details[Property Name], B62) - AVERAGEIFS(unit_details[Asking Rent], unit_details[Leased Date], ">=" & ($Q$2 - 14), unit_details[Leased Date], "<=" & ($Q$2 - 7), unit_details[Beds], 0, unit_details[Property Name], B62), 0) -> 0 | J62: =IFERROR(I62/AVERAGEIFS(unit_details[Asking Rent], unit_details[Leased Date], ">=" & ($Q$2 - 14), unit_details[Leased Date], "<=" & ($Q$2 - 7), unit_details[Beds], 0, unit_details[Property Name], B62),0) -> 0 | K62: =COUNTIFS(unit_details[First Listed], ">=" & ($Q$2 - 7), unit_details[First Listed], "<" & $Q$2, unit_details[Beds], 0, unit_details[Property Name], B62) -> 0 | L62: =COUNTIFS( unit_details[First Listed], ">=" & ($Q$2 - 7), unit_details[First Listed], "<" & $Q$2, unit_details[Beds], 0, unit_details[Property Name], B62 ) - COUNTIFS( unit_details[First Listed], ">=" & ($Q$2 - 14), unit_details[First Listed], "<=" & ($Q$2 - 7), unit_details[Beds], 0, unit_details[Property Name], B62 ) -> 0 | M62: =IFERROR(AVERAGEIFS(unit_details[Asking Rent],unit_details[First Listed],">="&($Q$2-7), unit_details[First Listed],"<="&$Q$2, unit_details[Beds],0, unit_details[Property Name],B62),"") | N62: =COUNTIFS(unit_details[Property Name], B62, unit_details[Beds], 0, unit_details[Leased Date], "") -> 0 | O62: =N62-(N62-K62+F62) -> 0 | P62: =IFERROR(AVERAGEIFS(unit_details[Asking Rent],unit_details[Property Name], B62, unit_details[Beds], 0, unit_details[Leased Date], ""),"") | Q62: =IFERROR(N62/SUMIFS(unit_mix_table['# Units],unit_mix_table[Beds],0,unit_mix_table[Property Name],B62),"")
B63: 210 East 5th Street, Delta, CO 81416 | E63: 1 BR | F63: =COUNTIFS(unit_details[Leased Date], ">=" & ($Q$2 - 7), unit_details[Leased Date], "<" & $Q$2, unit_details[Beds], 1, unit_details[Property Name], B62) -> 0 | G63: =COUNTIFS(unit_details[Leased Date], ">=" & ($Q$2 - 7), unit_details[Leased Date], "<" & $Q$2, unit_details[Beds], 1, unit_details[Property Name], B62) - COUNTIFS(unit_details[Leased Date], ">=" & ($Q$2 - 14), unit_details[Leased Date], "<=" & ($Q$2 - 7), unit_details[Beds], 1, unit_details[Property Name], B62) -> 0 | H63: =IFERROR(AVERAGEIFS(unit_details[Asking Rent],unit_details[Leased Date], ">=" & ($Q$2 - 7), unit_details[Leased Date], "<" & $Q$2, unit_details[Beds], 1, unit_details[Property Name], B62),"") | I63: =IFERROR( AVERAGEIFS(unit_details[Asking Rent], unit_details[Leased Date], ">=" & ($Q$2 - 7), unit_details[Leased Date], "<" & $Q$2, unit_details[Beds], 1, unit_details[Property Name], B62) - AVERAGEIFS(unit_details[Asking Rent], unit_details[Leased Date], ">=" & ($Q$2 - 14), unit_details[Leased Date], "<=" & ($Q$2 - 7), unit_details[Beds], 1, unit_details[Property Name], B62), 0) -> 0 | J63: =IFERROR(I63/AVERAGEIFS(unit_details[Asking Rent], unit_details[Leased Date], ">=" & ($Q$2 - 14), unit_details[Leased Date], "<=" & ($Q$2 - 7), unit_details[Beds], 1, unit_details[Property Name], B62),0) -> 0 | K63: =COUNTIFS(unit_details[First Listed], ">=" & ($Q$2 - 7), unit_details[First Listed], "<" & $Q$2, unit_details[Beds], 1, unit_details[Property Name], B62) -> 0 | L63: =COUNTIFS( unit_details[First Listed], ">=" & ($Q$2 - 7), unit_details[First Listed], "<" & $Q$2, unit_details[Beds], 1, unit_details[Property Name], B62 ) - COUNTIFS( unit_details[First Listed], ">=" & ($Q$2 - 14), unit_details[First Listed], "<=" & ($Q$2 - 7), unit_details[Beds], 1, unit_details[Property Name], B62 ) -> 0 | M63: =IFERROR(AVERAGEIFS(unit_details[Asking Rent],unit_details[First Listed],">="&($Q$2-7), unit_details[First Listed],"<="&$Q$2, unit_details[Beds],1, unit_details[Property Name],B62),"") | N63: =COUNTIFS(unit_details[Property Name], B62, unit_details[Beds], 1, unit_details[Leased Date], "") -> 7 | O63: =N63-(N63-K63+F63) -> 0 | P63: =IFERROR(AVERAGEIFS(unit_details[Asking Rent],unit_details[Property Name], B62, unit_details[Beds], 1, unit_details[Leased Date], ""),"") -> 1028.5714 | Q63: =IFERROR(N63/SUMIFS(unit_mix_table['# Units],unit_mix_table[Beds],1,unit_mix_table[Property Name],B62),"") -> 2.3333333
E64: 2 BR | F64: =COUNTIFS(unit_details[Leased Date], ">=" & ($Q$2 - 7), unit_details[Leased Date], "<" & $Q$2, unit_details[Beds], 2, unit_details[Property Name], B62) -> 0 | G64: =COUNTIFS(unit_details[Leased Date], ">=" & ($Q$2 - 7), unit_details[Leased Date], "<" & $Q$2, unit_details[Beds], 2, unit_details[Property Name], B62) - COUNTIFS(unit_details[Leased Date], ">=" & ($Q$2 - 14), unit_details[Leased Date], "<=" & ($Q$2 - 7), unit_details[Beds], 2, unit_details[Property Name], B62) -> 0 | H64: =IFERROR(AVERAGEIFS(unit_details[Asking Rent],unit_details[Leased Date], ">=" & ($Q$2 - 7), unit_details[Leased Date], "<" & $Q$2, unit_details[Beds], 2, unit_details[Property Name], B62),"") | I64: =IFERROR( AVERAGEIFS(unit_details[Asking Rent], unit_details[Leased Date], ">=" & ($Q$2 - 7), unit_details[Leased Date], "<" & $Q$2, unit_details[Beds], 2, unit_details[Property Name], B62) - AVERAGEIFS(unit_details[Asking Rent], unit_details[Leased Date], ">=" & ($Q$2 - 14), unit_details[Leased Date], "<=" & ($Q$2 - 7), unit_details[Beds], 2, unit_details[Property Name], B62), 0) -> 0 | J64: =IFERROR(I64/AVERAGEIFS(unit_details[Asking Rent], unit_details[Leased Date], ">=" & ($Q$2 - 14), unit_details[Leased Date], "<=" & ($Q$2 - 7), unit_details[Beds], 2, unit_details[Property Name], B62),0) -> 0 | K64: =COUNTIFS(unit_details[First Listed], ">=" & ($Q$2 - 7), unit_details[First Listed], "<" & $Q$2, unit_details[Beds], 2, unit_details[Property Name], B62) -> 0 | L64: =COUNTIFS( unit_details[First Listed], ">=" & ($Q$2 - 7), unit_details[First Listed], "<" & $Q$2, unit_details[Beds], 2, unit_details[Property Name], B62 ) - COUNTIFS( unit_details[First Listed], ">=" & ($Q$2 - 14), unit_details[First Listed], "<=" & ($Q$2 - 7), unit_details[Beds], 2, unit_details[Property Name], B62 ) -> 0 | M64: =IFERROR(AVERAGEIFS(unit_details[Asking Rent],unit_details[First Listed],">="&($Q$2-7), unit_details[First Listed],"<="&$Q$2, unit_details[Beds],2, unit_details[Property Name],B62),"") | N64: =COUNTIFS(unit_details[Property Name], B62, unit_details[Beds], 2, unit_details[Leased Date], "") -> 9 | O64: =N64-(N64-K64+F64) -> 0 | P64: =IFERROR(AVERAGEIFS(unit_details[Asking Rent],unit_details[Property Name], B62, unit_details[Beds], 2, unit_details[Leased Date], ""),"") -> 1211.1111 | Q64: =IFERROR(N64/SUMIFS(unit_mix_table['# Units],unit_mix_table[Beds],2,unit_mix_table[Property Name],B62),"") -> 1.5
E65: 3 BR | F65: =COUNTIFS(unit_details[Leased Date], ">=" & ($Q$2 - 7), unit_details[Leased Date], "<" & $Q$2, unit_details[Beds], 3, unit_details[Property Name], B62) -> 0 | G65: =COUNTIFS(unit_details[Leased Date], ">=" & ($Q$2 - 7), unit_details[Leased Date], "<" & $Q$2, unit_details[Beds], 3, unit_details[Property Name], B62) - COUNTIFS(unit_details[Leased Date], ">=" & ($Q$2 - 14), unit_details[Leased Date], "<=" & ($Q$2 - 7), unit_details[Beds], 3, unit_details[Property Name], B62) -> 0 | H65: =IFERROR(AVERAGEIFS(unit_details[Asking Rent],unit_details[Leased Date], ">=" & ($Q$2 - 7), unit_details[Leased Date], "<" & $Q$2, unit_details[Beds], 3, unit_details[Property Name], B62),"") | I65: =IFERROR( AVERAGEIFS(unit_details[Asking Rent], unit_details[Leased Date], ">=" & ($Q$2 - 7), unit_details[Leased Date], "<" & $Q$2, unit_details[Beds], 3, unit_details[Property Name], B62) - AVERAGEIFS(unit_details[Asking Rent], unit_details[Leased Date], ">=" & ($Q$2 - 14), unit_details[Leased Date], "<=" & ($Q$2 - 7), unit_details[Beds], 3, unit_details[Property Name], B62), 0) -> 0 | J65: =IFERROR(I65/AVERAGEIFS(unit_details[Asking Rent], unit_details[Leased Date], ">=" & ($Q$2 - 14), unit_details[Leased Date], "<=" & ($Q$2 - 7), unit_details[Beds], 3, unit_details[Property Name], B62),0) -> 0 | K65: =COUNTIFS(unit_details[First Listed], ">=" & ($Q$2 - 7), unit_details[First Listed], "<" & $Q$2, unit_details[Beds], 3, unit_details[Property Name], B62) -> 0 | L65: =COUNTIFS( unit_details[First Listed], ">=" & ($Q$2 - 7), unit_details[First Listed], "<" & $Q$2, unit_details[Beds], 3, unit_details[Property Name], B62 ) - COUNTIFS( unit_details[First Listed], ">=" & ($Q$2 - 14), unit_details[First Listed], "<=" & ($Q$2 - 7), unit_details[Beds], 3, unit_details[Property Name], B62 ) -> 0 | M65: =IFERROR(AVERAGEIFS(unit_details[Asking Rent],unit_details[First Listed],">="&($Q$2-7), unit_details[First Listed],"<="&$Q$2, unit_details[Beds],3, unit_details[Property Name],B62),"") | N65: =COUNTIFS(unit_details[Property Name], B62, unit_details[Beds], 3, unit_details[Leased Date], "") -> 0 | O65: =N65-(N65-K65+F65) -> 0 | P65: =IFERROR(AVERAGEIFS(unit_details[Asking Rent],unit_details[Property Name], B62, unit_details[Beds], 3, unit_details[Leased Date], ""),"") | Q65: =IFERROR(N65/SUMIFS(unit_mix_table['# Units],unit_mix_table[Beds],3,unit_mix_table[Property Name],B62),"")
B66: =IF(ISBLANK(OFFSET('Rent Comparison'!$A$1,2,20)),"",IF(OFFSET('Rent Comparison'!$A$1,2,20)=0,B67,OFFSET('Rent Comparison'!$A$1,2,20))) -> 625 A Street - 4 (29-4) | C66: =IF(ISBLANK(B66),"",IFERROR(INDEX(Specials!B:J,MATCH(B66&" - Active",Specials!I:I,0),2),"")) | E66: Studio | F66: =COUNTIFS(unit_details[Leased Date], ">=" & ($Q$2 - 7), unit_details[Leased Date], "<" & $Q$2, unit_details[Beds], 0, unit_details[Property Name], B66) -> 0 | G66: =COUNTIFS(unit_details[Leased Date], ">=" & ($Q$2 - 7), unit_details[Leased Date], "<" & $Q$2, unit_details[Beds], 0, unit_details[Property Name], B66) - COUNTIFS(unit_details[Leased Date], ">=" & ($Q$2 - 14), unit_details[Leased Date], "<=" & ($Q$2 - 7), unit_details[Beds], 0, unit_details[Property Name], B66) -> 0 | H66: =IFERROR(AVERAGEIFS(unit_details[Asking Rent],unit_details[Leased Date], ">=" & ($Q$2 - 7), unit_details[Leased Date], "<" & $Q$2, unit_details[Beds], 0, unit_details[Property Name], B66),"") | I66: =IFERROR( AVERAGEIFS(unit_details[Asking Rent], unit_details[Leased Date], ">=" & ($Q$2 - 7), unit_details[Leased Date], "<" & $Q$2, unit_details[Beds], 0, unit_details[Property Name], B66) - AVERAGEIFS(unit_details[Asking Rent], unit_details[Leased Date], ">=" & ($Q$2 - 14), unit_details[Leased Date], "<=" & ($Q$2 - 7), unit_details[Beds], 0, unit_details[Property Name], B66), 0) -> 0 | J66: =IFERROR(I66/AVERAGEIFS(unit_details[Asking Rent], unit_details[Leased Date], ">=" & ($Q$2 - 14), unit_details[Leased Date], "<=" & ($Q$2 - 7), unit_details[Beds], 0, unit_details[Property Name], B66),0) -> 0 | K66: =COUNTIFS(unit_details[First Listed], ">=" & ($Q$2 - 7), unit_details[First Listed], "<" & $Q$2, unit_details[Beds], 0, unit_details[Property Name], B66) -> 0 | L66: =COUNTIFS( unit_details[First Listed], ">=" & ($Q$2 - 7), unit_details[First Listed], "<" & $Q$2, unit_details[Beds], 0, unit_details[Property Name], B66 ) - COUNTIFS( unit_details[First Listed], ">=" & ($Q$2 - 14), unit_details[First Listed], "<=" & ($Q$2 - 7), unit_details[Beds], 0, unit_details[Property Name], B66 ) -> 0 | M66: =IFERROR(AVERAGEIFS(unit_details[Asking Rent],unit_details[First Listed],">="&($Q$2-7), unit_details[First Listed],"<="&$Q$2, unit_details[Beds],0, unit_details[Property Name],B66),"") | N66: =COUNTIFS(unit_details[Property Name], B66, unit_details[Beds], 0, unit_details[Leased Date], "") -> 0 | O66: =N66-(N66-K66+F66) -> 0 | P66: =IFERROR(AVERAGEIFS(unit_details[Asking Rent],unit_details[Property Name], B66, unit_details[Beds], 0, unit_details[Leased Date], ""),"") | Q66: =IFERROR(N66/SUMIFS(unit_mix_table['# Units],unit_mix_table[Beds],0,unit_mix_table[Property Name],B66),"")
B67: 625 A Street, Delta, CO 81416 | E67: 1 BR | F67: =COUNTIFS(unit_details[Leased Date], ">=" & ($Q$2 - 7), unit_details[Leased Date], "<" & $Q$2, unit_details[Beds], 1, unit_details[Property Name], B66) -> 0 | G67: =COUNTIFS(unit_details[Leased Date], ">=" & ($Q$2 - 7), unit_details[Leased Date], "<" & $Q$2, unit_details[Beds], 1, unit_details[Property Name], B66) - COUNTIFS(unit_details[Leased Date], ">=" & ($Q$2 - 14), unit_details[Leased Date], "<=" & ($Q$2 - 7), unit_details[Beds], 1, unit_details[Property Name], B66) -> 0 | H67: =IFERROR(AVERAGEIFS(unit_details[Asking Rent],unit_details[Leased Date], ">=" & ($Q$2 - 7), unit_details[Leased Date], "<" & $Q$2, unit_details[Beds], 1, unit_details[Property Name], B66),"") | I67: =IFERROR( AVERAGEIFS(unit_details[Asking Rent], unit_details[Leased Date], ">=" & ($Q$2 - 7), unit_details[Leased Date], "<" & $Q$2, unit_details[Beds], 1, unit_details[Property Name], B66) - AVERAGEIFS(unit_details[Asking Rent], unit_details[Leased Date], ">=" & ($Q$2 - 14), unit_details[Leased Date], "<=" & ($Q$2 - 7), unit_details[Beds], 1, unit_details[Property Name], B66), 0) -> 0 | J67: =IFERROR(I67/AVERAGEIFS(unit_details[Asking Rent], unit_details[Leased Date], ">=" & ($Q$2 - 14), unit_details[Leased Date], "<=" & ($Q$2 - 7), unit_details[Beds], 1, unit_details[Property Name], B66),0) -> 0 | K67: =COUNTIFS(unit_details[First Listed], ">=" & ($Q$2 - 7), unit_details[First Listed], "<" & $Q$2, unit_details[Beds], 1, unit_details[Property Name], B66) -> 0 | L67: =COUNTIFS( unit_details[First Listed], ">=" & ($Q$2 - 7), unit_details[First Listed], "<" & $Q$2, unit_details[Beds], 1, unit_details[Property Name], B66 ) - COUNTIFS( unit_details[First Listed], ">=" & ($Q$2 - 14), unit_details[First Listed], "<=" & ($Q$2 - 7), unit_details[Beds], 1, unit_details[Property Name], B66 ) -> 0 | M67: =IFERROR(AVERAGEIFS(unit_details[Asking Rent],unit_details[First Listed],">="&($Q$2-7), unit_details[First Listed],"<="&$Q$2, unit_details[Beds],1, unit_details[Property Name],B66),"") | N67: =COUNTIFS(unit_details[Property Name], B66, unit_details[Beds], 1, unit_details[Leased Date], "") -> 0 | O67: =N67-(N67-K67+F67) -> 0 | P67: =IFERROR(AVERAGEIFS(unit_details[Asking Rent],unit_details[Property Name], B66, unit_details[Beds], 1, unit_details[Leased Date], ""),"") | Q67: =IFERROR(N67/SUMIFS(unit_mix_table['# Units],unit_mix_table[Beds],1,unit_mix_table[Property Name],B66),"")
E68: 2 BR | F68: =COUNTIFS(unit_details[Leased Date], ">=" & ($Q$2 - 7), unit_details[Leased Date], "<" & $Q$2, unit_details[Beds], 2, unit_details[Property Name], B66) -> 0 | G68: =COUNTIFS(unit_details[Leased Date], ">=" & ($Q$2 - 7), unit_details[Leased Date], "<" & $Q$2, unit_details[Beds], 2, unit_details[Property Name], B66) - COUNTIFS(unit_details[Leased Date], ">=" & ($Q$2 - 14), unit_details[Leased Date], "<=" & ($Q$2 - 7), unit_details[Beds], 2, unit_details[Property Name], B66) -> 0 | H68: =IFERROR(AVERAGEIFS(unit_details[Asking Rent],unit_details[Leased Date], ">=" & ($Q$2 - 7), unit_details[Leased Date], "<" & $Q$2, unit_details[Beds], 2, unit_details[Property Name], B66),"") | I68: =IFERROR( AVERAGEIFS(unit_details[Asking Rent], unit_details[Leased Date], ">=" & ($Q$2 - 7), unit_details[Leased Date], "<" & $Q$2, unit_details[Beds], 2, unit_details[Property Name], B66) - AVERAGEIFS(unit_details[Asking Rent], unit_details[Leased Date], ">=" & ($Q$2 - 14), unit_details[Leased Date], "<=" & ($Q$2 - 7), unit_details[Beds], 2, unit_details[Property Name], B66), 0) -> 0 | J68: =IFERROR(I68/AVERAGEIFS(unit_details[Asking Rent], unit_details[Leased Date], ">=" & ($Q$2 - 14), unit_details[Leased Date], "<=" & ($Q$2 - 7), unit_details[Beds], 2, unit_details[Property Name], B66),0) -> 0 | K68: =COUNTIFS(unit_details[First Listed], ">=" & ($Q$2 - 7), unit_details[First Listed], "<" & $Q$2, unit_details[Beds], 2, unit_details[Property Name], B66) -> 0 | L68: =COUNTIFS( unit_details[First Listed], ">=" & ($Q$2 - 7), unit_details[First Listed], "<" & $Q$2, unit_details[Beds], 2, unit_details[Property Name], B66 ) - COUNTIFS( unit_details[First Listed], ">=" & ($Q$2 - 14), unit_details[First Listed], "<=" & ($Q$2 - 7), unit_details[Beds], 2, unit_details[Property Name], B66 ) -> 0 | M68: =IFERROR(AVERAGEIFS(unit_details[Asking Rent],unit_details[First Listed],">="&($Q$2-7), unit_details[First Listed],"<="&$Q$2, unit_details[Beds],2, unit_details[Property Name],B66),"") | N68: =COUNTIFS(unit_details[Property Name], B66, unit_details[Beds], 2, unit_details[Leased Date], "") -> 2 | O68: =N68-(N68-K68+F68) -> 0 | P68: =IFERROR(AVERAGEIFS(unit_details[Asking Rent],unit_details[Property Name], B66, unit_details[Beds], 2, unit_details[Leased Date], ""),"") -> 1150 | Q68: =IFERROR(N68/SUMIFS(unit_mix_table['# Units],unit_mix_table[Beds],2,unit_mix_table[Property Name],B66),"")
E69: 3 BR | F69: =COUNTIFS(unit_details[Leased Date], ">=" & ($Q$2 - 7), unit_details[Leased Date], "<" & $Q$2, unit_details[Beds], 3, unit_details[Property Name], B66) -> 0 | G69: =COUNTIFS(unit_details[Leased Date], ">=" & ($Q$2 - 7), unit_details[Leased Date], "<" & $Q$2, unit_details[Beds], 3, unit_details[Property Name], B66) - COUNTIFS(unit_details[Leased Date], ">=" & ($Q$2 - 14), unit_details[Leased Date], "<=" & ($Q$2 - 7), unit_details[Beds], 3, unit_details[Property Name], B66) -> 0 | H69: =IFERROR(AVERAGEIFS(unit_details[Asking Rent],unit_details[Leased Date], ">=" & ($Q$2 - 7), unit_details[Leased Date], "<" & $Q$2, unit_details[Beds], 3, unit_details[Property Name], B66),"") | I69: =IFERROR( AVERAGEIFS(unit_details[Asking Rent], unit_details[Leased Date], ">=" & ($Q$2 - 7), unit_details[Leased Date], "<" & $Q$2, unit_details[Beds], 3, unit_details[Property Name], B66) - AVERAGEIFS(unit_details[Asking Rent], unit_details[Leased Date], ">=" & ($Q$2 - 14), unit_details[Leased Date], "<=" & ($Q$2 - 7), unit_details[Beds], 3, unit_details[Property Name], B66), 0) -> 0 | J69: =IFERROR(I69/AVERAGEIFS(unit_details[Asking Rent], unit_details[Leased Date], ">=" & ($Q$2 - 14), unit_details[Leased Date], "<=" & ($Q$2 - 7), unit_details[Beds], 3, unit_details[Property Name], B66),0) -> 0 | K69: =COUNTIFS(unit_details[First Listed], ">=" & ($Q$2 - 7), unit_details[First Listed], "<" & $Q$2, unit_details[Beds], 3, unit_details[Property Name], B66) -> 0 | L69: =COUNTIFS( unit_details[First Listed], ">=" & ($Q$2 - 7), unit_details[First Listed], "<" & $Q$2, unit_details[Beds], 3, unit_details[Property Name], B66 ) - COUNTIFS( unit_details[First Listed], ">=" & ($Q$2 - 14), unit_details[First Listed], "<=" & ($Q$2 - 7), unit_details[Beds], 3, unit_details[Property Name], B66 ) -> 0 | M69: =IFERROR(AVERAGEIFS(unit_details[Asking Rent],unit_details[First Listed],">="&($Q$2-7), unit_details[First Listed],"<="&$Q$2, unit_details[Beds],3, unit_details[Property Name],B66),"") | N69: =COUNTIFS(unit_details[Property Name], B66, unit_details[Beds], 3, unit_details[Leased Date], "") -> 0 | O69: =N69-(N69-K69+F69) -> 0 | P69: =IFERROR(AVERAGEIFS(unit_details[Asking Rent],unit_details[Property Name], B66, unit_details[Beds], 3, unit_details[Leased Date], ""),"") | Q69: =IFERROR(N69/SUMIFS(unit_mix_table['# Units],unit_mix_table[Beds],3,unit_mix_table[Property Name],B66),"")
B70: =IF(ISBLANK(OFFSET('Rent Comparison'!$A$1,2,21)),"",IF(OFFSET('Rent Comparison'!$A$1,2,21)=0,B71,OFFSET('Rent Comparison'!$A$1,2,21))) | C70: =IF(ISBLANK(B70),"",IFERROR(INDEX(Specials!B:J,MATCH(B70&" - Active",Specials!I:I,0),2),"")) | E70: Studio | F70: =COUNTIFS(unit_details[Leased Date], ">=" & ($Q$2 - 7), unit_details[Leased Date], "<" & $Q$2, unit_details[Beds], 0, unit_details[Property Name], B70) -> 0 | G70: =COUNTIFS(unit_details[Leased Date], ">=" & ($Q$2 - 7), unit_details[Leased Date], "<" & $Q$2, unit_details[Beds], 0, unit_details[Property Name], B70) - COUNTIFS(unit_details[Leased Date], ">=" & ($Q$2 - 14), unit_details[Leased Date], "<=" & ($Q$2 - 7), unit_details[Beds], 0, unit_details[Property Name], B70) -> 0 | H70: =IFERROR(AVERAGEIFS(unit_details[Asking Rent],unit_details[Leased Date], ">=" & ($Q$2 - 7), unit_details[Leased Date], "<" & $Q$2, unit_details[Beds], 0, unit_details[Property Name], B70),"") | I70: =IFERROR( AVERAGEIFS(unit_details[Asking Rent], unit_details[Leased Date], ">=" & ($Q$2 - 7), unit_details[Leased Date], "<" & $Q$2, unit_details[Beds], 0, unit_details[Property Name], B70) - AVERAGEIFS(unit_details[Asking Rent], unit_details[Leased Date], ">=" & ($Q$2 - 14), unit_details[Leased Date], "<=" & ($Q$2 - 7), unit_details[Beds], 0, unit_details[Property Name], B70), 0) -> 0 | J70: =IFERROR(I70/AVERAGEIFS(unit_details[Asking Rent], unit_details[Leased Date], ">=" & ($Q$2 - 14), unit_details[Leased Date], "<=" & ($Q$2 - 7), unit_details[Beds], 0, unit_details[Property Name], B70),0) -> 0 | K70: =COUNTIFS(unit_details[First Listed], ">=" & ($Q$2 - 7), unit_details[First Listed], "<" & $Q$2, unit_details[Beds], 0, unit_details[Property Name], B70) -> 0 | L70: =COUNTIFS( unit_details[First Listed], ">=" & ($Q$2 - 7), unit_details[First Listed], "<" & $Q$2, unit_details[Beds], 0, unit_details[Property Name], B70 ) - COUNTIFS( unit_details[First Listed], ">=" & ($Q$2 - 14), unit_details[First Listed], "<=" & ($Q$2 - 7), unit_details[Beds], 0, unit_details[Property Name], B70 ) -> 0 | M70: =IFERROR(AVERAGEIFS(unit_details[Asking Rent],unit_details[First Listed],">="&($Q$2-7), unit_details[First Listed],"<="&$Q$2, unit_details[Beds],0, unit_details[Property Name],B70),"") | N70: =COUNTIFS(unit_details[Property Name], B70, unit_details[Beds], 0, unit_details[Leased Date], "") -> 0 | O70: =N70-(N70-K70+F70) -> 0 | P70: =IFERROR(AVERAGEIFS(unit_details[Asking Rent],unit_details[Property Name], B70, unit_details[Beds], 0, unit_details[Leased Date], ""),"") | Q70: =IFERROR(N70/SUMIFS(unit_mix_table['# Units],unit_mix_table[Beds],0,unit_mix_table[Property Name],B70),"")
B71: 476 East 13th Street, Delta, CO 81416 | E71: 1 BR | F71: =COUNTIFS(unit_details[Leased Date], ">=" & ($Q$2 - 7), unit_details[Leased Date], "<" & $Q$2, unit_details[Beds], 1, unit_details[Property Name], B70) -> 0 | G71: =COUNTIFS(unit_details[Leased Date], ">=" & ($Q$2 - 7), unit_details[Leased Date], "<" & $Q$2, unit_details[Beds], 1, unit_details[Property Name], B70) - COUNTIFS(unit_details[Leased Date], ">=" & ($Q$2 - 14), unit_details[Leased Date], "<=" & ($Q$2 - 7), unit_details[Beds], 1, unit_details[Property Name], B70) -> 0 | H71: =IFERROR(AVERAGEIFS(unit_details[Asking Rent],unit_details[Leased Date], ">=" & ($Q$2 - 7), unit_details[Leased Date], "<" & $Q$2, unit_details[Beds], 1, unit_details[Property Name], B70),"") | I71: =IFERROR( AVERAGEIFS(unit_details[Asking Rent], unit_details[Leased Date], ">=" & ($Q$2 - 7), unit_details[Leased Date], "<" & $Q$2, unit_details[Beds], 1, unit_details[Property Name], B70) - AVERAGEIFS(unit_details[Asking Rent], unit_details[Leased Date], ">=" & ($Q$2 - 14), unit_details[Leased Date], "<=" & ($Q$2 - 7), unit_details[Beds], 1, unit_details[Property Name], B70), 0) -> 0 | J71: =IFERROR(I71/AVERAGEIFS(unit_details[Asking Rent], unit_details[Leased Date], ">=" & ($Q$2 - 14), unit_details[Leased Date], "<=" & ($Q$2 - 7), unit_details[Beds], 1, unit_details[Property Name], B70),0) -> 0 | K71: =COUNTIFS(unit_details[First Listed], ">=" & ($Q$2 - 7), unit_details[First Listed], "<" & $Q$2, unit_details[Beds], 1, unit_details[Property Name], B70) -> 0 | L71: =COUNTIFS( unit_details[First Listed], ">=" & ($Q$2 - 7), unit_details[First Listed], "<" & $Q$2, unit_details[Beds], 1, unit_details[Property Name], B70 ) - COUNTIFS( unit_details[First Listed], ">=" & ($Q$2 - 14), unit_details[First Listed], "<=" & ($Q$2 - 7), unit_details[Beds], 1, unit_details[Property Name], B70 ) -> 0 | M71: =IFERROR(AVERAGEIFS(unit_details[Asking Rent],unit_details[First Listed],">="&($Q$2-7), unit_details[First Listed],"<="&$Q$2, unit_details[Beds],1, unit_details[Property Name],B70),"") | N71: =COUNTIFS(unit_details[Property Name], B70, unit_details[Beds], 1, unit_details[Leased Date], "") -> 7 | O71: =N71-(N71-K71+F71) -> 0 | P71: =IFERROR(AVERAGEIFS(unit_details[Asking Rent],unit_details[Property Name], B70, unit_details[Beds], 1, unit_details[Leased Date], ""),"") -> 1028.5714 | Q71: =IFERROR(N71/SUMIFS(unit_mix_table['# Units],unit_mix_table[Beds],1,unit_mix_table[Property Name],B70),"") -> 2.3333333
E72: 2 BR | F72: =COUNTIFS(unit_details[Leased Date], ">=" & ($Q$2 - 7), unit_details[Leased Date], "<" & $Q$2, unit_details[Beds], 2, unit_details[Property Name], B70) -> 0 | G72: =COUNTIFS(unit_details[Leased Date], ">=" & ($Q$2 - 7), unit_details[Leased Date], "<" & $Q$2, unit_details[Beds], 2, unit_details[Property Name], B70) - COUNTIFS(unit_details[Leased Date], ">=" & ($Q$2 - 14), unit_details[Leased Date], "<=" & ($Q$2 - 7), unit_details[Beds], 2, unit_details[Property Name], B70) -> 0 | H72: =IFERROR(AVERAGEIFS(unit_details[Asking Rent],unit_details[Leased Date], ">=" & ($Q$2 - 7), unit_details[Leased Date], "<" & $Q$2, unit_details[Beds], 2, unit_details[Property Name], B70),"") | I72: =IFERROR( AVERAGEIFS(unit_details[Asking Rent], unit_details[Leased Date], ">=" & ($Q$2 - 7), unit_details[Leased Date], "<" & $Q$2, unit_details[Beds], 2, unit_details[Property Name], B70) - AVERAGEIFS(unit_details[Asking Rent], unit_details[Leased Date], ">=" & ($Q$2 - 14), unit_details[Leased Date], "<=" & ($Q$2 - 7), unit_details[Beds], 2, unit_details[Property Name], B70), 0) -> 0 | J72: =IFERROR(I72/AVERAGEIFS(unit_details[Asking Rent], unit_details[Leased Date], ">=" & ($Q$2 - 14), unit_details[Leased Date], "<=" & ($Q$2 - 7), unit_details[Beds], 2, unit_details[Property Name], B70),0) -> 0 | K72: =COUNTIFS(unit_details[First Listed], ">=" & ($Q$2 - 7), unit_details[First Listed], "<" & $Q$2, unit_details[Beds], 2, unit_details[Property Name], B70) -> 0 | L72: =COUNTIFS( unit_details[First Listed], ">=" & ($Q$2 - 7), unit_details[First Listed], "<" & $Q$2, unit_details[Beds], 2, unit_details[Property Name], B70 ) - COUNTIFS( unit_details[First Listed], ">=" & ($Q$2 - 14), unit_details[First Listed], "<=" & ($Q$2 - 7), unit_details[Beds], 2, unit_details[Property Name], B70 ) -> 0 | M72: =IFERROR(AVERAGEIFS(unit_details[Asking Rent],unit_details[First Listed],">="&($Q$2-7), unit_details[First Listed],"<="&$Q$2, unit_details[Beds],2, unit_details[Property Name],B70),"") | N72: =COUNTIFS(unit_details[Property Name], B70, unit_details[Beds], 2, unit_details[Leased Date], "") -> 9 | O72: =N72-(N72-K72+F72) -> 0 | P72: =IFERROR(AVERAGEIFS(unit_details[Asking Rent],unit_details[Property Name], B70, unit_details[Beds], 2, unit_details[Leased Date], ""),"") -> 1211.1111 | Q72: =IFERROR(N72/SUMIFS(unit_mix_table['# Units],unit_mix_table[Beds],2,unit_mix_table[Property Name],B70),"") -> 1.5
B73: https://areabest.net | E73: 3 BR | F73: =COUNTIFS(unit_details[Leased Date], ">=" & ($Q$2 - 7), unit_details[Leased Date], "<" & $Q$2, unit_details[Beds], 3, unit_details[Property Name], B70) -> 0 | G73: =COUNTIFS(unit_details[Leased Date], ">=" & ($Q$2 - 7), unit_details[Leased Date], "<" & $Q$2, unit_details[Beds], 3, unit_details[Property Name], B70) - COUNTIFS(unit_details[Leased Date], ">=" & ($Q$2 - 14), unit_details[Leased Date], "<=" & ($Q$2 - 7), unit_details[Beds], 3, unit_details[Property Name], B70) -> 0 | H73: =IFERROR(AVERAGEIFS(unit_details[Asking Rent],unit_details[Leased Date], ">=" & ($Q$2 - 7), unit_details[Leased Date], "<" & $Q$2, unit_details[Beds], 3, unit_details[Property Name], B70),"") | I73: =IFERROR( AVERAGEIFS(unit_details[Asking Rent], unit_details[Leased Date], ">=" & ($Q$2 - 7), unit_details[Leased Date], "<" & $Q$2, unit_details[Beds], 3, unit_details[Property Name], B70) - AVERAGEIFS(unit_details[Asking Rent], unit_details[Leased Date], ">=" & ($Q$2 - 14), unit_details[Leased Date], "<=" & ($Q$2 - 7), unit_details[Beds], 3, unit_details[Property Name], B70), 0) -> 0 | J73: =IFERROR(I73/AVERAGEIFS(unit_details[Asking Rent], unit_details[Leased Date], ">=" & ($Q$2 - 14), unit_details[Leased Date], "<=" & ($Q$2 - 7), unit_details[Beds], 3, unit_details[Property Name], B70),0) -> 0 | K73: =COUNTIFS(unit_details[First Listed], ">=" & ($Q$2 - 7), unit_details[First Listed], "<" & $Q$2, unit_details[Beds], 3, unit_details[Property Name], B70) -> 0 | L73: =COUNTIFS( unit_details[First Listed], ">=" & ($Q$2 - 7), unit_details[First Listed], "<" & $Q$2, unit_details[Beds], 3, unit_details[Property Name], B70 ) - COUNTIFS( unit_details[First Listed], ">=" & ($Q$2 - 14), unit_details[First Listed], "<=" & ($Q$2 - 7), unit_details[Beds], 3, unit_details[Property Name], B70 ) -> 0 | M73: =IFERROR(AVERAGEIFS(unit_details[Asking Rent],unit_details[First Listed],">="&($Q$2-7), unit_details[First Listed],"<="&$Q$2, unit_details[Beds],3, unit_details[Property Name],B70),"") | N73: =COUNTIFS(unit_details[Property Name], B70, unit_details[Beds], 3, unit_details[Leased Date], "") -> 0 | O73: =N73-(N73-K73+F73) -> 0 | P73: =IFERROR(AVERAGEIFS(unit_details[Asking Rent],unit_details[Property Name], B70, unit_details[Beds], 3, unit_details[Leased Date], ""),"") | Q73: =IFERROR(N73/SUMIFS(unit_mix_table['# Units],unit_mix_table[Beds],3,unit_mix_table[Property Name],B70),"")
B74: =IF(ISBLANK(OFFSET('Rent Comparison'!$A$1,2,22)),"",IF(OFFSET('Rent Comparison'!$A$1,2,22)=0,B75,OFFSET('Rent Comparison'!$A$1,2,22))) | C74: =IF(ISBLANK(B74),"",IFERROR(INDEX(Specials!B:J,MATCH(B74&" - Active",Specials!I:I,0),2),"")) | E74: Studio | F74: =COUNTIFS(unit_details[Leased Date], ">=" & ($Q$2 - 7), unit_details[Leased Date], "<" & $Q$2, unit_details[Beds], 0, unit_details[Property Name], B74) -> 0 | G74: =COUNTIFS(unit_details[Leased Date], ">=" & ($Q$2 - 7), unit_details[Leased Date], "<" & $Q$2, unit_details[Beds], 0, unit_details[Property Name], B74) - COUNTIFS(unit_details[Leased Date], ">=" & ($Q$2 - 14), unit_details[Leased Date], "<=" & ($Q$2 - 7), unit_details[Beds], 0, unit_details[Property Name], B74) -> 0 | H74: =IFERROR(AVERAGEIFS(unit_details[Asking Rent],unit_details[Leased Date], ">=" & ($Q$2 - 7), unit_details[Leased Date], "<" & $Q$2, unit_details[Beds], 0, unit_details[Property Name], B74),"") | I74: =IFERROR( AVERAGEIFS(unit_details[Asking Rent], unit_details[Leased Date], ">=" & ($Q$2 - 7), unit_details[Leased Date], "<" & $Q$2, unit_details[Beds], 0, unit_details[Property Name], B74) - AVERAGEIFS(unit_details[Asking Rent], unit_details[Leased Date], ">=" & ($Q$2 - 14), unit_details[Leased Date], "<=" & ($Q$2 - 7), unit_details[Beds], 0, unit_details[Property Name], B74), 0) -> 0 | J74: =IFERROR(I74/AVERAGEIFS(unit_details[Asking Rent], unit_details[Leased Date], ">=" & ($Q$2 - 14), unit_details[Leased Date], "<=" & ($Q$2 - 7), unit_details[Beds], 0, unit_details[Property Name], B74),0) -> 0 | K74: =COUNTIFS(unit_details[First Listed], ">=" & ($Q$2 - 7), unit_details[First Listed], "<" & $Q$2, unit_details[Beds], 0, unit_details[Property Name], B74) -> 0 | L74: =COUNTIFS( unit_details[First Listed], ">=" & ($Q$2 - 7), unit_details[First Listed], "<" & $Q$2, unit_details[Beds], 0, unit_details[Property Name], B74 ) - COUNTIFS( unit_details[First Listed], ">=" & ($Q$2 - 14), unit_details[First Listed], "<=" & ($Q$2 - 7), unit_details[Beds], 0, unit_details[Property Name], B74 ) -> 0 | M74: =IFERROR(AVERAGEIFS(unit_details[Asking Rent],unit_details[First Listed],">="&($Q$2-7), unit_details[First Listed],"<="&$Q$2, unit_details[Beds],0, unit_details[Property Name],B74),"") | N74: =COUNTIFS(unit_details[Property Name], B74, unit_details[Beds], 0, unit_details[Leased Date], "") -> 0 | O74: =N74-(N74-K74+F74) -> 0 | P74: =IFERROR(AVERAGEIFS(unit_details[Asking Rent],unit_details[Property Name], B74, unit_details[Beds], 0, unit_details[Leased Date], ""),"") | Q74: =IFERROR(N74/SUMIFS(unit_mix_table['# Units],unit_mix_table[Beds],0,unit_mix_table[Property Name],B74),"")
B75: 525 Hastings Street, Delta, CO 81416 | E75: 1 BR | F75: =COUNTIFS(unit_details[Leased Date], ">=" & ($Q$2 - 7), unit_details[Leased Date], "<" & $Q$2, unit_details[Beds], 1, unit_details[Property Name], B74) -> 0 | G75: =COUNTIFS(unit_details[Leased Date], ">=" & ($Q$2 - 7), unit_details[Leased Date], "<" & $Q$2, unit_details[Beds], 1, unit_details[Property Name], B74) - COUNTIFS(unit_details[Leased Date], ">=" & ($Q$2 - 14), unit_details[Leased Date], "<=" & ($Q$2 - 7), unit_details[Beds], 1, unit_details[Property Name], B74) -> 0 | H75: =IFERROR(AVERAGEIFS(unit_details[Asking Rent],unit_details[Leased Date], ">=" & ($Q$2 - 7), unit_details[Leased Date], "<" & $Q$2, unit_details[Beds], 1, unit_details[Property Name], B74),"") | I75: =IFERROR( AVERAGEIFS(unit_details[Asking Rent], unit_details[Leased Date], ">=" & ($Q$2 - 7), unit_details[Leased Date], "<" & $Q$2, unit_details[Beds], 1, unit_details[Property Name], B74) - AVERAGEIFS(unit_details[Asking Rent], unit_details[Leased Date], ">=" & ($Q$2 - 14), unit_details[Leased Date], "<=" & ($Q$2 - 7), unit_details[Beds], 1, unit_details[Property Name], B74), 0) -> 0 | J75: =IFERROR(I75/AVERAGEIFS(unit_details[Asking Rent], unit_details[Leased Date], ">=" & ($Q$2 - 14), unit_details[Leased Date], "<=" & ($Q$2 - 7), unit_details[Beds], 1, unit_details[Property Name], B74),0) -> 0 | K75: =COUNTIFS(unit_details[First Listed], ">=" & ($Q$2 - 7), unit_details[First Listed], "<" & $Q$2, unit_details[Beds], 1, unit_details[Property Name], B74) -> 0 | L75: =COUNTIFS( unit_details[First Listed], ">=" & ($Q$2 - 7), unit_details[First Listed], "<" & $Q$2, unit_details[Beds], 1, unit_details[Property Name], B74 ) - COUNTIFS( unit_details[First Listed], ">=" & ($Q$2 - 14), unit_details[First Listed], "<=" & ($Q$2 - 7), unit_details[Beds], 1, unit_details[Property Name], B74 ) -> 0 | M75: =IFERROR(AVERAGEIFS(unit_details[Asking Rent],unit_details[First Listed],">="&($Q$2-7), unit_details[First Listed],"<="&$Q$2, unit_details[Beds],1, unit_details[Property Name],B74),"") | N75: =COUNTIFS(unit_details[Property Name], B74, unit_details[Beds], 1, unit_details[Leased Date], "") -> 7 | O75: =N75-(N75-K75+F75) -> 0 | P75: =IFERROR(AVERAGEIFS(unit_details[Asking Rent],unit_details[Property Name], B74, unit_details[Beds], 1, unit_details[Leased Date], ""),"") -> 1028.5714 | Q75: =IFERROR(N75/SUMIFS(unit_mix_table['# Units],unit_mix_table[Beds],1,unit_mix_table[Property Name],B74),"") -> 2.3333333
E76: 2 BR | F76: =COUNTIFS(unit_details[Leased Date], ">=" & ($Q$2 - 7), unit_details[Leased Date], "<" & $Q$2, unit_details[Beds], 2, unit_details[Property Name], B74) -> 0 | G76: =COUNTIFS(unit_details[Leased Date], ">=" & ($Q$2 - 7), unit_details[Leased Date], "<" & $Q$2, unit_details[Beds], 2, unit_details[Property Name], B74) - COUNTIFS(unit_details[Leased Date], ">=" & ($Q$2 - 14), unit_details[Leased Date], "<=" & ($Q$2 - 7), unit_details[Beds], 2, unit_details[Property Name], B74) -> 0 | H76: =IFERROR(AVERAGEIFS(unit_details[Asking Rent],unit_details[Leased Date], ">=" & ($Q$2 - 7), unit_details[Leased Date], "<" & $Q$2, unit_details[Beds], 2, unit_details[Property Name], B74),"") | I76: =IFERROR( AVERAGEIFS(unit_details[Asking Rent], unit_details[Leased Date], ">=" & ($Q$2 - 7), unit_details[Leased Date], "<" & $Q$2, unit_details[Beds], 2, unit_details[Property Name], B74) - AVERAGEIFS(unit_details[Asking Rent], unit_details[Leased Date], ">=" & ($Q$2 - 14), unit_details[Leased Date], "<=" & ($Q$2 - 7), unit_details[Beds], 2, unit_details[Property Name], B74), 0) -> 0 | J76: =IFERROR(I76/AVERAGEIFS(unit_details[Asking Rent], unit_details[Leased Date], ">=" & ($Q$2 - 14), unit_details[Leased Date], "<=" & ($Q$2 - 7), unit_details[Beds], 2, unit_details[Property Name], B74),0) -> 0 | K76: =COUNTIFS(unit_details[First Listed], ">=" & ($Q$2 - 7), unit_details[First Listed], "<" & $Q$2, unit_details[Beds], 2, unit_details[Property Name], B74) -> 0 | L76: =COUNTIFS( unit_details[First Listed], ">=" & ($Q$2 - 7), unit_details[First Listed], "<" & $Q$2, unit_details[Beds], 2, unit_details[Property Name], B74 ) - COUNTIFS( unit_details[First Listed], ">=" & ($Q$2 - 14), unit_details[First Listed], "<=" & ($Q$2 - 7), unit_details[Beds], 2, unit_details[Property Name], B74 ) -> 0 | M76: =IFERROR(AVERAGEIFS(unit_details[Asking Rent],unit_details[First Listed],">="&($Q$2-7), unit_details[First Listed],"<="&$Q$2, unit_details[Beds],2, unit_details[Property Name],B74),"") | N76: =COUNTIFS(unit_details[Property Name], B74, unit_details[Beds], 2, unit_details[Leased Date], "") -> 9 | O76: =N76-(N76-K76+F76) -> 0 | P76: =IFERROR(AVERAGEIFS(unit_details[Asking Rent],unit_details[Property Name], B74, unit_details[Beds], 2, unit_details[Leased Date], ""),"") -> 1211.1111 | Q76: =IFERROR(N76/SUMIFS(unit_mix_table['# Units],unit_mix_table[Beds],2,unit_mix_table[Property Name],B74),"") -> 1.5
E77: 3 BR | F77: =COUNTIFS(unit_details[Leased Date], ">=" & ($Q$2 - 7), unit_details[Leased Date], "<" & $Q$2, unit_details[Beds], 3, unit_details[Property Name], B74) -> 0 | G77: =COUNTIFS(unit_details[Leased Date], ">=" & ($Q$2 - 7), unit_details[Leased Date], "<" & $Q$2, unit_details[Beds], 3, unit_details[Property Name], B74) - COUNTIFS(unit_details[Leased Date], ">=" & ($Q$2 - 14), unit_details[Leased Date], "<=" & ($Q$2 - 7), unit_details[Beds], 3, unit_details[Property Name], B74) -> 0 | H77: =IFERROR(AVERAGEIFS(unit_details[Asking Rent],unit_details[Leased Date], ">=" & ($Q$2 - 7), unit_details[Leased Date], "<" & $Q$2, unit_details[Beds], 3, unit_details[Property Name], B74),"") | I77: =IFERROR( AVERAGEIFS(unit_details[Asking Rent], unit_details[Leased Date], ">=" & ($Q$2 - 7), unit_details[Leased Date], "<" & $Q$2, unit_details[Beds], 3, unit_details[Property Name], B74) - AVERAGEIFS(unit_details[Asking Rent], unit_details[Leased Date], ">=" & ($Q$2 - 14), unit_details[Leased Date], "<=" & ($Q$2 - 7), unit_details[Beds], 3, unit_details[Property Name], B74), 0) -> 0 | J77: =IFERROR(I77/AVERAGEIFS(unit_details[Asking Rent], unit_details[Leased Date], ">=" & ($Q$2 - 14), unit_details[Leased Date], "<=" & ($Q$2 - 7), unit_details[Beds], 3, unit_details[Property Name], B74),0) -> 0 | K77: =COUNTIFS(unit_details[First Listed], ">=" & ($Q$2 - 7), unit_details[First Listed], "<" & $Q$2, unit_details[Beds], 3, unit_details[Property Name], B74) -> 0 | L77: =COUNTIFS( unit_details[First Listed], ">=" & ($Q$2 - 7), unit_details[First Listed], "<" & $Q$2, unit_details[Beds], 3, unit_details[Property Name], B74 ) - COUNTIFS( unit_details[First Listed], ">=" & ($Q$2 - 14), unit_details[First Listed], "<=" & ($Q$2 - 7), unit_details[Beds], 3, unit_details[Property Name], B74 ) -> 0 | M77: =IFERROR(AVERAGEIFS(unit_details[Asking Rent],unit_details[First Listed],">="&($Q$2-7), unit_details[First Listed],"<="&$Q$2, unit_details[Beds],3, unit_details[Property Name],B74),"") | N77: =COUNTIFS(unit_details[Property Name], B74, unit_details[Beds], 3, unit_details[Leased Date], "") -> 0 | O77: =N77-(N77-K77+F77) -> 0 | P77: =IFERROR(AVERAGEIFS(unit_details[Asking Rent],unit_details[Property Name], B74, unit_details[Beds], 3, unit_details[Leased Date], ""),"") | Q77: =IFERROR(N77/SUMIFS(unit_mix_table['# Units],unit_mix_table[Beds],3,unit_mix_table[Property Name],B74),"")
B78: =IF(ISBLANK(OFFSET('Rent Comparison'!$A$1,2,23)),"",IF(OFFSET('Rent Comparison'!$A$1,2,23)=0,B79,OFFSET('Rent Comparison'!$A$1,2,23))) | C78: =IF(ISBLANK(B78),"",IFERROR(INDEX(Specials!B:J,MATCH(B78&" - Active",Specials!I:I,0),2),"")) | E78: Studio | F78: =COUNTIFS(unit_details[Leased Date], ">=" & ($Q$2 - 7), unit_details[Leased Date], "<" & $Q$2, unit_details[Beds], 0, unit_details[Property Name], B78) -> 0 | G78: =COUNTIFS(unit_details[Leased Date], ">=" & ($Q$2 - 7), unit_details[Leased Date], "<" & $Q$2, unit_details[Beds], 0, unit_details[Property Name], B78) - COUNTIFS(unit_details[Leased Date], ">=" & ($Q$2 - 14), unit_details[Leased Date], "<=" & ($Q$2 - 7), unit_details[Beds], 0, unit_details[Property Name], B78) -> 0 | H78: =IFERROR(AVERAGEIFS(unit_details[Asking Rent],unit_details[Leased Date], ">=" & ($Q$2 - 7), unit_details[Leased Date], "<" & $Q$2, unit_details[Beds], 0, unit_details[Property Name], B78),"") | I78: =IFERROR( AVERAGEIFS(unit_details[Asking Rent], unit_details[Leased Date], ">=" & ($Q$2 - 7), unit_details[Leased Date], "<" & $Q$2, unit_details[Beds], 0, unit_details[Property Name], B78) - AVERAGEIFS(unit_details[Asking Rent], unit_details[Leased Date], ">=" & ($Q$2 - 14), unit_details[Leased Date], "<=" & ($Q$2 - 7), unit_details[Beds], 0, unit_details[Property Name], B78), 0) -> 0 | J78: =IFERROR(I78/AVERAGEIFS(unit_details[Asking Rent], unit_details[Leased Date], ">=" & ($Q$2 - 14), unit_details[Leased Date], "<=" & ($Q$2 - 7), unit_details[Beds], 0, unit_details[Property Name], B78),0) -> 0 | K78: =COUNTIFS(unit_details[First Listed], ">=" & ($Q$2 - 7), unit_details[First Listed], "<" & $Q$2, unit_details[Beds], 0, unit_details[Property Name], B78) -> 0 | L78: =COUNTIFS( unit_details[First Listed], ">=" & ($Q$2 - 7), unit_details[First Listed], "<" & $Q$2, unit_details[Beds], 0, unit_details[Property Name], B78 ) - COUNTIFS( unit_details[First Listed], ">=" & ($Q$2 - 14), unit_details[First Listed], "<=" & ($Q$2 - 7), unit_details[Beds], 0, unit_details[Property Name], B78 ) -> 0 | M78: =IFERROR(AVERAGEIFS(unit_details[Asking Rent],unit_details[First Listed],">="&($Q$2-7), unit_details[First Listed],"<="&$Q$2, unit_details[Beds],0, unit_details[Property Name],B78),"") | N78: =COUNTIFS(unit_details[Property Name], B78, unit_details[Beds], 0, unit_details[Leased Date], "") -> 0 | O78: =N78-(N78-K78+F78) -> 0 | P78: =IFERROR(AVERAGEIFS(unit_details[Asking Rent],unit_details[Property Name], B78, unit_details[Beds], 0, unit_details[Leased Date], ""),"") | Q78: =IFERROR(N78/SUMIFS(unit_mix_table['# Units],unit_mix_table[Beds],0,unit_mix_table[Property Name],B78),"")
B79: 845 Palmer Street, Delta, CO 81416 | E79: 1 BR | F79: =COUNTIFS(unit_details[Leased Date], ">=" & ($Q$2 - 7), unit_details[Leased Date], "<" & $Q$2, unit_details[Beds], 1, unit_details[Property Name], B78) -> 0 | G79: =COUNTIFS(unit_details[Leased Date], ">=" & ($Q$2 - 7), unit_details[Leased Date], "<" & $Q$2, unit_details[Beds], 1, unit_details[Property Name], B78) - COUNTIFS(unit_details[Leased Date], ">=" & ($Q$2 - 14), unit_details[Leased Date], "<=" & ($Q$2 - 7), unit_details[Beds], 1, unit_details[Property Name], B78) -> 0 | H79: =IFERROR(AVERAGEIFS(unit_details[Asking Rent],unit_details[Leased Date], ">=" & ($Q$2 - 7), unit_details[Leased Date], "<" & $Q$2, unit_details[Beds], 1, unit_details[Property Name], B78),"") | I79: =IFERROR( AVERAGEIFS(unit_details[Asking Rent], unit_details[Leased Date], ">=" & ($Q$2 - 7), unit_details[Leased Date], "<" & $Q$2, unit_details[Beds], 1, unit_details[Property Name], B78) - AVERAGEIFS(unit_details[Asking Rent], unit_details[Leased Date], ">=" & ($Q$2 - 14), unit_details[Leased Date], "<=" & ($Q$2 - 7), unit_details[Beds], 1, unit_details[Property Name], B78), 0) -> 0 | J79: =IFERROR(I79/AVERAGEIFS(unit_details[Asking Rent], unit_details[Leased Date], ">=" & ($Q$2 - 14), unit_details[Leased Date], "<=" & ($Q$2 - 7), unit_details[Beds], 1, unit_details[Property Name], B78),0) -> 0 | K79: =COUNTIFS(unit_details[First Listed], ">=" & ($Q$2 - 7), unit_details[First Listed], "<" & $Q$2, unit_details[Beds], 1, unit_details[Property Name], B78) -> 0 | L79: =COUNTIFS( unit_details[First Listed], ">=" & ($Q$2 - 7), unit_details[First Listed], "<" & $Q$2, unit_details[Beds], 1, unit_details[Property Name], B78 ) - COUNTIFS( unit_details[First Listed], ">=" & ($Q$2 - 14), unit_details[First Listed], "<=" & ($Q$2 - 7), unit_details[Beds], 1, unit_details[Property Name], B78 ) -> 0 | M79: =IFERROR(AVERAGEIFS(unit_details[Asking Rent],unit_details[First Listed],">="&($Q$2-7), unit_details[First Listed],"<="&$Q$2, unit_details[Beds],1, unit_details[Property Name],B78),"") | N79: =COUNTIFS(unit_details[Property Name], B78, unit_details[Beds], 1, unit_details[Leased Date], "") -> 7 | O79: =N79-(N79-K79+F79) -> 0 | P79: =IFERROR(AVERAGEIFS(unit_details[Asking Rent],unit_details[Property Name], B78, unit_details[Beds], 1, unit_details[Leased Date], ""),"") -> 1028.5714 | Q79: =IFERROR(N79/SUMIFS(unit_mix_table['# Units],unit_mix_table[Beds],1,unit_mix_table[Property Name],B78),"") -> 2.3333333
E80: 2 BR | F80: =COUNTIFS(unit_details[Leased Date], ">=" & ($Q$2 - 7), unit_details[Leased Date], "<" & $Q$2, unit_details[Beds], 2, unit_details[Property Name], B78) -> 0 | G80: =COUNTIFS(unit_details[Leased Date], ">=" & ($Q$2 - 7), unit_details[Leased Date], "<" & $Q$2, unit_details[Beds], 2, unit_details[Property Name], B78) - COUNTIFS(unit_details[Leased Date], ">=" & ($Q$2 - 14), unit_details[Leased Date], "<=" & ($Q$2 - 7), unit_details[Beds], 2, unit_details[Property Name], B78) -> 0 | H80: =IFERROR(AVERAGEIFS(unit_details[Asking Rent],unit_details[Leased Date], ">=" & ($Q$2 - 7), unit_details[Leased Date], "<" & $Q$2, unit_details[Beds], 2, unit_details[Property Name], B78),"") | I80: =IFERROR( AVERAGEIFS(unit_details[Asking Rent], unit_details[Leased Date], ">=" & ($Q$2 - 7), unit_details[Leased Date], "<" & $Q$2, unit_details[Beds], 2, unit_details[Property Name], B78) - AVERAGEIFS(unit_details[Asking Rent], unit_details[Leased Date], ">=" & ($Q$2 - 14), unit_details[Leased Date], "<=" & ($Q$2 - 7), unit_details[Beds], 2, unit_details[Property Name], B78), 0) -> 0 | J80: =IFERROR(I80/AVERAGEIFS(unit_details[Asking Rent], unit_details[Leased Date], ">=" & ($Q$2 - 14), unit_details[Leased Date], "<=" & ($Q$2 - 7), unit_details[Beds], 2, unit_details[Property Name], B78),0) -> 0 | K80: =COUNTIFS(unit_details[First Listed], ">=" & ($Q$2 - 7), unit_details[First Listed], "<" & $Q$2, unit_details[Beds], 2, unit_details[Property Name], B78) -> 0 | L80: =COUNTIFS( unit_details[First Listed], ">=" & ($Q$2 - 7), unit_details[First Listed], "<" & $Q$2, unit_details[Beds], 2, unit_details[Property Name], B78 ) - COUNTIFS( unit_details[First Listed], ">=" & ($Q$2 - 14), unit_details[First Listed], "<=" & ($Q$2 - 7), unit_details[Beds], 2, unit_details[Property Name], B78 ) -> 0 | M80: =IFERROR(AVERAGEIFS(unit_details[Asking Rent],unit_details[First Listed],">="&($Q$2-7), unit_details[First Listed],"<="&$Q$2, unit_details[Beds],2, unit_details[Property Name],B78),"") | N80: =COUNTIFS(unit_details[Property Name], B78, unit_details[Beds], 2, unit_details[Leased Date], "") -> 9 | O80: =N80-(N80-K80+F80) -> 0 | P80: =IFERROR(AVERAGEIFS(unit_details[Asking Rent],unit_details[Property Name], B78, unit_details[Beds], 2, unit_details[Leased Date], ""),"") -> 1211.1111 | Q80: =IFERROR(N80/SUMIFS(unit_mix_table['# Units],unit_mix_table[Beds],2,unit_mix_table[Property Name],B78),"") -> 1.5
E81: 3 BR | F81: =COUNTIFS(unit_details[Leased Date], ">=" & ($Q$2 - 7), unit_details[Leased Date], "<" & $Q$2, unit_details[Beds], 3, unit_details[Property Name], B78) -> 0 | G81: =COUNTIFS(unit_details[Leased Date], ">=" & ($Q$2 - 7), unit_details[Leased Date], "<" & $Q$2, unit_details[Beds], 3, unit_details[Property Name], B78) - COUNTIFS(unit_details[Leased Date], ">=" & ($Q$2 - 14), unit_details[Leased Date], "<=" & ($Q$2 - 7), unit_details[Beds], 3, unit_details[Property Name], B78) -> 0 | H81: =IFERROR(AVERAGEIFS(unit_details[Asking Rent],unit_details[Leased Date], ">=" & ($Q$2 - 7), unit_details[Leased Date], "<" & $Q$2, unit_details[Beds], 3, unit_details[Property Name], B78),"") | I81: =IFERROR( AVERAGEIFS(unit_details[Asking Rent], unit_details[Leased Date], ">=" & ($Q$2 - 7), unit_details[Leased Date], "<" & $Q$2, unit_details[Beds], 3, unit_details[Property Name], B78) - AVERAGEIFS(unit_details[Asking Rent], unit_details[Leased Date], ">=" & ($Q$2 - 14), unit_details[Leased Date], "<=" & ($Q$2 - 7), unit_details[Beds], 3, unit_details[Property Name], B78), 0) -> 0 | J81: =IFERROR(I81/AVERAGEIFS(unit_details[Asking Rent], unit_details[Leased Date], ">=" & ($Q$2 - 14), unit_details[Leased Date], "<=" & ($Q$2 - 7), unit_details[Beds], 3, unit_details[Property Name], B78),0) -> 0 | K81: =COUNTIFS(unit_details[First Listed], ">=" & ($Q$2 - 7), unit_details[First Listed], "<" & $Q$2, unit_details[Beds], 3, unit_details[Property Name], B78) -> 0 | L81: =COUNTIFS( unit_details[First Listed], ">=" & ($Q$2 - 7), unit_details[First Listed], "<" & $Q$2, unit_details[Beds], 3, unit_details[Property Name], B78 ) - COUNTIFS( unit_details[First Listed], ">=" & ($Q$2 - 14), unit_details[First Listed], "<=" & ($Q$2 - 7), unit_details[Beds], 3, unit_details[Property Name], B78 ) -> 0 | M81: =IFERROR(AVERAGEIFS(unit_details[Asking Rent],unit_details[First Listed],">="&($Q$2-7), unit_details[First Listed],"<="&$Q$2, unit_details[Beds],3, unit_details[Property Name],B78),"") | N81: =COUNTIFS(unit_details[Property Name], B78, unit_details[Beds], 3, unit_details[Leased Date], "") -> 0 | O81: =N81-(N81-K81+F81) -> 0 | P81: =IFERROR(AVERAGEIFS(unit_details[Asking Rent],unit_details[Property Name], B78, unit_details[Beds], 3, unit_details[Leased Date], ""),"") | Q81: =IFERROR(N81/SUMIFS(unit_mix_table['# Units],unit_mix_table[Beds],3,unit_mix_table[Property Name],B78),"")
B82: =IF(ISBLANK(OFFSET('Rent Comparison'!$A$1,2,24)),"",IF(OFFSET('Rent Comparison'!$A$1,2,24)=0,B83,OFFSET('Rent Comparison'!$A$1,2,24))) | C82: =IF(ISBLANK(B82),"",IFERROR(INDEX(Specials!B:J,MATCH(B82&" - Active",Specials!I:I,0),2),"")) | E82: Studio | F82: =COUNTIFS(unit_details[Leased Date], ">=" & ($Q$2 - 7), unit_details[Leased Date], "<" & $Q$2, unit_details[Beds], 0, unit_details[Property Name], B82) -> 0 | G82: =COUNTIFS(unit_details[Leased Date], ">=" & ($Q$2 - 7), unit_details[Leased Date], "<" & $Q$2, unit_details[Beds], 0, unit_details[Property Name], B82) - COUNTIFS(unit_details[Leased Date], ">=" & ($Q$2 - 14), unit_details[Leased Date], "<=" & ($Q$2 - 7), unit_details[Beds], 0, unit_details[Property Name], B82) -> 0 | H82: =IFERROR(AVERAGEIFS(unit_details[Asking Rent],unit_details[Leased Date], ">=" & ($Q$2 - 7), unit_details[Leased Date], "<" & $Q$2, unit_details[Beds], 0, unit_details[Property Name], B82),"") | I82: =IFERROR( AVERAGEIFS(unit_details[Asking Rent], unit_details[Leased Date], ">=" & ($Q$2 - 7), unit_details[Leased Date], "<" & $Q$2, unit_details[Beds], 0, unit_details[Property Name], B82) - AVERAGEIFS(unit_details[Asking Rent], unit_details[Leased Date], ">=" & ($Q$2 - 14), unit_details[Leased Date], "<=" & ($Q$2 - 7), unit_details[Beds], 0, unit_details[Property Name], B82), 0) -> 0 | J82: =IFERROR(I82/AVERAGEIFS(unit_details[Asking Rent], unit_details[Leased Date], ">=" & ($Q$2 - 14), unit_details[Leased Date], "<=" & ($Q$2 - 7), unit_details[Beds], 0, unit_details[Property Name], B82),0) -> 0 | K82: =COUNTIFS(unit_details[First Listed], ">=" & ($Q$2 - 7), unit_details[First Listed], "<" & $Q$2, unit_details[Beds], 0, unit_details[Property Name], B82) -> 0 | L82: =COUNTIFS( unit_details[First Listed], ">=" & ($Q$2 - 7), unit_details[First Listed], "<" & $Q$2, unit_details[Beds], 0, unit_details[Property Name], B82 ) - COUNTIFS( unit_details[First Listed], ">=" & ($Q$2 - 14), unit_details[First Listed], "<=" & ($Q$2 - 7), unit_details[Beds], 0, unit_details[Property Name], B82 ) -> 0 | M82: =IFERROR(AVERAGEIFS(unit_details[Asking Rent],unit_details[First Listed],">="&($Q$2-7), unit_details[First Listed],"<="&$Q$2, unit_details[Beds],0, unit_details[Property Name],B82),"") | N82: =COUNTIFS(unit_details[Property Name], B82, unit_details[Beds], 0, unit_details[Leased Date], "") -> 0 | O82: =N82-(N82-K82+F82) -> 0 | P82: =IFERROR(AVERAGEIFS(unit_details[Asking Rent],unit_details[Property Name], B82, unit_details[Beds], 0, unit_details[Leased Date], ""),"") | Q82: =IFERROR(N82/SUMIFS(unit_mix_table['# Units],unit_mix_table[Beds],0,unit_mix_table[Property Name],B82),"")
B83: 340 Main Street, Delta, CO 81416 | E83: 1 BR | F83: =COUNTIFS(unit_details[Leased Date], ">=" & ($Q$2 - 7), unit_details[Leased Date], "<" & $Q$2, unit_details[Beds], 1, unit_details[Property Name], B82) -> 0 | G83: =COUNTIFS(unit_details[Leased Date], ">=" & ($Q$2 - 7), unit_details[Leased Date], "<" & $Q$2, unit_details[Beds], 1, unit_details[Property Name], B82) - COUNTIFS(unit_details[Leased Date], ">=" & ($Q$2 - 14), unit_details[Leased Date], "<=" & ($Q$2 - 7), unit_details[Beds], 1, unit_details[Property Name], B82) -> 0 | H83: =IFERROR(AVERAGEIFS(unit_details[Asking Rent],unit_details[Leased Date], ">=" & ($Q$2 - 7), unit_details[Leased Date], "<" & $Q$2, unit_details[Beds], 1, unit_details[Property Name], B82),"") | I83: =IFERROR( AVERAGEIFS(unit_details[Asking Rent], unit_details[Leased Date], ">=" & ($Q$2 - 7), unit_details[Leased Date], "<" & $Q$2, unit_details[Beds], 1, unit_details[Property Name], B82) - AVERAGEIFS(unit_details[Asking Rent], unit_details[Leased Date], ">=" & ($Q$2 - 14), unit_details[Leased Date], "<=" & ($Q$2 - 7), unit_details[Beds], 1, unit_details[Property Name], B82), 0) -> 0 | J83: =IFERROR(I83/AVERAGEIFS(unit_details[Asking Rent], unit_details[Leased Date], ">=" & ($Q$2 - 14), unit_details[Leased Date], "<=" & ($Q$2 - 7), unit_details[Beds], 1, unit_details[Property Name], B82),0) -> 0 | K83: =COUNTIFS(unit_details[First Listed], ">=" & ($Q$2 - 7), unit_details[First Listed], "<" & $Q$2, unit_details[Beds], 1, unit_details[Property Name], B82) -> 0 | L83: =COUNTIFS( unit_details[First Listed], ">=" & ($Q$2 - 7), unit_details[First Listed], "<" & $Q$2, unit_details[Beds], 1, unit_details[Property Name], B82 ) - COUNTIFS( unit_details[First Listed], ">=" & ($Q$2 - 14), unit_details[First Listed], "<=" & ($Q$2 - 7), unit_details[Beds], 1, unit_details[Property Name], B82 ) -> 0 | M83: =IFERROR(AVERAGEIFS(unit_details[Asking Rent],unit_details[First Listed],">="&($Q$2-7), unit_details[First Listed],"<="&$Q$2, unit_details[Beds],1, unit_details[Property Name],B82),"") | N83: =COUNTIFS(unit_details[Property Name], B82, unit_details[Beds], 1, unit_details[Leased Date], "") -> 7 | O83: =N83-(N83-K83+F83) -> 0 | P83: =IFERROR(AVERAGEIFS(unit_details[Asking Rent],unit_details[Property Name], B82, unit_details[Beds], 1, unit_details[Leased Date], ""),"") -> 1028.5714 | Q83: =IFERROR(N83/SUMIFS(unit_mix_table['# Units],unit_mix_table[Beds],1,unit_mix_table[Property Name],B82),"") -> 2.3333333
E84: 2 BR | F84: =COUNTIFS(unit_details[Leased Date], ">=" & ($Q$2 - 7), unit_details[Leased Date], "<" & $Q$2, unit_details[Beds], 2, unit_details[Property Name], B82) -> 0 | G84: =COUNTIFS(unit_details[Leased Date], ">=" & ($Q$2 - 7), unit_details[Leased Date], "<" & $Q$2, unit_details[Beds], 2, unit_details[Property Name], B82) - COUNTIFS(unit_details[Leased Date], ">=" & ($Q$2 - 14), unit_details[Leased Date], "<=" & ($Q$2 - 7), unit_details[Beds], 2, unit_details[Property Name], B82) -> 0 | H84: =IFERROR(AVERAGEIFS(unit_details[Asking Rent],unit_details[Leased Date], ">=" & ($Q$2 - 7), unit_details[Leased Date], "<" & $Q$2, unit_details[Beds], 2, unit_details[Property Name], B82),"") | I84: =IFERROR( AVERAGEIFS(unit_details[Asking Rent], unit_details[Leased Date], ">=" & ($Q$2 - 7), unit_details[Leased Date], "<" & $Q$2, unit_details[Beds], 2, unit_details[Property Name], B82) - AVERAGEIFS(unit_details[Asking Rent], unit_details[Leased Date], ">=" & ($Q$2 - 14), unit_details[Leased Date], "<=" & ($Q$2 - 7), unit_details[Beds], 2, unit_details[Property Name], B82), 0) -> 0 | J84: =IFERROR(I84/AVERAGEIFS(unit_details[Asking Rent], unit_details[Leased Date], ">=" & ($Q$2 - 14), unit_details[Leased Date], "<=" & ($Q$2 - 7), unit_details[Beds], 2, unit_details[Property Name], B82),0) -> 0 | K84: =COUNTIFS(unit_details[First Listed], ">=" & ($Q$2 - 7), unit_details[First Listed], "<" & $Q$2, unit_details[Beds], 2, unit_details[Property Name], B82) -> 0 | L84: =COUNTIFS( unit_details[First Listed], ">=" & ($Q$2 - 7), unit_details[First Listed], "<" & $Q$2, unit_details[Beds], 2, unit_details[Property Name], B82 ) - COUNTIFS( unit_details[First Listed], ">=" & ($Q$2 - 14), unit_details[First Listed], "<=" & ($Q$2 - 7), unit_details[Beds], 2, unit_details[Property Name], B82 ) -> 0 | M84: =IFERROR(AVERAGEIFS(unit_details[Asking Rent],unit_details[First Listed],">="&($Q$2-7), unit_details[First Listed],"<="&$Q$2, unit_details[Beds],2, unit_details[Property Name],B82),"") | N84: =COUNTIFS(unit_details[Property Name], B82, unit_details[Beds], 2, unit_details[Leased Date], "") -> 9 | O84: =N84-(N84-K84+F84) -> 0 | P84: =IFERROR(AVERAGEIFS(unit_details[Asking Rent],unit_details[Property Name], B82, unit_details[Beds], 2, unit_details[Leased Date], ""),"") -> 1211.1111 | Q84: =IFERROR(N84/SUMIFS(unit_mix_table['# Units],unit_mix_table[Beds],2,unit_mix_table[Property Name],B82),"") -> 1.5
E85: 3 BR | F85: =COUNTIFS(unit_details[Leased Date], ">=" & ($Q$2 - 7), unit_details[Leased Date], "<" & $Q$2, unit_details[Beds], 3, unit_details[Property Name], B82) -> 0 | G85: =COUNTIFS(unit_details[Leased Date], ">=" & ($Q$2 - 7), unit_details[Leased Date], "<" & $Q$2, unit_details[Beds], 3, unit_details[Property Name], B82) - COUNTIFS(unit_details[Leased Date], ">=" & ($Q$2 - 14), unit_details[Leased Date], "<=" & ($Q$2 - 7), unit_details[Beds], 3, unit_details[Property Name], B82) -> 0 | H85: =IFERROR(AVERAGEIFS(unit_details[Asking Rent],unit_details[Leased Date], ">=" & ($Q$2 - 7), unit_details[Leased Date], "<" & $Q$2, unit_details[Beds], 3, unit_details[Property Name], B82),"") | I85: =IFERROR( AVERAGEIFS(unit_details[Asking Rent], unit_details[Leased Date], ">=" & ($Q$2 - 7), unit_details[Leased Date], "<" & $Q$2, unit_details[Beds], 3, unit_details[Property Name], B82) - AVERAGEIFS(unit_details[Asking Rent], unit_details[Leased Date], ">=" & ($Q$2 - 14), unit_details[Leased Date], "<=" & ($Q$2 - 7), unit_details[Beds], 3, unit_details[Property Name], B82), 0) -> 0 | J85: =IFERROR(I85/AVERAGEIFS(unit_details[Asking Rent], unit_details[Leased Date], ">=" & ($Q$2 - 14), unit_details[Leased Date], "<=" & ($Q$2 - 7), unit_details[Beds], 3, unit_details[Property Name], B82),0) -> 0 | K85: =COUNTIFS(unit_details[First Listed], ">=" & ($Q$2 - 7), unit_details[First Listed], "<" & $Q$2, unit_details[Beds], 3, unit_details[Property Name], B82) -> 0 | L85: =COUNTIFS( unit_details[First Listed], ">=" & ($Q$2 - 7), unit_details[First Listed], "<" & $Q$2, unit_details[Beds], 3, unit_details[Property Name], B82 ) - COUNTIFS( unit_details[First Listed], ">=" & ($Q$2 - 14), unit_details[First Listed], "<=" & ($Q$2 - 7), unit_details[Beds], 3, unit_details[Property Name], B82 ) -> 0 | M85: =IFERROR(AVERAGEIFS(unit_details[Asking Rent],unit_details[First Listed],">="&($Q$2-7), unit_details[First Listed],"<="&$Q$2, unit_details[Beds],3, unit_details[Property Name],B82),"") | N85: =COUNTIFS(unit_details[Property Name], B82, unit_details[Beds], 3, unit_details[Leased Date], "") -> 0 | O85: =N85-(N85-K85+F85) -> 0 | P85: =IFERROR(AVERAGEIFS(unit_details[Asking Rent],unit_details[Property Name], B82, unit_details[Beds], 3, unit_details[Leased Date], ""),"") | Q85: =IFERROR(N85/SUMIFS(unit_mix_table['# Units],unit_mix_table[Beds],3,unit_mix_table[Property Name],B82),"")
